Workbook
Name OO: #REF!
Name ProbThreshold: #REF!
Name Rules: #REF!

Sheet TB & MCC Cost Audit 2020-Curren
A1: Open
L2: Budget | P2: Actual
L3: Revenue | M3: COGS | N3: Gross Profit | P3: Revenue | Q3: COGS | W3: COGS | Z3: Gross Profit
A4: Project | B4: Opportunity | C4: Type | D4: Year | E4: Month | F4: Invoice # | G4: Item Number | H4: GL Account | I4: Size | J4: Size Description | K4: Item Description | L4: Budget Revenue | M4: Budget Cost | N4: Budget GP $ | O4: Budget GP% | P4: Actual Revenue | Q4: WO # | R4: Labor Hrs | S4: Labor/OH $ | T4: Exp Rpts | U4: Material | V4: Shipping | W4: Total Actual Cost | X4: Actual Lab/OH Rate | Y4: Actual Material % | Z4: Actual GP $ | AA4: Actual GP % | AB4: B vs A $ | AC4: Variance | AD4: Comments
A5: Dekalb | C5: TBEN | D5: 2020 | E5: 43889 | F5: 160107 | G5: 400240TB | I5: 1 | J5: TB Small | K5: 2400 STD TB | L5: =285779-1 -> 285778 | M5: =L5*(1-O5) -> 128600.1 | N5: =L5-M5 -> 157177.9 | O5: =1-0.45 -> 0.55 | P5: 100126.28 | Q5: 554 | R5: =29.5+19.5 -> 49 | S5: =1203.26+509.4 -> 1712.66 | T5: 0 | U5: 22484.52 | W5: =SUM(S5:V5) -> 24197.18 | X5: =IFERROR(S5/R5,"") -> 34.952245 | Y5: =U5/P5 -> 0.22456162 | Z5: =P5-W5 -> 75929.1 | AA5: =Z5/P5 -> 0.75833338
A6: Dekalb | C6: TBEN | D6: 2020 | E6: 43889 | F6: 160107 | G6: 400247TB | I6: 1 | J6: TB Small | K6: 2410 ADV TB | L6: 0 | M6: =L6*(1-O6) -> 0 | N6: =L6-M6 -> 0 | O6: =1-0.45 -> 0.55 | P6: 126153.56 | Q6: 731 | R6: =24.5+23 -> 47.5 | S6: =1215.4+547.03 -> 1762.43 | T6: 0 | U6: 29128.1 | W6: =SUM(S6:V6) -> 30890.53 | X6: =IFERROR(S6/R6,"") -> 37.103789 | Y6: =U6/P6 -> 0.230894 | Z6: =P6-W6 -> 95263.03 | AA6: =Z6/P6 -> 0.75513549
A7: Dekalb | C7: TBEN | D7: 2020 | E7: 43889 | F7: 160107 | G7: 220100119 | K7: Tank Duplex 100 Gal | L7: 0 | M7: =L7*(1-O7) -> 0 | N7: =L7-M7 -> 0 | O7: =1-0.45 -> 0.55 | P7: 9800 | Q7: 881 | R7: 0 | S7: 0 | T7: 0 | U7: 10992.08 | W7: =SUM(S7:V7) -> 10992.08 | X7: =IFERROR(S7/R7,"") | Y7: =U7/P7 -> 1.1216408 | Z7: =P7-W7 -> -1192.08 | AA7: =Z7/P7 -> -0.12164082
A8: Dekalb | C8: TBEN | D8: 2020 | E8: 43889 | F8: 160107 | G8: TBRECIRC | K8: Test Bench Recir System | L8: 0 | M8: =L8*(1-O8) -> 0 | N8: =L8-M8 -> 0 | O8: =1-0.45 -> 0.55 | P8: 63250.96 | Q8: 556 | R8: =6.5+25+12.5 -> 44 | S8: =1018.16+416.14 -> 1434.3 | T8: 0 | U8: 17372.69 | W8: =SUM(S8:V8) -> 18806.99 | X8: =IFERROR(S8/R8,"") -> 32.597727 | Y8: =U8/P8 -> 0.27466287 | Z8: =P8-W8 -> 44443.97 | AA8: =Z8/P8 -> 0.7026608
A9: Dekalb | C9: TBEN | D9: 2020 | E9: 43889 | F9: 160107 | G9: 210500119 | K9: Tank - Single - 500 Gallon - A | L9: 0 | M9: =L9*(1-O9) -> 0 | N9: =L9-M9 -> 0 | O9: =1-0.45 -> 0.55 | P9: 19018 | Q9: 882 | R9: 0 | S9: 0 | T9: 0 | U9: 5056.01 | W9: =SUM(S9:V9) -> 5056.01 | X9: =IFERROR(S9/R9,"") | Y9: =U9/P9 -> 0.26585393 | Z9: =P9-W9 -> 13961.99 | AA9: =Z9/P9 -> 0.73414607 | AB9: =M9-W9 -> -5056.01 | AC9: =AA9-O9 -> 0.18414607
A10: Dekalb | C10: TBIN | D10: 2020 | E10: 43889 | F10: 160107 | G10: 516121129 | K10: Test Bench Installation & Trai | L10: 29525 | M10: =L10*(1-O10) -> 14762.5 | N10: =L10-M10 -> 14762.5 | O10: =1-0.5 -> 0.5 | P10: 29525 | Q10: 884 | R10: 165 | S10: =5100.15+2295.15 -> 7395.3 | T10: 5097.02 | U10: 3533.88 | W10: =SUM(S10:V10) -> 16026.2 | X10: =IFERROR(S10/R10,"") -> 44.82 | Y10: =U10/P10 -> 0.11969111 | Z10: =P10-W10 -> 13498.8 | AA10: =Z10/P10 -> 0.45719898 | AB10: =M10-W10 -> -1263.7 | AC10: =AA10-O10 -> -0.042801016
A11: Dekalb | C11: M3IN | D11: 2020 | E11: 43889 | F11: 160107 | G11: /711420120 | K11: M3 Enterprise Software (Annual | L11: 52528 | M11: =L11*(1-O11) -> 1050.56 | N11: =L11-M11 -> 51477.44 | O11: =1-0.02 -> 0.98 | P11: 19958 | W11: =SUM(S11:V11) -> 0 | X11: =IFERROR(S11/R11,"") | Y11: =U11/P11 -> 0 | Z11: =P11-W11 -> 19958 | AA11: =Z11/P11 -> 1 | AB11: =M11-W11 -> 1050.56 | AC11: =AA11-O11 -> 0.02
A12: Dekalb | C12: M3IN | D12: 2020 | E12: 43889 | F12: 160107 | G12: 616420129 | K12: M3 Enterprise Software Install | L12: 10000 | M12: =L12*(1-O12) -> 5290 | N12: =L12-M12 -> 4710 | O12: =1-0.529 -> 0.471 | P12: 10000 | Q12: 885 | R12: 33.5 | S12: =1035.49+465.99 -> 1501.48 | T12: 2058.91 | U12: 3320.38 | W12: =SUM(S12:V12) -> 6880.77 | X12: =IFERROR(S12/R12,"") -> 44.820299 | Y12: =U12/P12 -> 0.332038 | Z12: =P12-W12 -> 3119.23 | AA12: =Z12/P12 -> 0.311923 | AB12: =M12-W12 -> -1590.77 | AC12: =AA12-O12 -> -0.159077
D13: 2020 | E13: 43889 | X13: =IFERROR(S13/R13,"")
A14: Dekalb | C14: Rev Total | D14: 2020 | E14: 43889 | L14: =SUM(L5:L13) -> 377831 | M14: =SUM(M5:M13) -> 149703.16 | N14: =SUM(N5:N13) -> 228127.84 | O14: =((P5*O5)+(P6*O6)+(P7*O7)+(P8*O8)+(P9*O9)+(P10*O10))/P14 -> 0.50248375 | P14: =SUM(P5:P13) -> 377831.8 | R14: =SUM(R5:R13) -> 339 | S14: =SUM(S5:S13) -> 13806.17 | T14: =SUM(T5:T13) -> 7155.93 | U14: =SUM(U5:U13) -> 91887.66 | W14: =SUM(W5:W12) -> 112849.76 | X14: =IFERROR(S14/R14,"") -> 40.726165 | Y14: =U14/P14 -> 0.24319726 | Z14: =P14-W14 -> 264982.04 | AA14: =Z14/P14 -> 0.70132276 | AB14: =M14-W14 -> 36853.4 | AC14: =AA14-O14 -> 0.19883901
A15: Dekalb | C15: SCH | D15: 2020 | E15: 43889 | F15: 160107 | G15: 997080WH | K15: Shipping/Crating/Handling | L15: 0 | M15: 0 | N15: 0 | O15: 0 | P15: 5500 | Q15: 883 | R15: 30.5 | S15: =838.75+377.59 -> 1216.34 | T15: 2289 | U15: 400 | W15: 3905.34 | X15: =IFERROR(S15/R15,"") -> 39.88 | Y15: =U15/P15 -> 0.072727273 | Z15: =P15-W15 -> 1594.66 | AA15: =Z15/P15 -> 0.28993818 | AB15: =M15-W15 -> -3905.34 | AC15: =AA15-O15 -> 0.28993818
A16: Dekalb | C16: DRM3 | D16: 2020 | E16: 43889 | F16: 160107 | G16: /M3RC | K16: M3 Software License Renewal- C | P16: =21821+24003+26404+29044 -> 101272 | X16: =IFERROR(S16/R16,"") | AB16: =M16-W16 -> 0 | AC16: =AA16-O16 -> 0
A17: Dekalb | C17: DRMCC | D17: 2020 | E17: 43889 | F17: 160107 | G17: /811000010 | I17: =MID(G17,3,1) -> 1 | J17: Small/Medium | K17: MCC Annual 2020 | L17: =P17 -> 9680 | M17: =L17*0.3 -> 2904 | N17: =L17-M17 -> 6776 | O17: =N17/L17 -> 0.7 | P17: 9680 | W17: =SUM(S17:V17) -> 0 | X17: =IFERROR(S17/R17,"") | Z17: =P17-W17 -> 9680 | AA17: =Z17/P17 -> 1 | AB17: =M17-W17 -> 2904 | AC17: =AA17-O17 -> 0.3
D18: 2020 | E18: 43889
A19: Dekalb | C19: Inv Total | D19: 2020 | E19: 43889 | P19: =SUM(P14:P17) -> 494283.8 | R19: =SUM(R14:R17) -> 369.5 | S19: =SUM(S14:S17) -> 15022.51 | T19: =SUM(T14:T17) -> 9444.93 | U19: =SUM(U14:U17) -> 92287.66 | W19: =SUM(S19:U19) -> 116755.1 | X19: =IFERROR(S19/R19,"") -> 40.656319 | AB19: =M19-W19 -> -116755.1 | AC19: =AA19-O19 -> 0
A20: Dekalb | C20: Total TBEN | D20: 2020 | E20: 43889 | L20: =L5+L6+L7+L8+L9 -> 285778 | M20: =M5+M6+M7+M8+M9 -> 128600.1 | N20: =N5+N6+N7+N8+N9 -> 157177.9 | O20: =((P5*O5)+(P6*O6)+(P7*O7)+(P8*O8)+(P9*O9))/P20 -> 0.55 | P20: =P5+P6+P7+P8+P9 -> 318348.8 | R20: =R5+R6+R7+R8+R9 -> 140.5 | S20: =S5+S6+S7+S8+S9 -> 4909.39 | T20: =T5+T6+T7+T8+T9 -> 0 | U20: =U5+U6+U7+U8+U9 -> 85033.4 | W20: =W5+W6+W7+W8+W9 -> 89942.79 | X20: =IFERROR(S20/R20,"") -> 34.942278 | Y20: =U20/P20 -> 0.26710765 | Z20: =P20-W20 -> 228406.01 | AA20: =Z20/P20 -> 0.71747093 | AB20: =M20-W20 -> 38657.31 | AC20: =AA20-O20 -> 0.16747093
A22: Coos Bay | C22: TBEN | D22: 2020 | E22: 43889 | F22: 160104 | G22: 123051220 | I22: =MID(G22,2,1) -> 2 | J22: TB Medium | K22: TB New Medium Series 3-510 Mun200 | O22: =1-0.45 -> 0.55 | P22: 44635 | Q22: 831 | R22: =13+14 -> 27 | S22: =688.08+309.7 -> 997.78 | U22: 12206.78 | W22: =SUM(S22:V22) -> 13204.56 | X22: =IFERROR(S22/R22,"") -> 36.954815 | Y22: =U22/P22 -> 0.27348 | Z22: =P22-W22 -> 31430.44 | AA22: =Z22/P22 -> 0.70416579 | AB22: =M22-W22 -> -13204.56 | AC22: =AA22-O22 -> 0.15416579
A23: Coos Bay | C23: TBEN | D23: 2020 | E23: 43889 | F23: 160104 | G23: 220100210 | K23: Tank Duplex 100 Gal | O23: =1-0.45 -> 0.55 | P23: 6600 | Q23: 832 | R23: 2 | S23: =54.08+24.34 -> 78.42 | U23: 4539.48 | W23: =SUM(S23:V23) -> 4617.9 | X23: =IFERROR(S23/R23,"") -> 39.21 | Y23: =U23/P23 -> 0.6878 | Z23: =P23-W23 -> 1982.1 | AA23: =Z23/P23 -> 0.30031818 | AB23: =M23-W23 -> -4617.9 | AC23: =AA23-O23 -> -0.24968182
A24: Coos Bay | C24: TBIN | D24: 2020 | E24: 43889 | F24: 160104 | G24: 523051120 | K24: TB Install & Training | O24: =1-0.45 -> 0.55 | P24: 15965 | Q24: 833 | R24: 41 | S24: =1267.31+570.31 -> 1837.62 | T24: 2158.97 | W24: =SUM(S24:V24) -> 3996.59 | X24: =IFERROR(S24/R24,"") -> 44.82 | Y24: =U24/P24 -> 0 | Z24: =P24-W24 -> 11968.41 | AA24: =Z24/P24 -> 0.74966552 | AB24: =M24-W24 -> -3996.59 | AC24: =AA24-O24 -> 0.19966552
D25: 2020 | E25: 43889 | X25: =IFERROR(S25/R25,"")
A26: Coos Bay | C26: Rev Total | D26: 2020 | E26: 43889 | F26: 160104 | O26: =((P22*O22)+(P23*O23)+(P24*O24))/P26 -> 0.55 | P26: =SUM(P22:P25) -> 67200 | R26: =SUM(R22:R25) -> 70 | S26: =SUM(S22:S25) -> 2913.82 | T26: =SUM(T22:T25) -> 2158.97 | U26: =SUM(U22:U25) -> 16746.26 | W26: =SUM(W22:W25) -> 21819.05 | X26: =IFERROR(S26/R26,"") -> 41.626 | Y26: =U26/P26 -> 0.2492003 | Z26: =P26-W26 -> 45380.95 | AA26: =Z26/P26 -> 0.67531176 | AB26: =M26-W26 -> -21819.05 | AC26: =AA26-O26 -> 0.12531176
A27: Coos Bay | C27: SCH | D27: 2020 | E27: 43889 | F27: 160104 | G27: 997080WH | K27: Shipping / Crating / Handling | O27: 0 | P27: 6500 | Q27: 834 | R27: 8 | S27: =220+99.04 -> 319.04 | T27: 1448.35 | U27: 269.65 | W27: 2037.04 | X27: =IFERROR(S27/R27,"") -> 39.88 | Y27: =U27/P27 -> 0.041484615 | Z27: =P27-W27 -> 4462.96 | AA27: =Z27/P27 -> 0.68660923 | AB27: =M27-W27 -> -2037.04 | AC27: =AA27-O27 -> 0.68660923
D28: 2020 | E28: 43889 | X28: =IFERROR(S28/R28,"")
A29: Coos Bay | C29: Inv Total | D29: 2020 | E29: 43889 | P29: =SUM(P26:P27) -> 73700 | R29: =SUM(R26:R27) -> 78 | S29: =SUM(S26:S27) -> 3232.86 | T29: =SUM(T26:T27) -> 3607.32 | U29: =SUM(U26:U27) -> 17015.91 | W29: =SUM(S29:U29) -> 23856.09 | X29: =IFERROR(S29/R29,"") -> 41.446923 | AB29: =M29-W29 -> -23856.09 | AC29: =AA29-O29 -> 0
A30: Coos Bay | C30: Total TBEN | D30: 2020 | E30: 43889 | O30: =((P22*O22)+(P23*O23)+(P24*O24))/P30 -> 0.55 | P30: =P22+P23+P24 -> 67200 | R30: =R22+R23+R24 -> 70 | S30: =S22+S23+S24 -> 2913.82 | T30: =T22+T23+T24 -> 2158.97 | U30: =U22+U23+U24 -> 16746.26 | W30: =W22+W23+W24 -> 21819.05 | X30: =IFERROR(S30/R30,"") -> 41.626 | Y30: =U30/P30 -> 0.2492003 | Z30: =P30-W30 -> 45380.95 | AA30: =Z30/P30 -> 0.67531176 | AB30: =M30-W30 -> -21819.05 | AC30: =AA30-O30 -> 0.12531176
A32: White House | C32: TBEN | D32: 2020 | E32: 43982 | F32: 160594 | G32: 125100120 | I32: =MID(G32,2,1) -> 2 | J32: TB Medium | K32: TB New Med Series 5 | O32: =1-0.45 -> 0.55 | P32: 110058.37 | Q32: 886 | R32: =14+52 -> 66 | S32: =1766.09+794.88 -> 2560.97 | U32: 27639.17 | W32: =SUM(S32:V32) -> 30200.14 | X32: =IFERROR(S32/R32,"") -> 38.802576 | Y32: =U32/P32 -> 0.25113192 | Z32: =P32-W32 -> 79858.23 | AA32: =Z32/P32 -> 0.72559888 | AB32: =M32-W32 -> -30200.14 | AC32: =AA32-O32 -> 0.17559888
A33: White House | C33: TBEN | D33: 2020 | E33: 43982 | F33: 160594 | G33: 220100110 | K33: Tank New Duplex 100 Gal | O33: =1-0.45 -> 0.55 | P33: 6600 | Q33: 887 | U33: 7885.36 | W33: =SUM(S33:V33) -> 7885.36 | X33: =IFERROR(S33/R33,"") | Y33: =U33/P33 -> 1.1947515 | Z33: =P33-W33 -> -1285.36 | AA33: =Z33/P33 -> -0.19475152 | AB33: =M33-W33 -> -7885.36 | AC33: =AA33-O33 -> -0.74475152
A34: White House | C34: TBEN | D34: 2020 | E34: 43982 | F34: 160594 | G34: 210500110 | K34: Tank New Single 500 Gal | O34: =1-0.45 -> 0.55 | P34: 15000 | Q34: 888 | U34: 5028.47 | W34: =SUM(S34:V34) -> 5028.47 | X34: =IFERROR(S34/R34,"") | Y34: =U34/P34 -> 0.33523133 | Z34: =P34-W34 -> 9971.53 | AA34: =Z34/P34 -> 0.66476867 | AB34: =M34-W34 -> -5028.47 | AC34: =AA34-O34 -> 0.11476867
A35: White House | C35: TBEN | D35: 2020 | E35: 43982 | F35: 160594 | G35: 210010110 | K35: Tank New Single 10 Gal | O35: =1-0.45 -> 0.55 | P35: 8760 | Q35: 889 | R35: 1 | S35: =27.04+12.17 -> 39.21 | U35: 1361.01 | W35: =SUM(S35:V35) -> 1400.22 | X35: =IFERROR(S35/R35,"") -> 39.21 | Y35: =U35/P35 -> 0.15536644 | Z35: =P35-W35 -> 7359.78 | AA35: =Z35/P35 -> 0.84015753 | AB35: =M35-W35 -> -1400.22 | AC35: =AA35-O35 -> 0.29015753
A36: White House | C36: TBIN | D36: 2020 | E36: 43982 | F36: 160594 | G36: 525100120 | K36: TB Install & Training | O36: =1-0.45 -> 0.55 | P36: 14920 | Q36: 890 | R36: 100.75 | S36: =3114.21+1401.46 -> 4515.67 | T36: 6342.27 | U36: 1608.3 | W36: =SUM(S36:V36) -> 12466.24 | X36: =IFERROR(S36/R36,"") -> 44.820546 | Y36: =U36/P36 -> 0.10779491 | Z36: =P36-W36 -> 2453.76 | AA36: =Z36/P36 -> 0.16446113 | AB36: =M36-W36 -> -12466.24 | AC36: =AA36-O36 -> -0.38553887
A37: White House | C37: M3IN | D37: 2020 | E37: 43982 | F37: 160594 | G37: 626520120 | K37: M3 Software install & Train | O37: =1-0.529 -> 0.471 | P37: 6655 | Q37: 891 | R37: 16 | S37: =628.48+282.88 -> 911.36 | T37: 1351.34 | U37: 2322.74 | W37: =SUM(S37:V37) -> 4585.44 | X37: =IFERROR(S37/R37,"") -> 56.96 | Y37: =U37/P37 -> 0.34902179 | Z37: =P37-W37 -> 2069.56 | AA37: =Z37/P37 -> 0.31097821 | AB37: =M37-W37 -> -4585.44 | AC37: =AA37-O37 -> -0.16002179
D38: 2020 | E38: 43982 | X38: =IFERROR(S38/R38,"")
A39: White House | C39: Rev Total | D39: 2020 | E39: 43982 | O39: =((P32*O32)+(P33*O33)+(P34*O34)+(P35*O35))/P39 -> 0.47674855 | P39: =SUM(P32:P37) -> 161993.37 | R39: =SUM(R32:R37) -> 183.75 | S39: =SUM(S32:S37) -> 8027.21 | T39: =SUM(T32:T37) -> 7693.61 | U39: =SUM(U32:U37) -> 45845.05 | W39: =SUM(W32:W38) -> 61565.87 | X39: =IFERROR(S39/R39,"") -> 43.685497 | Y39: =U39/P39 -> 0.28300572 | Z39: =P39-W39 -> 100427.5 | AA39: =Z39/P39 -> 0.61994821 | AB39: =M39-W39 -> -61565.87 | AC39: =AA39-O39 -> 0.14319967
A40: White House | C40: SCH | D40: 2020 | E40: 43982 | F40: 160594 | G40: 997080WH | K40: Shipping / Crating / Handling | O40: 0 | P40: 5210 | Q40: 892 | R40: 18 | S40: =495+222.84 -> 717.84 | T40: 2509.92 | U40: 645.13 | W40: =SUM(S40:V40) -> 3872.89 | X40: =IFERROR(S40/R40,"") -> 39.88 | Y40: =U40/P40 -> 0.12382534 | Z40: =P40-W40 -> 1337.11 | AA40: =Z40/P40 -> 0.25664299 | AB40: =M40-W40 -> -3872.89 | AC40: =AA40-O40 -> 0.25664299
A41: White House | C41: DRM3 | D41: 2020 | E41: 43982 | F41: 160594 | G41: /721520120 | P41: 9979 | X41: =IFERROR(S41/R41,"") | AB41: =M41-W41 -> 0 | AC41: =AA41-O41 -> 0
D42: 2020 | E42: 43982 | X42: =IFERROR(S42/R42,"")
A43: White House | C43: Inv Total | D43: 2020 | E43: 43982 | P43: =SUM(P39:P42) -> 177182.37 | R43: =SUM(R39:R42) -> 201.75 | S43: =SUM(S39:S42) -> 8745.05 | T43: =SUM(T39:T42) -> 10203.53 | U43: =SUM(U39:U42) -> 46490.18 | W43: =SUM(S43:U43) -> 65438.76 | X43: =IFERROR(S43/R43,"") -> 43.345973 | AB43: =M43-W43 -> -65438.76 | AC43: =AA43-O43 -> 0
A44: White House | C44: Total TBEN | D44: 2020 | E44: 43982 | O44: =((P32*O32)+(P33*O33)+(P34*O34)+(P35*O35))/P44 -> 0.55 | P44: =P32+P33+P34+P35 -> 140418.37 | R44: =R32+R33+R34+R35 -> 67 | S44: =S32+S33+S34+S35 -> 2600.18 | T44: =T32+T33+T34+T35 -> 0 | U44: =U32+U33+U34+U35 -> 41914.01 | W44: =W32+W33+W34+W35 -> 44514.19 | X44: =IFERROR(S44/R44,"") -> 38.808657 | Y44: =U44/P44 -> 0.29849378 | Z44: =P44-W44 -> 95904.18 | AA44: =Z44/P44 -> 0.68298884 | AB44: =M44-W44 -> -44514.19 | AC44: =AA44-O44 -> 0.13298884
A46: St. Paul | C46: TBEN | D46: 2020 | E46: 43982 | F46: 160500 | G46: 925000310 | K46: TB Med Series 5000 St | O46: =1-0.45 -> 0.55 | P46: 22074 | Q46: 901 | R46: 8 | S46: =192.32+86.56 -> 278.88 | U46: 16593.88 | W46: =SUM(S46:V46) -> 16872.76 | X46: =IFERROR(S46/R46,"") -> 34.86 | Y46: =U46/P46 -> 0.7517387 | Z46: =P46-W46 -> 5201.24 | AA46: =Z46/P46 -> 0.23562743 | AB46: =M46-W46 -> -16872.76 | AC46: =AA46-O46 -> -0.31437257
A47: St. Paul | C47: TBIN | D47: 2020 | E47: 43982 | F47: 160500 | G47: 525000210 | K47: Test Bench Installation & Training | O47: =1-0.45 -> 0.55 | P47: 7860 | Q47: 902 | R47: 92.5 | S47: =2859.22+1286.72 -> 4145.94 | T47: 2314.84 | U47: 1545.15 | W47: =SUM(S47:V47) -> 8005.93 | X47: =IFERROR(S47/R47,"") -> 44.820973 | Y47: =U47/P47 -> 0.19658397 | Z47: =P47-W47 -> -145.93 | AA47: =Z47/P47 -> -0.018566158 | AB47: =M47-W47 -> -8005.93 | AC47: =AA47-O47 -> -0.56856616
A48: St. Paul | C48: TBEN | D48: 2020 | E48: 43982 | F48: 160500 | G48: 220100110 | K48: Tank New Duplex 100 Gal | O48: =1-0.45 -> 0.55 | P48: 6600 | Q48: 903 | U48: 7996.56 | W48: =SUM(S48:V48) -> 7996.56 | X48: =IFERROR(S48/R48,"") | Y48: =U48/P48 -> 1.2116 | Z48: =P48-W48 -> -1396.56 | AA48: =Z48/P48 -> -0.2116 | AB48: =M48-W48 -> -7996.56 | AC48: =AA48-O48 -> -0.7616
A49: St. Paul | C49: TBEN | D49: 2020 | E49: 43982 | F49: 160500 | G49: 210500110 | K49: Tank New 500 Gal | O49: =1-0.45 -> 0.55 | P49: 15000 | Q49: 904 | U49: 6055.97 | W49: =SUM(S49:V49) -> 6055.97 | X49: =IFERROR(S49/R49,"") | Y49: =U49/P49 -> 0.40373133 | Z49: =P49-W49 -> 8944.03 | AA49: =Z49/P49 -> 0.59626867 | AB49: =M49-W49 -> -6055.97 | AC49: =AA49-O49 -> 0.046268667
A50: St. Paul | C50: TBEN | D50: 2020 | E50: 43982 | F50: 160500 | G50: 910100310 | K50: Equip Sm Series 1000 Sta | O50: =1-0.45 -> 0.55 | P50: 42924 | Q50: 905 | R50: 5 | S50: =120.2+54.1 -> 174.3 | U50: 8995.19 | W50: =SUM(S50:V50) -> 9169.49 | X50: =IFERROR(S50/R50,"") -> 34.86 | Y50: =U50/P50 -> 0.20956085 | Z50: =P50-W50 -> 33754.51 | AA50: =Z50/P50 -> 0.78637848 | AB50: =M50-W50 -> -9169.49 | AC50: =AA50-O50 -> 0.23637848
A51: St. Paul | C51: TBIN | D51: 2020 | E51: 43982 | F51: 160500 | G51: 510100210 | K51: Test Bench Installation & Training | O51: =1-0.45 -> 0.55 | P51: 7840 | Q51: 906 | R51: 77.75 | S51: =2403.29+1081.54 -> 3484.83 | T51: 2171 | U51: 767.23 | W51: =SUM(S51:V51) -> 6423.06 | X51: =IFERROR(S51/R51,"") -> 44.820965 | Y51: =U51/P51 -> 0.097860969 | Z51: =P51-W51 -> 1416.94 | AA51: =Z51/P51 -> 0.18073214 | AB51: =M51-W51 -> -6423.06 | AC51: =AA51-O51 -> -0.36926786
A52: St. Paul | C52: TBEN | D52: 2020 | E52: 43982 | F52: 160500 | G52: 940000310 | K52: TB Large Bench | O52: =1-0.45 -> 0.55 | P52: 42924 | Q52: 907 | R52: 5.5 | S52: =132.22+59.51 -> 191.73 | U52: 9545.98 | W52: =SUM(S52:V52) -> 9737.71 | X52: =IFERROR(S52/R52,"") -> 34.86 | Y52: =U52/P52 -> 0.2223926 | Z52: =P52-W52 -> 33186.29 | AA52: =Z52/P52 -> 0.77314067 | AB52: =M52-W52 -> -9737.71 | AC52: =AA52-O52 -> 0.22314067
A53: St. Paul | C53: TBIN | D53: 2020 | E53: 43982 | F53: 160500 | G53: 540000210 | K53: Test Bench Installation & Training | O53: =1-0.45 -> 0.55 | P53: 7840 | Q53: 908 | R53: 146.25 | S53: =4520.62+2034.37 -> 6554.99 | T53: 2296.26 | U53: 1912.12 | W53: =SUM(S53:V53) -> 10763.37 | X53: =IFERROR(S53/R53,"") -> 44.820444 | Y53: =U53/P53 -> 0.24389286 | Z53: =P53-W53 -> -2923.37 | AA53: =Z53/P53 -> -0.37287883 | AB53: =M53-W53 -> -10763.37 | AC53: =AA53-O53 -> -0.92287883
A54: St. Paul | C54: M3IN | D54: 2020 | E54: 43982 | F54: 160500 | G54: 616420120 | K54: M3 Software Installation & Training | O54: =1-0.45 -> 0.55 | P54: 6655 | Q54: 909 | R54: 16 | S54: =628.48+282.88 -> 911.36 | T54: 960 | U54: 1045.75 | W54: =SUM(S54:V54) -> 2917.11 | X54: =IFERROR(S54/R54,"") -> 56.96 | Y54: =U54/P54 -> 0.15713749 | Z54: =P54-W54 -> 3737.89 | AA54: =Z54/P54 -> 0.56166642 | AB54: =M54-W54 -> -2917.11 | AC54: =AA54-O54 -> 0.011666416
A55: St. Paul | C55: M3IN | D55: 2020 | E55: 43982 | F55: 160500 | G55: 626420120 | K55: M3 Software Installation & Training | O55: =1-0.45 -> 0.55 | P55: 6655 | Q55: 910 | R55: 16 | S55: =628.48+282.88 -> 911.36 | T55: 960 | U55: 1045.76 | W55: =SUM(S55:V55) -> 2917.12 | X55: =IFERROR(S55/R55,"") -> 56.96 | Y55: =U55/P55 -> 0.15713899 | Z55: =P55-W55 -> 3737.88 | AA55: =Z55/P55 -> 0.56166491 | AB55: =M55-W55 -> -2917.12 | AC55: =AA55-O55 -> 0.011664914
A56: St. Paul | C56: M3IN | D56: 2020 | E56: 43982 | F56: 160500 | G56: 646620120 | K56: M3 Software Installation & Training | O56: =1-0.45 -> 0.55 | P56: 19965 | Q56: 911 | R56: 16 | S56: =628.48+282.88 -> 911.36 | T56: 998.41 | U56: 2399.45 | W56: =SUM(S56:V56) -> 4309.22 | X56: =IFERROR(S56/R56,"") -> 56.96 | Y56: =U56/P56 -> 0.12018282 | Z56: =P56-W56 -> 15655.78 | AA56: =Z56/P56 -> 0.78416128 | AB56: =M56-W56 -> -4309.22 | AC56: =AA56-O56 -> 0.23416128
D57: 2020 | E57: 43982 | X57: =IFERROR(S57/R57,"")
A58: St. Paul | C58: Rev Total | D58: 2020 | E58: 43982 | F58: 160500 | O58: =((P46*O46)+(P48*O48)+(P49*O49)+(P50*O50)+(P52*O52))/P58 -> 0.38230249 | P58: =SUM(P46:P56) -> 186337 | R58: =SUM(R46:R56) -> 383 | S58: =SUM(S46:S52) -> 8275.68 | T58: =SUM(T46:T52) -> 4485.84 | U58: =SUM(U46:U56) -> 57903.04 | W58: =SUM(W46:W52) -> 64261.48 | X58: =IFERROR(S58/R58,"") -> 21.60752 | Y58: =U58/P58 -> 0.31074365 | Z58: =P58-W58 -> 122075.52 | AA58: =Z58/P58 -> 0.65513301 | AB58: =M58-W58 -> -64261.48 | AC58: =AA58-O58 -> 0.27283052
A59: St. Paul | C59: SCH | D59: 2020 | E59: 43982 | F59: 160500 | G59: 997080WH | K59: Shipping / Crating / Handling | O59: 0 | P59: 7860 | Q59: 912 | R59: 46.5 | S59: =1278.75+575.67 -> 1854.42 | T59: 5091.62 | U59: 806.07 | W59: =SUM(S59:U59) -> 7752.11 | X59: =IFERROR(S59/R59,"") -> 39.88 | Y59: =U59/P59 -> 0.10255344 | Z59: =P59-W59 -> 107.89 | AA59: =Z59/P59 -> 0.013726463 | AB59: =M59-W59 -> -7752.11 | AC59: =AA59-O59 -> 0.013726463
A60: St. Paul | C60: DRM3 | D60: 2020 | E60: 43982 | F60: 160500 | G60: /711420120 | K60: M3 Enterprise Software | P60: 17194 | X60: =IFERROR(S60/R60,"") | AB60: =M60-W60 -> 0 | AC60: =AA60-O60 -> 0
A61: St. Paul | C61: DRM3 | D61: 2020 | E61: 43982 | F61: 160500 | G61: /721420120 | K61: M3 Enterprise Software | P61: 17194 | X61: =IFERROR(S61/R61,"")
A62: St. Paul | C62: DRM3 | D62: 2020 | E62: 43982 | F62: 160500 | G62: /741620120 | K62: M3 Enterprise Software | P62: 15543 | X62: =IFERROR(S62/R62,"")
A63: St. Paul | C63: DRMCC | D63: 2020 | E63: 43982 | F63: 160500 | G63: /811003010 | I63: =MID(G63,3,1) -> 1 | J63: =IF(I63="1","Small/Medium","Large") -> Small/Medium | K63: MCC Annual 2020 | L63: =P63 -> 9680 | M63: =L63*0.3 -> 2904 | N63: =L63-M63 -> 6776 | O63: =N63/L63 -> 0.7 | P63: 9680 | W63: =SUM(S63:V63) -> 0 | X63: =IFERROR(S63/R63,"") | Z63: =P63-W63 -> 9680 | AA63: =Z63/P63 -> 1 | AB63: =M63-W63 -> 2904 | AC63: =AA63-O63 -> 0.3
A64: St. Paul | C64: DRMCC | D64: 2020 | E64: 43982 | F64: 160500 | G64: /821003010 | I64: =MID(G64,3,1) -> 2 | J64: =IF(I64="1","Small/Medium","Large") -> Large | K64: MCC Annual 2020 | L64: =P64 -> 9680 | M64: =L64*0.3 -> 2904 | N64: =L64-M64 -> 6776 | O64: =N64/L64 -> 0.7 | P64: 9680 | W64: =SUM(S64:V64) -> 0 | X64: =IFERROR(S64/R64,"") | Z64: =P64-W64 -> 9680 | AA64: =Z64/P64 -> 1 | AB64: =M64-W64 -> 2904 | AC64: =AA64-O64 -> 0.3
A65: St. Paul | C65: Inv Total | D65: 2020 | E65: 43982 | P65: =SUM(P58:P64) -> 263488 | R65: =SUM(R58:R64) -> 429.5 | S65: =SUM(S58:S64) -> 10130.1 | T65: =SUM(T58:T64) -> 9577.46 | U65: =SUM(U58:U64) -> 58709.11 | W65: =SUM(S65:U65) -> 78416.67 | X65: =IFERROR(S65/R65,"") -> 23.585797 | AB65: =M65-W65 -> -78416.67 | AC65: =AA65-O65 -> 0
A66: St. Paul | C66: Total TBEN | D66: 2020 | E66: 43982 | O66: =((P45*O45)+(P46*O46)+(P48*O48)+(P49*O49)+(P50*O50)+(P52*O52))/P66 -> 0.55 | P66: =P46+P48+P49+P50+P52 -> 129522 | R66: =R46+R48+R49+R50+R52 -> 18.5 | S66: =S46+S48+S49+S50+S52 -> 644.91 | T66: =T46+T48+T49+T50+T52 -> 0 | U66: =U46+U48+U49+U50+U52 -> 49187.58 | W66: =W46+W48+W49+W50+W52 -> 49832.49 | X66: =IFERROR(S66/R66,"") -> 34.86 | Y66: =U66/P66 -> 0.37976236 | Z66: =P66-W66 -> 79689.51 | AA66: =Z66/P66 -> 0.61525849 | AB66: =M66-W66 -> -49832.49 | AC66: =AA66-O66 -> 0.065258489
A68: Artesian Resources | C68: M3IN | D68: 2020 | E68: 43982 | F68: 160463 | G68: 616200120 | K68: M3 Software install & Train | O68: =1-0.529 -> 0.471 | P68: 6584.76 | Q68: 921 | R68: 32 | S68: =1256.96+565.76 -> 1822.72 | T68: 718 | W68: =SUM(S68:V68) -> 2540.72 | X68: =IFERROR(S68/R68,"") -> 56.96 | Y68: =U68/P68 -> 0 | Z68: =P68-W68 -> 4044.04 | AA68: =Z68/P68 -> 0.61415146 | AB68: =M68-W68 -> -2540.72 | AC68: =AA68-O68 -> 0.14315146
A69: Artesian Resources | C69: M3IN | D69: 2020 | E69: 43982 | F69: 160463 | G69: 646200120 | K69: M3 Software install & Train | O69: =1-0.529 -> 0.471 | P69: 17535.24 | Q69: 922 | R69: 32 | S69: =1256.96+565.76 -> 1822.72 | T69: 1453.05 | W69: =SUM(S69:V69) -> 3275.77 | X69: =IFERROR(S69/R69,"") -> 56.96 | Y69: =U69/P69 -> 0 | Z69: =P69-W69 -> 14259.47 | AA69: =Z69/P69 -> 0.81318933 | AB69: =M69-W69 -> -3275.77 | AC69: =AA69-O69 -> 0.34218933
A70: Artesian Resources | C70: TBIN | D70: 2020 | E70: 43982 | F70: 160463 | G70: 514121220 | K70: TB Install & Train | O70: =1-0.45 -> 0.55 | P70: 7840 | Q70: 924 | R70: 51.25 | S70: =1584.15+712.9 -> 2297.05 | T70: 784.79 | U70: 1800.99 | W70: =SUM(S70:V70) -> 4882.83 | X70: =IFERROR(S70/R70,"") -> 44.820488 | Y70: =U70/P70 -> 0.22971811 | Z70: =P70-W70 -> 2957.17 | AA70: =Z70/P70 -> 0.37719005 | AB70: =M70-W70 -> -4882.83 | AC70: =AA70-O70 -> -0.17280995
A71: Artesian Resources | C71: TBEN | D71: 2020 | E71: 43982 | F71: 160463 | G71: 910000310 | K71: TB SM Series 2410 Adv | O71: =1-0.45 -> 0.55 | P71: 43674 | Q71: 919 | R71: 8 | S71: =192.32+86.56 -> 278.88 | U71: 8870.52 | W71: =SUM(S71:V71) -> 9149.4 | X71: =IFERROR(S71/R71,"") -> 34.86 | Y71: =U71/P71 -> 0.20310757 | Z71: =P71-W71 -> 34524.6 | AA71: =Z71/P71 -> 0.79050694 | AB71: =M71-W71 -> -9149.4 | AC71: =AA71-O71 -> 0.24050694
A72: Artesian Resources | C72: TBIN | D72: 2020 | E72: 43982 | F72: 160463 | G72: 540000210 | K72: TB Install & Train | O72: =1-0.45 -> 0.55 | P72: 7840 | Q72: 925 | R72: 50 | S72: =1545.51+695.51 -> 2241.02 | T72: 1612.83 | U72: 3217.03 | W72: =SUM(S72:V72) -> 7070.88 | X72: =IFERROR(S72/R72,"") -> 44.8204 | Y72: =U72/P72 -> 0.41033546 | Z72: =P72-W72 -> 769.12 | AA72: =Z72/P72 -> 0.098102041 | AB72: =M72-W72 -> -7070.88 | AC72: =AA72-O72 -> -0.45189796
A73: Artesian Resources | C73: TBEN | D73: 2020 | E73: 43982 | F73: 160463 | G73: 940000310 | K73: TB Large Bench Sta | O73: =1-0.45 -> 0.55 | P73: 43674 | Q73: 920 | S73: 0 | T73: 0 | U73: 9600.87 | W73: =SUM(S73:V73) -> 9600.87 | X73: =IFERROR(S73/R73,"") | Y73: =U73/P73 -> 0.21983033 | Z73: =P73-W73 -> 34073.13 | AA73: =Z73/P73 -> 0.78016967 | AB73: =M73-W73 -> -9600.87 | AC73: =AA73-O73 -> 0.23016967
D74: 2020 | E74: 43982 | X74: =IFERROR(S74/R74,"")
A75: Artesian Resources | C75: Rev Total | D75: 2020 | E75: 43982 | O75: =((P71*O71)+(P73*O73))/P75 -> 0.37783842 | P75: =SUM(P68:P74) -> 127148 | R75: =SUM(R68:R74) -> 173.25 | S75: =SUM(S68:S74) -> 8462.39 | T75: =SUM(T68:T74) -> 4568.67 | U75: =SUM(U68:U74) -> 23489.41 | W75: =SUM(W68:W74) -> 36520.47 | X75: =IFERROR(S75/R75,"") -> 48.844964 | Y75: =U75/P75 -> 0.1847407 | Z75: =P75-W75 -> 90627.53 | AA75: =Z75/P75 -> 0.71277197 | AB75: =M75-W75 -> -36520.47 | AC75: =AA75-O75 -> 0.33493354
A76: Artesian Resources | C76: SCH | D76: 2020 | E76: 43982 | F76: 160463 | G76: 997080WH | K76: Shipping / Crating / Handling | O76: 0 | P76: 6240 | Q76: 923 | R76: 4 | S76: =110+49.52 -> 159.52 | T76: 1036.13 | U76: 254.56 | W76: =SUM(S76:U76) -> 1450.21 | X76: =IFERROR(S76/R76,"") -> 39.88 | Y76: =U76/P76 -> 0.040794872 | Z76: =P76-W76 -> 4789.79 | AA76: =Z76/P76 -> 0.76759455 | AB76: =M76-W76 -> -1450.21 | AC76: =AA76-O76 -> 0.76759455
A77: Artesian Resources | C77: DRM3 | D77: 2020 | E77: 43982 | F77: 160463 | G77: /743200120 | K77: M3 Enterprise Software | P77: 25625.74 | X77: =IFERROR(S77/R77,"") | AB77: =M77-W77 -> 0 | AC77: =AA77-O77 -> 0
A78: Artesian Resources | C78: DRM3 | D78: 2020 | E78: 43982 | F78: 160463 | G78: /713200120 | K78: M3 Enterprise Software | P78: 9602.26 | X78: =IFERROR(S78/R78,"") | AB78: =M78-W78 -> 0 | AC78: =AA78-O78 -> 0
D79: 2020 | E79: 43982 | X79: =IFERROR(S79/R79,"")
A80: Artesian Resources | C80: Inv Total | D80: 2020 | E80: 43982 | P80: =SUM(P75:P79) -> 168616 | R80: =SUM(R75:R79) -> 177.25 | S80: =SUM(S75:S79) -> 8621.91 | T80: =SUM(T75:T79) -> 5604.8 | U80: =SUM(U75:U79) -> 23743.97 | W80: =SUM(S80:U80) -> 37970.68 | X80: =IFERROR(S80/R80,"") -> 48.642652 | Y80: =U80/P80 -> 0.14081683 | Z80: =P80-W80 -> 130645.32 | AA80: =Z80/P80 -> 0.77480975 | AB80: =M80-W80 -> -37970.68 | AC80: =AA80-O80 -> 0.77480975
A81: Artesian Resources | C81: Total TBEN | D81: 2020 | E81: 43982 | O81: =((P71*O71)+(P73*O73))/P81 -> 0.55 | P81: =P71+P73 -> 87348 | R81: =R71+R73 -> 8 | S81: =S71+S73 -> 278.88 | T81: =T71+T73 -> 0 | U81: =U71+U73 -> 18471.39 | W81: =W71+W73 -> 18750.27 | X81: =IFERROR(S81/R81,"") -> 34.86 | Y81: =U81/P81 -> 0.21146895 | Z81: =P81-W81 -> 68597.73 | AA81: =Z81/P81 -> 0.7853383 | AB81: =M81-W81 -> -18750.27 | AC81: =AA81-O81 -> 0.2353383
A83: Folsom | C83: TBEN | D83: 2020 | E83: 43920 | F83: 160339 | G83: 123050120 | I83: =MID(G83,2,1) -> 2 | J83: TB Medium | K83: TB New Medium | O83: =1-0.45 -> 0.55 | P83: 21873 | Q83: 893 | R83: =18+32+4 -> 54 | S83: =1365.96+614.8 -> 1980.76 | U83: 20639.05 | W83: =SUM(S83:V83) -> 22619.81 | X83: =IFERROR(S83/R83,"") -> 36.680741 | Y83: =U83/P83 -> 0.9435857 | Z83: =P83-W83 -> -746.81 | AA83: =Z83/P83 -> -0.034143007 | AB83: =M83-W83 -> -22619.81 | AC83: =AA83-O83 -> -0.58414301
A84: Folsom | C84: TBEN | D84: 2020 | E84: 43920 | F84: 160339 | G84: 220100110 | K84: Tank New Duplex 100 Gal | O84: =1-0.45 -> 0.55 | P84: 4900 | Q84: 894 | R84: 0 | S84: 0 | U84: 7871.31 | W84: =SUM(S84:V84) -> 7871.31 | X84: =IFERROR(S84/R84,"") | Y84: =U84/P84 -> 1.6063898 | Z84: =P84-W84 -> -2971.31 | AA84: =Z84/P84 -> -0.6063898 | AB84: =M84-W84 -> -7871.31 | AC84: =AA84-O84 -> -1.1563898
A85: Folsom | C85: TBIN | D85: 2020 | E85: 43920 | F85: 160339 | G85: 523050120 | K85: TB Install & Train | O85: =1-0.45 -> 0.55 | P85: 11255 | Q85: 895 | R85: 92 | S85: =2843.72+1279.72 -> 4123.44 | T85: 4019.86 | U85: 928.32 | W85: =SUM(S85:V85) -> 9071.62 | X85: =IFERROR(S85/R85,"") -> 44.82 | Y85: =U85/P85 -> 0.082480675 | Z85: =P85-W85 -> 2183.38 | AA85: =Z85/P85 -> 0.193992 | AB85: =M85-W85 -> -9071.62 | AC85: =AA85-O85 -> -0.356008
A86: Folsom | C86: M3IT | D86: 2020 | E86: 43920 | F86: 160339 | G86: 626620120 | K86: M3 Software Install & Train | O86: =1-0.529 -> 0.471 | P86: 6155 | Q86: 896 | R86: 16 | S86: =628.48+282.88 -> 911.36 | T86: 892.56 | U86: 2203.89 | W86: =SUM(S86:V86) -> 4007.81 | X86: =IFERROR(S86/R86,"") -> 56.96 | Y86: =U86/P86 -> 0.35806499 | Z86: =P86-W86 -> 2147.19 | AA86: =Z86/P86 -> 0.34885297 | AB86: =M86-W86 -> -4007.81 | AC86: =AA86-O86 -> -0.12214703
D87: 2020 | E87: 43920 | X87: =IFERROR(S87/R87,"")
D88: 2020 | E88: 43920 | X88: =IFERROR(S88/R88,"")
A89: Folsom | C89: Rev Total | D89: 2020 | E89: 43920 | O89: =((P83*O83)+(P84*O84))/P89 -> 0.33327637 | P89: =SUM(P83:P88) -> 44183 | R89: =SUM(R83:R87) -> 162 | S89: =SUM(S83:S87) -> 7015.56 | T89: =SUM(T83:T87) -> 4912.42 | U89: =SUM(U83:U87) -> 31642.57 | W89: =SUM(W83:W88) -> 43570.55 | X89: =IFERROR(S89/R89,"") -> 43.305926 | Y89: =U89/P89 -> 0.7161707 | Z89: =P89-W89 -> 612.45 | AA89: =Z89/P89 -> 0.013861666 | AB89: =M89-W89 -> -43570.55 | AC89: =AA89-O89 -> -0.31941471
A90: Folsom | C90: SCH | D90: 2020 | E90: 43920 | F90: 160339 | G90: 997080WH | K90: Shipping / Crating / Handling | O90: 0 | P90: 4000 | Q90: 897 | R90: 4 | S90: =110+49.52 -> 159.52 | T90: 269.65 | U90: 4082.94 | W90: =SUM(S90:U90) -> 4512.11 | X90: =IFERROR(S90/R90,"") -> 39.88 | Y90: =U90/P90 -> 1.020735 | Z90: =P90-W90 -> -512.11 | AA90: =Z90/P90 -> -0.1280275 | AB90: =M90-W90 -> -4512.11 | AC90: =AA90-O90 -> -0.1280275
A91: Folsom | C91: DRMCC | D91: 2020 | E91: 43920 | F91: 160339 | G91: /811001011 | I91: =MID(G91,3,1) -> 1 | J91: =IF(I91="1","Small/Medium","Large") -> Small/Medium | K91: MCC Annual 2021 | L91: =P91 -> 9680 | M91: =L91*0.3 -> 2904 | N91: =L91-M91 -> 6776 | O91: =N91/L91 -> 0.7 | P91: 9680 | W91: =SUM(S91:V91) -> 0 | X91: =IFERROR(S91/R91,"") | Z91: =P91-W91 -> 9680 | AA91: =Z91/P91 -> 1 | AB91: =M91-W91 -> 2904 | AC91: =AA91-O91 -> 0.3
A92: Folsom | C92: DRM3 | D92: 2020 | E92: 43920 | F92: 160339 | G92: /721620120 | K92: M3 Software Annual | P92: 9979 | X92: =IFERROR(S92/R92,"") | AB92: =M92-W92 -> 0 | AC92: =AA92-O92 -> 0
A93: Folsom | C93: DRM3 | D93: 2020 | E93: 43920 | F93: 160339 | G93: /721620120 | K93: M3 Software Annual Yr 1 | P93: 10977 | X93: =IFERROR(S93/R93,"") | AB93: =M93-W93 -> 0 | AC93: =AA93-O93 -> 0
A94: Folsom | D94: 2020 | E94: 43920 | K94: Sales Tax | P94: 6228.46 | X94: =IFERROR(S94/R94,"") | AB94: =M94-W94 -> 0 | AC94: =AA94-O94 -> 0
A95: Folsom | C95: Inv Total | D95: 2020 | E95: 43920 | P95: =SUM(P89:P94) -> 85047.46 | R95: =SUM(R89:R94) -> 166 | S95: =SUM(S89:S94) -> 7175.08 | T95: =SUM(T89:T94) -> 5182.07 | U95: =SUM(U89:U94) -> 35725.51 | W95: =SUM(S95:U95) -> 48082.66 | X95: =IFERROR(S95/R95,"") -> 43.223373 | Y95: =U95/P95 -> 0.42006557 | Z95: =P95-W95 -> 36964.8 | AA95: =Z95/P95 -> 0.43463732 | AB95: =M95-W95 -> -48082.66 | AC95: =AA95-O95 -> 0.43463732
A96: Folsom | C96: Total TBEN | D96: 2020 | E96: 43920 | O96: =((P83*O83)+(P84*O84))/P96 -> 0.55 | P96: =P83+P84 -> 26773 | R96: =R83+R84 -> 54 | S96: =S83+S84 -> 1980.76 | T96: =T83+T84 -> 0 | U96: =U83+U84 -> 28510.36 | W96: =W83+W84 -> 30491.12 | X96: =IFERROR(S96/R96,"") -> 36.680741 | Y96: =U96/P96 -> 1.0648922 | Z96: =P96-W96 -> -3718.12 | AA96: =Z96/P96 -> -0.13887573 | AB96: =M96-W96 -> -30491.12 | AC96: =AA96-O96 -> -0.68887573
A98: Springfield Water | C98: TBEN | D98: 2020 | E98: 44043 | F98: 160994 | G98: 110010210 | I98: =MID(G98,2,1) -> 1 | J98: TB Small | K98: TB New Small Series 100 | O98: =1-0.45 -> 0.55 | P98: 15796 | Q98: 978 | R98: =12.5+11.5+4+2 -> 30 | S98: =779.4+350.79 -> 1130.19 | T98: 0 | U98: 7294.14 | W98: =SUM(S98:V98) -> 8424.33 | X98: =IFERROR(S98/R98,"") -> 37.673 | Y98: =U98/P98 -> 0.46177133 | Z98: =P98-W98 -> 7371.67 | AA98: =Z98/P98 -> 0.46667954 | AB98: =M98-W98 -> -8424.33 | AC98: =AA98-O98 -> -0.083320461
A99: Springfield Water | C99: TBEN | D99: 2020 | E99: 44043 | F99: 160994 | G99: 220100210 | K99: Tank New Duplex 100 Gal | O99: =1-0.45 -> 0.55 | P99: 5999 | Q99: 979 | R99: 3 | S99: =81.12+36.51 -> 117.63 | U99: 7800.67 | W99: =SUM(S99:V99) -> 7918.3 | X99: =IFERROR(S99/R99,"") -> 39.21 | Y99: =U99/P99 -> 1.3003284 | Z99: =P99-W99 -> -1919.3 | AA99: =Z99/P99 -> -0.31993666 | AB99: =M99-W99 -> -7918.3 | AC99: =AA99-O99 -> -0.86993666
A100: Springfield Water | C100: TBIN | D100: 2020 | E100: 44043 | F100: 160994 | G100: 510010110 | K100: TB Install & Train | O100: =1-0.45 -> 0.55 | P100: 4995 | Q100: 980 | R100: 32 | S100: =989.12+445.12 -> 1434.24 | T100: 1438.81 | W100: =SUM(S100:V100) -> 2873.05 | X100: =IFERROR(S100/R100,"") -> 44.82 | Y100: =U100/P100 -> 0 | Z100: =P100-W100 -> 2121.95 | AA100: =Z100/P100 -> 0.42481481 | AB100: =M100-W100 -> -2873.05 | AC100: =AA100-O100 -> -0.12518519
D101: 2020 | E101: 44043 | X101: =IFERROR(S101/R101,"")
A102: Springfield Water | C102: Rev Total | D102: 2020 | E102: 44043 | O102: =((P98*O98)+(P99*O99))/P102 -> 0.44745241 | P102: =SUM(P98:P101) -> 26790 | R102: =SUM(R98:R101) -> 65 | S102: =SUM(S98:S101) -> 2682.06 | T102: =SUM(T98:T101) -> 1438.81 | U102: =SUM(U98:U101) -> 15094.81 | W102: =SUM(W98:W101) -> 19215.68 | X102: =IFERROR(S102/R102,"") -> 41.262462 | Y102: =U102/P102 -> 0.56344942 | Z102: =P102-W102 -> 7574.32 | AA102: =Z102/P102 -> 0.28272938 | AB102: =M102-W102 -> -19215.68 | AC102: =AA102-O102 -> -0.16472303
A103: Springfield Water | C103: SCH | D103: 2020 | E103: 44043 | F103: 160994 | G103: 997080WH | K103: Shipping / Crating / Handling | O103: 0 | P103: 1000 | Q103: 981 | R103: 5.5 | S103: =151.25+68.09 -> 219.34 | T103: 776.4 | W103: =SUM(S103:U103) -> 995.74 | X103: =IFERROR(S103/R103,"") -> 39.88 | Y103: =U103/P103 -> 0 | Z103: =P103-W103 -> 4.26 | AA103: =Z103/P103 -> 0.00426 | AB103: =M103-W103 -> -995.74 | AC103: =AA103-O103 -> 0.00426
D104: 2020 | E104: 44043
A105: Springfield Water | C105: Inv Total | D105: 2020 | E105: 44043 | P105: =SUM(P102:P103) -> 27790 | R105: =SUM(R102:R103) -> 70.5 | S105: =SUM(S102:S103) -> 2901.4 | T105: =SUM(T102:T103) -> 2215.21 | U105: =SUM(U102:U103) -> 15094.81 | W105: =SUM(S105:U105) -> 20211.42 | X105: =IFERROR(S105/R105,"") -> 41.15461 | Y105: =U105/P105 -> 0.54317416 | Z105: =P105-W105 -> 7578.58 | AA105: =Z105/P105 -> 0.27270889 | AB105: =M105-W105 -> -20211.42 | AC105: =AA105-O105 -> 0.27270889
A106: Springfield Water | C106: Total TBEN | D106: 2020 | E106: 44043 | O106: =((P98*O98)+(P99*O99))/P106 -> 0.55 | P106: =P98+P99 -> 21795 | R106: =R98+R99 -> 33 | S106: =S98+S99 -> 1247.82 | T106: =T98+T99 -> 0 | U106: =U98+U99 -> 15094.81 | W106: =W98+W99 -> 16342.63 | X106: =IFERROR(S106/R106,"") -> 37.812727 | Y106: =U106/P106 -> 0.69258133 | Z106: =P106-W106 -> 5452.37 | AA106: =Z106/P106 -> 0.25016609 | AB106: =M106-W106 -> -16342.63 | AC106: =AA106-O106 -> -0.29983391
...

Sheet MCC Margin Analysis
A1: MCC
C2: =SUM(C4:C96) -> 936076.39 | D2: =SUM(D4:D96) -> 846560.68 | E2: =SUM(E4:E96) -> 1190947 | F2: =SUM(F4:F96) -> 1441605.4 | G2: =SUM(G4:G96) -> 1336147.9 | J2: =SUM(J4:J96) -> 207210.08 | K2: =SUM(K4:K96) -> 187490.49 | L2: =SUM(L4:L96) -> 236679.49 | M2: =SUM(M4:M96) -> 321230.19 | N2: =SUM(N4:N96) -> 293678.83 | Q2: =IFERROR((C2-J2)/C2," - ") -> 0.77863978 | R2: =IFERROR((D2-K2)/D2," - ") -> 0.77852681 | S2: =IFERROR((E2-L2)/E2," - ") -> 0.80126782 | T2: =IFERROR((F2-M2)/F2," - ") -> 0.77717189 | U2: =IFERROR((G2-N2)/G2," - ") -> 0.78020485
A3: REV | B3: Customer | C3: 2021 | D3: =C3+1 -> 2022 | E3: =D3+1 -> 2023 | F3: =E3+1 -> 2024 | G3: =F3+1 -> 2025 | I3: COGS | J3: 2021 | K3: =J3+1 -> 2022 | L3: =K3+1 -> 2023 | M3: =L3+1 -> 2024 | N3: =M3+1 -> 2025 | P3: GPM % | Q3: 2021 | R3: =Q3+1 -> 2022 | S3: =R3+1 -> 2023 | T3: =S3+1 -> 2024 | U3: =T3+1 -> 2025
B4: Alameda | C4: =SUMIFS('TB & MCC Cost Audit 2020-Curren'!$P:$P,'TB & MCC Cost Audit 2020-Curren'!$C:$C,'MCC Margin Analysis'!$A$1,'TB & MCC Cost Audit 2020-Curren'!$D:$D,'MCC Margin Analysis'!C$3,'TB & MCC Cost Audit 2020-Curren'!$A:$A,'MCC Margin Analysis'!$B4) -> 40676 | D4: =SUMIFS('TB & MCC Cost Audit 2020-Curren'!$P:$P,'TB & MCC Cost Audit 2020-Curren'!$C:$C,'MCC Margin Analysis'!$A$1,'TB & MCC Cost Audit 2020-Curren'!$D:$D,'MCC Margin Analysis'!D$3,'TB & MCC Cost Audit 2020-Curren'!$A:$A,'MCC Margin Analysis'!$B4) -> 31320 | E4: =SUMIFS('TB & MCC Cost Audit 2020-Curren'!$P:$P,'TB & MCC Cost Audit 2020-Curren'!$C:$C,'MCC Margin Analysis'!$A$1,'TB & MCC Cost Audit 2020-Curren'!$D:$D,'MCC Margin Analysis'!E$3,'TB & MCC Cost Audit 2020-Curren'!$A:$A,'MCC Margin Analysis'!$B4) -> 31946 | F4: =SUMIFS('TB & MCC Cost Audit 2020-Curren'!$P:$P,'TB & MCC Cost Audit 2020-Curren'!$C:$C,'MCC Margin Analysis'!$A$1,'TB & MCC Cost Audit 2020-Curren'!$D:$D,'MCC Margin Analysis'!F$3,'TB & MCC Cost Audit 2020-Curren'!$A:$A,'MCC Margin Analysis'!$B4) -> 32584 | G4: =SUMIFS('TB & MCC Cost Audit 2020-Curren'!$P:$P,'TB & MCC Cost Audit 2020-Curren'!$C:$C,'MCC Margin Analysis'!$A$1,'TB & MCC Cost Audit 2020-Curren'!$D:$D,'MCC Margin Analysis'!G$3,'TB & MCC Cost Audit 2020-Curren'!$A:$A,'MCC Margin Analysis'!$B4) -> 33236 | J4: =SUMIFS('TB & MCC Cost Audit 2020-Curren'!$W:$W,'TB & MCC Cost Audit 2020-Curren'!$C:$C,'MCC Margin Analysis'!$A$1,'TB & MCC Cost Audit 2020-Curren'!$D:$D,'MCC Margin Analysis'!J$3,'TB & MCC Cost Audit 2020-Curren'!$A:$A,'MCC Margin Analysis'!$B4) -> 8509.5 | K4: =SUMIFS('TB & MCC Cost Audit 2020-Curren'!$W:$W,'TB & MCC Cost Audit 2020-Curren'!$C:$C,'MCC Margin Analysis'!$A$1,'TB & MCC Cost Audit 2020-Curren'!$D:$D,'MCC Margin Analysis'!K$3,'TB & MCC Cost Audit 2020-Curren'!$A:$A,'MCC Margin Analysis'!$B4) -> 4654.75 | L4: =SUMIFS('TB & MCC Cost Audit 2020-Curren'!$W:$W,'TB & MCC Cost Audit 2020-Curren'!$C:$C,'MCC Margin Analysis'!$A$1,'TB & MCC Cost Audit 2020-Curren'!$D:$D,'MCC Margin Analysis'!L$3,'TB & MCC Cost Audit 2020-Curren'!$A:$A,'MCC Margin Analysis'!$B4) -> 4572.81 | M4: =SUMIFS('TB & MCC Cost Audit 2020-Curren'!$W:$W,'TB & MCC Cost Audit 2020-Curren'!$C:$C,'MCC Margin Analysis'!$A$1,'TB & MCC Cost Audit 2020-Curren'!$D:$D,'MCC Margin Analysis'!M$3,'TB & MCC Cost Audit 2020-Curren'!$A:$A,'MCC Margin Analysis'!$B4) -> 4543.06 | N4: =SUMIFS('TB & MCC Cost Audit 2020-Curren'!$W:$W,'TB & MCC Cost Audit 2020-Curren'!$C:$C,'MCC Margin Analysis'!$A$1,'TB & MCC Cost Audit 2020-Curren'!$D:$D,'MCC Margin Analysis'!N$3,'TB & MCC Cost Audit 2020-Curren'!$A:$A,'MCC Margin Analysis'!$B4) -> 6316.41 | Q4: =IFERROR((C4-J4)/C4," - ") -> 0.79079801 | R4: =IFERROR((D4-K4)/D4," - ") -> 0.85138091 | S4: =IFERROR((E4-L4)/E4," - ") -> 0.85685814 | T4: =IFERROR((F4-M4)/F4," - ") -> 0.8605739 | U4: =IFERROR((G4-N4)/G4," - ") -> 0.80995276
B5: Albemarle | C5: =SUMIFS('TB & MCC Cost Audit 2020-Curren'!$P:$P,'TB & MCC Cost Audit 2020-Curren'!$C:$C,'MCC Margin Analysis'!$A$1,'TB & MCC Cost Audit 2020-Curren'!$D:$D,'MCC Margin Analysis'!C$3,'TB & MCC Cost Audit 2020-Curren'!$A:$A,'MCC Margin Analysis'!$B5) -> 0 | D5: =SUMIFS('TB & MCC Cost Audit 2020-Curren'!$P:$P,'TB & MCC Cost Audit 2020-Curren'!$C:$C,'MCC Margin Analysis'!$A$1,'TB & MCC Cost Audit 2020-Curren'!$D:$D,'MCC Margin Analysis'!D$3,'TB & MCC Cost Audit 2020-Curren'!$A:$A,'MCC Margin Analysis'!$B5) -> 0 | E5: =SUMIFS('TB & MCC Cost Audit 2020-Curren'!$P:$P,'TB & MCC Cost Audit 2020-Curren'!$C:$C,'MCC Margin Analysis'!$A$1,'TB & MCC Cost Audit 2020-Curren'!$D:$D,'MCC Margin Analysis'!E$3,'TB & MCC Cost Audit 2020-Curren'!$A:$A,'MCC Margin Analysis'!$B5) -> 0 | F5: =SUMIFS('TB & MCC Cost Audit 2020-Curren'!$P:$P,'TB & MCC Cost Audit 2020-Curren'!$C:$C,'MCC Margin Analysis'!$A$1,'TB & MCC Cost Audit 2020-Curren'!$D:$D,'MCC Margin Analysis'!F$3,'TB & MCC Cost Audit 2020-Curren'!$A:$A,'MCC Margin Analysis'!$B5) -> 0 | G5: =SUMIFS('TB & MCC Cost Audit 2020-Curren'!$P:$P,'TB & MCC Cost Audit 2020-Curren'!$C:$C,'MCC Margin Analysis'!$A$1,'TB & MCC Cost Audit 2020-Curren'!$D:$D,'MCC Margin Analysis'!G$3,'TB & MCC Cost Audit 2020-Curren'!$A:$A,'MCC Margin Analysis'!$B5) -> 0 | J5: =SUMIFS('TB & MCC Cost Audit 2020-Curren'!$W:$W,'TB & MCC Cost Audit 2020-Curren'!$C:$C,'MCC Margin Analysis'!$A$1,'TB & MCC Cost Audit 2020-Curren'!$D:$D,'MCC Margin Analysis'!J$3,'TB & MCC Cost Audit 2020-Curren'!$A:$A,'MCC Margin Analysis'!$B5) -> 0 | K5: =SUMIFS('TB & MCC Cost Audit 2020-Curren'!$W:$W,'TB & MCC Cost Audit 2020-Curren'!$C:$C,'MCC Margin Analysis'!$A$1,'TB & MCC Cost Audit 2020-Curren'!$D:$D,'MCC Margin Analysis'!K$3,'TB & MCC Cost Audit 2020-Curren'!$A:$A,'MCC Margin Analysis'!$B5) -> 0 | L5: =SUMIFS('TB & MCC Cost Audit 2020-Curren'!$W:$W,'TB & MCC Cost Audit 2020-Curren'!$C:$C,'MCC Margin Analysis'!$A$1,'TB & MCC Cost Audit 2020-Curren'!$D:$D,'MCC Margin Analysis'!L$3,'TB & MCC Cost Audit 2020-Curren'!$A:$A,'MCC Margin Analysis'!$B5) -> 0 | M5: =SUMIFS('TB & MCC Cost Audit 2020-Curren'!$W:$W,'TB & MCC Cost Audit 2020-Curren'!$C:$C,'MCC Margin Analysis'!$A$1,'TB & MCC Cost Audit 2020-Curren'!$D:$D,'MCC Margin Analysis'!M$3,'TB & MCC Cost Audit 2020-Curren'!$A:$A,'MCC Margin Analysis'!$B5) -> 0 | N5: =SUMIFS('TB & MCC Cost Audit 2020-Curren'!$W:$W,'TB & MCC Cost Audit 2020-Curren'!$C:$C,'MCC Margin Analysis'!$A$1,'TB & MCC Cost Audit 2020-Curren'!$D:$D,'MCC Margin Analysis'!N$3,'TB & MCC Cost Audit 2020-Curren'!$A:$A,'MCC Margin Analysis'!$B5) -> 0 | Q5: =IFERROR((C5-J5)/C5," - ") -> - | R5: =IFERROR((D5-K5)/D5," - ") -> - | S5: =IFERROR((E5-L5)/E5," - ") -> - | T5: =IFERROR((F5-M5)/F5," - ") -> - | U5: =IFERROR((G5-N5)/G5," - ") -> -
B6: Allen | C6: =SUMIFS('TB & MCC Cost Audit 2020-Curren'!$P:$P,'TB & MCC Cost Audit 2020-Curren'!$C:$C,'MCC Margin Analysis'!$A$1,'TB & MCC Cost Audit 2020-Curren'!$D:$D,'MCC Margin Analysis'!C$3,'TB & MCC Cost Audit 2020-Curren'!$A:$A,'MCC Margin Analysis'!$B6) -> 0 | D6: =SUMIFS('TB & MCC Cost Audit 2020-Curren'!$P:$P,'TB & MCC Cost Audit 2020-Curren'!$C:$C,'MCC Margin Analysis'!$A$1,'TB & MCC Cost Audit 2020-Curren'!$D:$D,'MCC Margin Analysis'!D$3,'TB & MCC Cost Audit 2020-Curren'!$A:$A,'MCC Margin Analysis'!$B6) -> 0 | E6: =SUMIFS('TB & MCC Cost Audit 2020-Curren'!$P:$P,'TB & MCC Cost Audit 2020-Curren'!$C:$C,'MCC Margin Analysis'!$A$1,'TB & MCC Cost Audit 2020-Curren'!$D:$D,'MCC Margin Analysis'!E$3,'TB & MCC Cost Audit 2020-Curren'!$A:$A,'MCC Margin Analysis'!$B6) -> 9680 | F6: =SUMIFS('TB & MCC Cost Audit 2020-Curren'!$P:$P,'TB & MCC Cost Audit 2020-Curren'!$C:$C,'MCC Margin Analysis'!$A$1,'TB & MCC Cost Audit 2020-Curren'!$D:$D,'MCC Margin Analysis'!F$3,'TB & MCC Cost Audit 2020-Curren'!$A:$A,'MCC Margin Analysis'!$B6) -> 9680 | G6: =SUMIFS('TB & MCC Cost Audit 2020-Curren'!$P:$P,'TB & MCC Cost Audit 2020-Curren'!$C:$C,'MCC Margin Analysis'!$A$1,'TB & MCC Cost Audit 2020-Curren'!$D:$D,'MCC Margin Analysis'!G$3,'TB & MCC Cost Audit 2020-Curren'!$A:$A,'MCC Margin Analysis'!$B6) -> 9680 | J6: =SUMIFS('TB & MCC Cost Audit 2020-Curren'!$W:$W,'TB & MCC Cost Audit 2020-Curren'!$C:$C,'MCC Margin Analysis'!$A$1,'TB & MCC Cost Audit 2020-Curren'!$D:$D,'MCC Margin Analysis'!J$3,'TB & MCC Cost Audit 2020-Curren'!$A:$A,'MCC Margin Analysis'!$B6) -> 0 | K6: =SUMIFS('TB & MCC Cost Audit 2020-Curren'!$W:$W,'TB & MCC Cost Audit 2020-Curren'!$C:$C,'MCC Margin Analysis'!$A$1,'TB & MCC Cost Audit 2020-Curren'!$D:$D,'MCC Margin Analysis'!K$3,'TB & MCC Cost Audit 2020-Curren'!$A:$A,'MCC Margin Analysis'!$B6) -> 0 | L6: =SUMIFS('TB & MCC Cost Audit 2020-Curren'!$W:$W,'TB & MCC Cost Audit 2020-Curren'!$C:$C,'MCC Margin Analysis'!$A$1,'TB & MCC Cost Audit 2020-Curren'!$D:$D,'MCC Margin Analysis'!L$3,'TB & MCC Cost Audit 2020-Curren'!$A:$A,'MCC Margin Analysis'!$B6) -> 3069 | M6: =SUMIFS('TB & MCC Cost Audit 2020-Curren'!$W:$W,'TB & MCC Cost Audit 2020-Curren'!$C:$C,'MCC Margin Analysis'!$A$1,'TB & MCC Cost Audit 2020-Curren'!$D:$D,'MCC Margin Analysis'!M$3,'TB & MCC Cost Audit 2020-Curren'!$A:$A,'MCC Margin Analysis'!$B6) -> 2866.47 | N6: =SUMIFS('TB & MCC Cost Audit 2020-Curren'!$W:$W,'TB & MCC Cost Audit 2020-Curren'!$C:$C,'MCC Margin Analysis'!$A$1,'TB & MCC Cost Audit 2020-Curren'!$D:$D,'MCC Margin Analysis'!N$3,'TB & MCC Cost Audit 2020-Curren'!$A:$A,'MCC Margin Analysis'!$B6) -> 4077.37 | Q6: =IFERROR((C6-J6)/C6," - ") -> - | R6: =IFERROR((D6-K6)/D6," - ") -> - | S6: =IFERROR((E6-L6)/E6," - ") -> 0.68295455 | T6: =IFERROR((F6-M6)/F6," - ") -> 0.70387707 | U6: =IFERROR((G6-N6)/G6," - ") -> 0.57878409
B7: Anne Arundel | C7: =SUMIFS('TB & MCC Cost Audit 2020-Curren'!$P:$P,'TB & MCC Cost Audit 2020-Curren'!$C:$C,'MCC Margin Analysis'!$A$1,'TB & MCC Cost Audit 2020-Curren'!$D:$D,'MCC Margin Analysis'!C$3,'TB & MCC Cost Audit 2020-Curren'!$A:$A,'MCC Margin Analysis'!$B7) -> 0 | D7: =SUMIFS('TB & MCC Cost Audit 2020-Curren'!$P:$P,'TB & MCC Cost Audit 2020-Curren'!$C:$C,'MCC Margin Analysis'!$A$1,'TB & MCC Cost Audit 2020-Curren'!$D:$D,'MCC Margin Analysis'!D$3,'TB & MCC Cost Audit 2020-Curren'!$A:$A,'MCC Margin Analysis'!$B7) -> 9353 | E7: =SUMIFS('TB & MCC Cost Audit 2020-Curren'!$P:$P,'TB & MCC Cost Audit 2020-Curren'!$C:$C,'MCC Margin Analysis'!$A$1,'TB & MCC Cost Audit 2020-Curren'!$D:$D,'MCC Margin Analysis'!E$3,'TB & MCC Cost Audit 2020-Curren'!$A:$A,'MCC Margin Analysis'!$B7) -> 9353 | F7: =SUMIFS('TB & MCC Cost Audit 2020-Curren'!$P:$P,'TB & MCC Cost Audit 2020-Curren'!$C:$C,'MCC Margin Analysis'!$A$1,'TB & MCC Cost Audit 2020-Curren'!$D:$D,'MCC Margin Analysis'!F$3,'TB & MCC Cost Audit 2020-Curren'!$A:$A,'MCC Margin Analysis'!$B7) -> 9353 | G7: =SUMIFS('TB & MCC Cost Audit 2020-Curren'!$P:$P,'TB & MCC Cost Audit 2020-Curren'!$C:$C,'MCC Margin Analysis'!$A$1,'TB & MCC Cost Audit 2020-Curren'!$D:$D,'MCC Margin Analysis'!G$3,'TB & MCC Cost Audit 2020-Curren'!$A:$A,'MCC Margin Analysis'!$B7) -> 9353 | J7: =SUMIFS('TB & MCC Cost Audit 2020-Curren'!$W:$W,'TB & MCC Cost Audit 2020-Curren'!$C:$C,'MCC Margin Analysis'!$A$1,'TB & MCC Cost Audit 2020-Curren'!$D:$D,'MCC Margin Analysis'!J$3,'TB & MCC Cost Audit 2020-Curren'!$A:$A,'MCC Margin Analysis'!$B7) -> 0 | K7: =SUMIFS('TB & MCC Cost Audit 2020-Curren'!$W:$W,'TB & MCC Cost Audit 2020-Curren'!$C:$C,'MCC Margin Analysis'!$A$1,'TB & MCC Cost Audit 2020-Curren'!$D:$D,'MCC Margin Analysis'!K$3,'TB & MCC Cost Audit 2020-Curren'!$A:$A,'MCC Margin Analysis'!$B7) -> 4420.05 | L7: =SUMIFS('TB & MCC Cost Audit 2020-Curren'!$W:$W,'TB & MCC Cost Audit 2020-Curren'!$C:$C,'MCC Margin Analysis'!$A$1,'TB & MCC Cost Audit 2020-Curren'!$D:$D,'MCC Margin Analysis'!L$3,'TB & MCC Cost Audit 2020-Curren'!$A:$A,'MCC Margin Analysis'!$B7) -> 3609.59 | M7: =SUMIFS('TB & MCC Cost Audit 2020-Curren'!$W:$W,'TB & MCC Cost Audit 2020-Curren'!$C:$C,'MCC Margin Analysis'!$A$1,'TB & MCC Cost Audit 2020-Curren'!$D:$D,'MCC Margin Analysis'!M$3,'TB & MCC Cost Audit 2020-Curren'!$A:$A,'MCC Margin Analysis'!$B7) -> 2346.39 | N7: =SUMIFS('TB & MCC Cost Audit 2020-Curren'!$W:$W,'TB & MCC Cost Audit 2020-Curren'!$C:$C,'MCC Margin Analysis'!$A$1,'TB & MCC Cost Audit 2020-Curren'!$D:$D,'MCC Margin Analysis'!N$3,'TB & MCC Cost Audit 2020-Curren'!$A:$A,'MCC Margin Analysis'!$B7) -> 4296.96 | Q7: =IFERROR((C7-J7)/C7," - ") -> - | R7: =IFERROR((D7-K7)/D7," - ") -> 0.52741901 | S7: =IFERROR((E7-L7)/E7," - ") -> 0.61407142 | T7: =IFERROR((F7-M7)/F7," - ") -> 0.74912969 | U7: =IFERROR((G7-N7)/G7," - ") -> 0.54057949
B8: Apex | C8: =SUMIFS('TB & MCC Cost Audit 2020-Curren'!$P:$P,'TB & MCC Cost Audit 2020-Curren'!$C:$C,'MCC Margin Analysis'!$A$1,'TB & MCC Cost Audit 2020-Curren'!$D:$D,'MCC Margin Analysis'!C$3,'TB & MCC Cost Audit 2020-Curren'!$A:$A,'MCC Margin Analysis'!$B8) -> 0 | D8: =SUMIFS('TB & MCC Cost Audit 2020-Curren'!$P:$P,'TB & MCC Cost Audit 2020-Curren'!$C:$C,'MCC Margin Analysis'!$A$1,'TB & MCC Cost Audit 2020-Curren'!$D:$D,'MCC Margin Analysis'!D$3,'TB & MCC Cost Audit 2020-Curren'!$A:$A,'MCC Margin Analysis'!$B8) -> 9116 | E8: =SUMIFS('TB & MCC Cost Audit 2020-Curren'!$P:$P,'TB & MCC Cost Audit 2020-Curren'!$C:$C,'MCC Margin Analysis'!$A$1,'TB & MCC Cost Audit 2020-Curren'!$D:$D,'MCC Margin Analysis'!E$3,'TB & MCC Cost Audit 2020-Curren'!$A:$A,'MCC Margin Analysis'!$B8) -> 12749 | F8: =SUMIFS('TB & MCC Cost Audit 2020-Curren'!$P:$P,'TB & MCC Cost Audit 2020-Curren'!$C:$C,'MCC Margin Analysis'!$A$1,'TB & MCC Cost Audit 2020-Curren'!$D:$D,'MCC Margin Analysis'!F$3,'TB & MCC Cost Audit 2020-Curren'!$A:$A,'MCC Margin Analysis'!$B8) -> 12084 | G8: =SUMIFS('TB & MCC Cost Audit 2020-Curren'!$P:$P,'TB & MCC Cost Audit 2020-Curren'!$C:$C,'MCC Margin Analysis'!$A$1,'TB & MCC Cost Audit 2020-Curren'!$D:$D,'MCC Margin Analysis'!G$3,'TB & MCC Cost Audit 2020-Curren'!$A:$A,'MCC Margin Analysis'!$B8) -> 11454 | J8: =SUMIFS('TB & MCC Cost Audit 2020-Curren'!$W:$W,'TB & MCC Cost Audit 2020-Curren'!$C:$C,'MCC Margin Analysis'!$A$1,'TB & MCC Cost Audit 2020-Curren'!$D:$D,'MCC Margin Analysis'!J$3,'TB & MCC Cost Audit 2020-Curren'!$A:$A,'MCC Margin Analysis'!$B8) -> 0 | K8: =SUMIFS('TB & MCC Cost Audit 2020-Curren'!$W:$W,'TB & MCC Cost Audit 2020-Curren'!$C:$C,'MCC Margin Analysis'!$A$1,'TB & MCC Cost Audit 2020-Curren'!$D:$D,'MCC Margin Analysis'!K$3,'TB & MCC Cost Audit 2020-Curren'!$A:$A,'MCC Margin Analysis'!$B8) -> 3394.42 | L8: =SUMIFS('TB & MCC Cost Audit 2020-Curren'!$W:$W,'TB & MCC Cost Audit 2020-Curren'!$C:$C,'MCC Margin Analysis'!$A$1,'TB & MCC Cost Audit 2020-Curren'!$D:$D,'MCC Margin Analysis'!L$3,'TB & MCC Cost Audit 2020-Curren'!$A:$A,'MCC Margin Analysis'!$B8) -> 3080.99 | M8: =SUMIFS('TB & MCC Cost Audit 2020-Curren'!$W:$W,'TB & MCC Cost Audit 2020-Curren'!$C:$C,'MCC Margin Analysis'!$A$1,'TB & MCC Cost Audit 2020-Curren'!$D:$D,'MCC Margin Analysis'!M$3,'TB & MCC Cost Audit 2020-Curren'!$A:$A,'MCC Margin Analysis'!$B8) -> 2341.53 | N8: =SUMIFS('TB & MCC Cost Audit 2020-Curren'!$W:$W,'TB & MCC Cost Audit 2020-Curren'!$C:$C,'MCC Margin Analysis'!$A$1,'TB & MCC Cost Audit 2020-Curren'!$D:$D,'MCC Margin Analysis'!N$3,'TB & MCC Cost Audit 2020-Curren'!$A:$A,'MCC Margin Analysis'!$B8) -> 1816.18 | Q8: =IFERROR((C8-J8)/C8," - ") -> - | R8: =IFERROR((D8-K8)/D8," - ") -> 0.62764151 | S8: =IFERROR((E8-L8)/E8," - ") -> 0.75833477 | T8: =IFERROR((F8-M8)/F8," - ") -> 0.8062289 | U8: =IFERROR((G8-N8)/G8," - ") -> 0.84143705
B9: Aqua Penn | C9: =SUMIFS('TB & MCC Cost Audit 2020-Curren'!$P:$P,'TB & MCC Cost Audit 2020-Curren'!$C:$C,'MCC Margin Analysis'!$A$1,'TB & MCC Cost Audit 2020-Curren'!$D:$D,'MCC Margin Analysis'!C$3,'TB & MCC Cost Audit 2020-Curren'!$A:$A,'MCC Margin Analysis'!$B9) -> 32434 | D9: =SUMIFS('TB & MCC Cost Audit 2020-Curren'!$P:$P,'TB & MCC Cost Audit 2020-Curren'!$C:$C,'MCC Margin Analysis'!$A$1,'TB & MCC Cost Audit 2020-Curren'!$D:$D,'MCC Margin Analysis'!D$3,'TB & MCC Cost Audit 2020-Curren'!$A:$A,'MCC Margin Analysis'!$B9) -> 0 | E9: =SUMIFS('TB & MCC Cost Audit 2020-Curren'!$P:$P,'TB & MCC Cost Audit 2020-Curren'!$C:$C,'MCC Margin Analysis'!$A$1,'TB & MCC Cost Audit 2020-Curren'!$D:$D,'MCC Margin Analysis'!E$3,'TB & MCC Cost Audit 2020-Curren'!$A:$A,'MCC Margin Analysis'!$B9) -> 41625 | F9: =SUMIFS('TB & MCC Cost Audit 2020-Curren'!$P:$P,'TB & MCC Cost Audit 2020-Curren'!$C:$C,'MCC Margin Analysis'!$A$1,'TB & MCC Cost Audit 2020-Curren'!$D:$D,'MCC Margin Analysis'!F$3,'TB & MCC Cost Audit 2020-Curren'!$A:$A,'MCC Margin Analysis'!$B9) -> 44749 | G9: =SUMIFS('TB & MCC Cost Audit 2020-Curren'!$P:$P,'TB & MCC Cost Audit 2020-Curren'!$C:$C,'MCC Margin Analysis'!$A$1,'TB & MCC Cost Audit 2020-Curren'!$D:$D,'MCC Margin Analysis'!G$3,'TB & MCC Cost Audit 2020-Curren'!$A:$A,'MCC Margin Analysis'!$B9) -> 48107 | J9: =SUMIFS('TB & MCC Cost Audit 2020-Curren'!$W:$W,'TB & MCC Cost Audit 2020-Curren'!$C:$C,'MCC Margin Analysis'!$A$1,'TB & MCC Cost Audit 2020-Curren'!$D:$D,'MCC Margin Analysis'!J$3,'TB & MCC Cost Audit 2020-Curren'!$A:$A,'MCC Margin Analysis'!$B9) -> 3232.83 | K9: =SUMIFS('TB & MCC Cost Audit 2020-Curren'!$W:$W,'TB & MCC Cost Audit 2020-Curren'!$C:$C,'MCC Margin Analysis'!$A$1,'TB & MCC Cost Audit 2020-Curren'!$D:$D,'MCC Margin Analysis'!K$3,'TB & MCC Cost Audit 2020-Curren'!$A:$A,'MCC Margin Analysis'!$B9) -> 0 | L9: =SUMIFS('TB & MCC Cost Audit 2020-Curren'!$W:$W,'TB & MCC Cost Audit 2020-Curren'!$C:$C,'MCC Margin Analysis'!$A$1,'TB & MCC Cost Audit 2020-Curren'!$D:$D,'MCC Margin Analysis'!L$3,'TB & MCC Cost Audit 2020-Curren'!$A:$A,'MCC Margin Analysis'!$B9) -> 5455.82 | M9: =SUMIFS('TB & MCC Cost Audit 2020-Curren'!$W:$W,'TB & MCC Cost Audit 2020-Curren'!$C:$C,'MCC Margin Analysis'!$A$1,'TB & MCC Cost Audit 2020-Curren'!$D:$D,'MCC Margin Analysis'!M$3,'TB & MCC Cost Audit 2020-Curren'!$A:$A,'MCC Margin Analysis'!$B9) -> 7193.03 | N9: =SUMIFS('TB & MCC Cost Audit 2020-Curren'!$W:$W,'TB & MCC Cost Audit 2020-Curren'!$C:$C,'MCC Margin Analysis'!$A$1,'TB & MCC Cost Audit 2020-Curren'!$D:$D,'MCC Margin Analysis'!N$3,'TB & MCC Cost Audit 2020-Curren'!$A:$A,'MCC Margin Analysis'!$B9) -> 11164.4 | Q9: =IFERROR((C9-J9)/C9," - ") -> 0.90032589 | R9: =IFERROR((D9-K9)/D9," - ") -> - | S9: =IFERROR((E9-L9)/E9," - ") -> 0.86892925 | T9: =IFERROR((F9-M9)/F9," - ") -> 0.83925831 | U9: =IFERROR((G9-N9)/G9," - ") -> 0.76792567
B10: Artesian Resources | C10: =SUMIFS('TB & MCC Cost Audit 2020-Curren'!$P:$P,'TB & MCC Cost Audit 2020-Curren'!$C:$C,'MCC Margin Analysis'!$A$1,'TB & MCC Cost Audit 2020-Curren'!$D:$D,'MCC Margin Analysis'!C$3,'TB & MCC Cost Audit 2020-Curren'!$A:$A,'MCC Margin Analysis'!$B10) -> 0 | D10: =SUMIFS('TB & MCC Cost Audit 2020-Curren'!$P:$P,'TB & MCC Cost Audit 2020-Curren'!$C:$C,'MCC Margin Analysis'!$A$1,'TB & MCC Cost Audit 2020-Curren'!$D:$D,'MCC Margin Analysis'!D$3,'TB & MCC Cost Audit 2020-Curren'!$A:$A,'MCC Margin Analysis'!$B10) -> 0 | E10: =SUMIFS('TB & MCC Cost Audit 2020-Curren'!$P:$P,'TB & MCC Cost Audit 2020-Curren'!$C:$C,'MCC Margin Analysis'!$A$1,'TB & MCC Cost Audit 2020-Curren'!$D:$D,'MCC Margin Analysis'!E$3,'TB & MCC Cost Audit 2020-Curren'!$A:$A,'MCC Margin Analysis'!$B10) -> 0 | F10: =SUMIFS('TB & MCC Cost Audit 2020-Curren'!$P:$P,'TB & MCC Cost Audit 2020-Curren'!$C:$C,'MCC Margin Analysis'!$A$1,'TB & MCC Cost Audit 2020-Curren'!$D:$D,'MCC Margin Analysis'!F$3,'TB & MCC Cost Audit 2020-Curren'!$A:$A,'MCC Margin Analysis'!$B10) -> 0 | G10: =SUMIFS('TB & MCC Cost Audit 2020-Curren'!$P:$P,'TB & MCC Cost Audit 2020-Curren'!$C:$C,'MCC Margin Analysis'!$A$1,'TB & MCC Cost Audit 2020-Curren'!$D:$D,'MCC Margin Analysis'!G$3,'TB & MCC Cost Audit 2020-Curren'!$A:$A,'MCC Margin Analysis'!$B10) -> 0 | J10: =SUMIFS('TB & MCC Cost Audit 2020-Curren'!$W:$W,'TB & MCC Cost Audit 2020-Curren'!$C:$C,'MCC Margin Analysis'!$A$1,'TB & MCC Cost Audit 2020-Curren'!$D:$D,'MCC Margin Analysis'!J$3,'TB & MCC Cost Audit 2020-Curren'!$A:$A,'MCC Margin Analysis'!$B10) -> 0 | K10: =SUMIFS('TB & MCC Cost Audit 2020-Curren'!$W:$W,'TB & MCC Cost Audit 2020-Curren'!$C:$C,'MCC Margin Analysis'!$A$1,'TB & MCC Cost Audit 2020-Curren'!$D:$D,'MCC Margin Analysis'!K$3,'TB & MCC Cost Audit 2020-Curren'!$A:$A,'MCC Margin Analysis'!$B10) -> 0 | L10: =SUMIFS('TB & MCC Cost Audit 2020-Curren'!$W:$W,'TB & MCC Cost Audit 2020-Curren'!$C:$C,'MCC Margin Analysis'!$A$1,'TB & MCC Cost Audit 2020-Curren'!$D:$D,'MCC Margin Analysis'!L$3,'TB & MCC Cost Audit 2020-Curren'!$A:$A,'MCC Margin Analysis'!$B10) -> 0 | M10: =SUMIFS('TB & MCC Cost Audit 2020-Curren'!$W:$W,'TB & MCC Cost Audit 2020-Curren'!$C:$C,'MCC Margin Analysis'!$A$1,'TB & MCC Cost Audit 2020-Curren'!$D:$D,'MCC Margin Analysis'!M$3,'TB & MCC Cost Audit 2020-Curren'!$A:$A,'MCC Margin Analysis'!$B10) -> 0 | N10: =SUMIFS('TB & MCC Cost Audit 2020-Curren'!$W:$W,'TB & MCC Cost Audit 2020-Curren'!$C:$C,'MCC Margin Analysis'!$A$1,'TB & MCC Cost Audit 2020-Curren'!$D:$D,'MCC Margin Analysis'!N$3,'TB & MCC Cost Audit 2020-Curren'!$A:$A,'MCC Margin Analysis'!$B10) -> 0 | Q10: =IFERROR((C10-J10)/C10," - ") -> - | R10: =IFERROR((D10-K10)/D10," - ") -> - | S10: =IFERROR((E10-L10)/E10," - ") -> - | T10: =IFERROR((F10-M10)/F10," - ") -> - | U10: =IFERROR((G10-N10)/G10," - ") -> -
B11: Aruba | C11: =SUMIFS('TB & MCC Cost Audit 2020-Curren'!$P:$P,'TB & MCC Cost Audit 2020-Curren'!$C:$C,'MCC Margin Analysis'!$A$1,'TB & MCC Cost Audit 2020-Curren'!$D:$D,'MCC Margin Analysis'!C$3,'TB & MCC Cost Audit 2020-Curren'!$A:$A,'MCC Margin Analysis'!$B11) -> 0 | D11: =SUMIFS('TB & MCC Cost Audit 2020-Curren'!$P:$P,'TB & MCC Cost Audit 2020-Curren'!$C:$C,'MCC Margin Analysis'!$A$1,'TB & MCC Cost Audit 2020-Curren'!$D:$D,'MCC Margin Analysis'!D$3,'TB & MCC Cost Audit 2020-Curren'!$A:$A,'MCC Margin Analysis'!$B11) -> 0 | E11: =SUMIFS('TB & MCC Cost Audit 2020-Curren'!$P:$P,'TB & MCC Cost Audit 2020-Curren'!$C:$C,'MCC Margin Analysis'!$A$1,'TB & MCC Cost Audit 2020-Curren'!$D:$D,'MCC Margin Analysis'!E$3,'TB & MCC Cost Audit 2020-Curren'!$A:$A,'MCC Margin Analysis'!$B11) -> 0 | F11: =SUMIFS('TB & MCC Cost Audit 2020-Curren'!$P:$P,'TB & MCC Cost Audit 2020-Curren'!$C:$C,'MCC Margin Analysis'!$A$1,'TB & MCC Cost Audit 2020-Curren'!$D:$D,'MCC Margin Analysis'!F$3,'TB & MCC Cost Audit 2020-Curren'!$A:$A,'MCC Margin Analysis'!$B11) -> 0 | G11: =SUMIFS('TB & MCC Cost Audit 2020-Curren'!$P:$P,'TB & MCC Cost Audit 2020-Curren'!$C:$C,'MCC Margin Analysis'!$A$1,'TB & MCC Cost Audit 2020-Curren'!$D:$D,'MCC Margin Analysis'!G$3,'TB & MCC Cost Audit 2020-Curren'!$A:$A,'MCC Margin Analysis'!$B11) -> 0 | J11: =SUMIFS('TB & MCC Cost Audit 2020-Curren'!$W:$W,'TB & MCC Cost Audit 2020-Curren'!$C:$C,'MCC Margin Analysis'!$A$1,'TB & MCC Cost Audit 2020-Curren'!$D:$D,'MCC Margin Analysis'!J$3,'TB & MCC Cost Audit 2020-Curren'!$A:$A,'MCC Margin Analysis'!$B11) -> 0 | K11: =SUMIFS('TB & MCC Cost Audit 2020-Curren'!$W:$W,'TB & MCC Cost Audit 2020-Curren'!$C:$C,'MCC Margin Analysis'!$A$1,'TB & MCC Cost Audit 2020-Curren'!$D:$D,'MCC Margin Analysis'!K$3,'TB & MCC Cost Audit 2020-Curren'!$A:$A,'MCC Margin Analysis'!$B11) -> 0 | L11: =SUMIFS('TB & MCC Cost Audit 2020-Curren'!$W:$W,'TB & MCC Cost Audit 2020-Curren'!$C:$C,'MCC Margin Analysis'!$A$1,'TB & MCC Cost Audit 2020-Curren'!$D:$D,'MCC Margin Analysis'!L$3,'TB & MCC Cost Audit 2020-Curren'!$A:$A,'MCC Margin Analysis'!$B11) -> 0 | M11: =SUMIFS('TB & MCC Cost Audit 2020-Curren'!$W:$W,'TB & MCC Cost Audit 2020-Curren'!$C:$C,'MCC Margin Analysis'!$A$1,'TB & MCC Cost Audit 2020-Curren'!$D:$D,'MCC Margin Analysis'!M$3,'TB & MCC Cost Audit 2020-Curren'!$A:$A,'MCC Margin Analysis'!$B11) -> 0 | N11: =SUMIFS('TB & MCC Cost Audit 2020-Curren'!$W:$W,'TB & MCC Cost Audit 2020-Curren'!$C:$C,'MCC Margin Analysis'!$A$1,'TB & MCC Cost Audit 2020-Curren'!$D:$D,'MCC Margin Analysis'!N$3,'TB & MCC Cost Audit 2020-Curren'!$A:$A,'MCC Margin Analysis'!$B11) -> 0 | Q11: =IFERROR((C11-J11)/C11," - ") -> - | R11: =IFERROR((D11-K11)/D11," - ") -> - | S11: =IFERROR((E11-L11)/E11," - ") -> - | T11: =IFERROR((F11-M11)/F11," - ") -> - | U11: =IFERROR((G11-N11)/G11," - ") -> -
B12: Austin | C12: =SUMIFS('TB & MCC Cost Audit 2020-Curren'!$P:$P,'TB & MCC Cost Audit 2020-Curren'!$C:$C,'MCC Margin Analysis'!$A$1,'TB & MCC Cost Audit 2020-Curren'!$D:$D,'MCC Margin Analysis'!C$3,'TB & MCC Cost Audit 2020-Curren'!$A:$A,'MCC Margin Analysis'!$B12) -> 17279 | D12: =SUMIFS('TB & MCC Cost Audit 2020-Curren'!$P:$P,'TB & MCC Cost Audit 2020-Curren'!$C:$C,'MCC Margin Analysis'!$A$1,'TB & MCC Cost Audit 2020-Curren'!$D:$D,'MCC Margin Analysis'!D$3,'TB & MCC Cost Audit 2020-Curren'!$A:$A,'MCC Margin Analysis'!$B12) -> 20445 | E12: =SUMIFS('TB & MCC Cost Audit 2020-Curren'!$P:$P,'TB & MCC Cost Audit 2020-Curren'!$C:$C,'MCC Margin Analysis'!$A$1,'TB & MCC Cost Audit 2020-Curren'!$D:$D,'MCC Margin Analysis'!E$3,'TB & MCC Cost Audit 2020-Curren'!$A:$A,'MCC Margin Analysis'!$B12) -> 19848 | F12: =SUMIFS('TB & MCC Cost Audit 2020-Curren'!$P:$P,'TB & MCC Cost Audit 2020-Curren'!$C:$C,'MCC Margin Analysis'!$A$1,'TB & MCC Cost Audit 2020-Curren'!$D:$D,'MCC Margin Analysis'!F$3,'TB & MCC Cost Audit 2020-Curren'!$A:$A,'MCC Margin Analysis'!$B12) -> 19269 | G12: =SUMIFS('TB & MCC Cost Audit 2020-Curren'!$P:$P,'TB & MCC Cost Audit 2020-Curren'!$C:$C,'MCC Margin Analysis'!$A$1,'TB & MCC Cost Audit 2020-Curren'!$D:$D,'MCC Margin Analysis'!G$3,'TB & MCC Cost Audit 2020-Curren'!$A:$A,'MCC Margin Analysis'!$B12) -> 18707 | J12: =SUMIFS('TB & MCC Cost Audit 2020-Curren'!$W:$W,'TB & MCC Cost Audit 2020-Curren'!$C:$C,'MCC Margin Analysis'!$A$1,'TB & MCC Cost Audit 2020-Curren'!$D:$D,'MCC Margin Analysis'!J$3,'TB & MCC Cost Audit 2020-Curren'!$A:$A,'MCC Margin Analysis'!$B12) -> 6455.24 | K12: =SUMIFS('TB & MCC Cost Audit 2020-Curren'!$W:$W,'TB & MCC Cost Audit 2020-Curren'!$C:$C,'MCC Margin Analysis'!$A$1,'TB & MCC Cost Audit 2020-Curren'!$D:$D,'MCC Margin Analysis'!K$3,'TB & MCC Cost Audit 2020-Curren'!$A:$A,'MCC Margin Analysis'!$B12) -> 4056.99 | L12: =SUMIFS('TB & MCC Cost Audit 2020-Curren'!$W:$W,'TB & MCC Cost Audit 2020-Curren'!$C:$C,'MCC Margin Analysis'!$A$1,'TB & MCC Cost Audit 2020-Curren'!$D:$D,'MCC Margin Analysis'!L$3,'TB & MCC Cost Audit 2020-Curren'!$A:$A,'MCC Margin Analysis'!$B12) -> 4362.94 | M12: =SUMIFS('TB & MCC Cost Audit 2020-Curren'!$W:$W,'TB & MCC Cost Audit 2020-Curren'!$C:$C,'MCC Margin Analysis'!$A$1,'TB & MCC Cost Audit 2020-Curren'!$D:$D,'MCC Margin Analysis'!M$3,'TB & MCC Cost Audit 2020-Curren'!$A:$A,'MCC Margin Analysis'!$B12) -> 4109.49 | N12: =SUMIFS('TB & MCC Cost Audit 2020-Curren'!$W:$W,'TB & MCC Cost Audit 2020-Curren'!$C:$C,'MCC Margin Analysis'!$A$1,'TB & MCC Cost Audit 2020-Curren'!$D:$D,'MCC Margin Analysis'!N$3,'TB & MCC Cost Audit 2020-Curren'!$A:$A,'MCC Margin Analysis'!$B12) -> 3760.63 | Q12: =IFERROR((C12-J12)/C12," - ") -> 0.62641125 | R12: =IFERROR((D12-K12)/D12," - ") -> 0.80156566 | S12: =IFERROR((E12-L12)/E12," - ") -> 0.78018239 | T12: =IFERROR((F12-M12)/F12," - ") -> 0.7867305 | U12: =IFERROR((G12-N12)/G12," - ") -> 0.79897204
B13: Badger | C13: =SUMIFS('TB & MCC Cost Audit 2020-Curren'!$P:$P,'TB & MCC Cost Audit 2020-Curren'!$C:$C,'MCC Margin Analysis'!$A$1,'TB & MCC Cost Audit 2020-Curren'!$D:$D,'MCC Margin Analysis'!C$3,'TB & MCC Cost Audit 2020-Curren'!$A:$A,'MCC Margin Analysis'!$B13) -> 0 | D13: =SUMIFS('TB & MCC Cost Audit 2020-Curren'!$P:$P,'TB & MCC Cost Audit 2020-Curren'!$C:$C,'MCC Margin Analysis'!$A$1,'TB & MCC Cost Audit 2020-Curren'!$D:$D,'MCC Margin Analysis'!D$3,'TB & MCC Cost Audit 2020-Curren'!$A:$A,'MCC Margin Analysis'!$B13) -> 0 | E13: =SUMIFS('TB & MCC Cost Audit 2020-Curren'!$P:$P,'TB & MCC Cost Audit 2020-Curren'!$C:$C,'MCC Margin Analysis'!$A$1,'TB & MCC Cost Audit 2020-Curren'!$D:$D,'MCC Margin Analysis'!E$3,'TB & MCC Cost Audit 2020-Curren'!$A:$A,'MCC Margin Analysis'!$B13) -> 0 | F13: =SUMIFS('TB & MCC Cost Audit 2020-Curren'!$P:$P,'TB & MCC Cost Audit 2020-Curren'!$C:$C,'MCC Margin Analysis'!$A$1,'TB & MCC Cost Audit 2020-Curren'!$D:$D,'MCC Margin Analysis'!F$3,'TB & MCC Cost Audit 2020-Curren'!$A:$A,'MCC Margin Analysis'!$B13) -> 0 | G13: =SUMIFS('TB & MCC Cost Audit 2020-Curren'!$P:$P,'TB & MCC Cost Audit 2020-Curren'!$C:$C,'MCC Margin Analysis'!$A$1,'TB & MCC Cost Audit 2020-Curren'!$D:$D,'MCC Margin Analysis'!G$3,'TB & MCC Cost Audit 2020-Curren'!$A:$A,'MCC Margin Analysis'!$B13) -> 0 | J13: =SUMIFS('TB & MCC Cost Audit 2020-Curren'!$W:$W,'TB & MCC Cost Audit 2020-Curren'!$C:$C,'MCC Margin Analysis'!$A$1,'TB & MCC Cost Audit 2020-Curren'!$D:$D,'MCC Margin Analysis'!J$3,'TB & MCC Cost Audit 2020-Curren'!$A:$A,'MCC Margin Analysis'!$B13) -> 0 | K13: =SUMIFS('TB & MCC Cost Audit 2020-Curren'!$W:$W,'TB & MCC Cost Audit 2020-Curren'!$C:$C,'MCC Margin Analysis'!$A$1,'TB & MCC Cost Audit 2020-Curren'!$D:$D,'MCC Margin Analysis'!K$3,'TB & MCC Cost Audit 2020-Curren'!$A:$A,'MCC Margin Analysis'!$B13) -> 0 | L13: =SUMIFS('TB & MCC Cost Audit 2020-Curren'!$W:$W,'TB & MCC Cost Audit 2020-Curren'!$C:$C,'MCC Margin Analysis'!$A$1,'TB & MCC Cost Audit 2020-Curren'!$D:$D,'MCC Margin Analysis'!L$3,'TB & MCC Cost Audit 2020-Curren'!$A:$A,'MCC Margin Analysis'!$B13) -> 0 | M13: =SUMIFS('TB & MCC Cost Audit 2020-Curren'!$W:$W,'TB & MCC Cost Audit 2020-Curren'!$C:$C,'MCC Margin Analysis'!$A$1,'TB & MCC Cost Audit 2020-Curren'!$D:$D,'MCC Margin Analysis'!M$3,'TB & MCC Cost Audit 2020-Curren'!$A:$A,'MCC Margin Analysis'!$B13) -> 0 | N13: =SUMIFS('TB & MCC Cost Audit 2020-Curren'!$W:$W,'TB & MCC Cost Audit 2020-Curren'!$C:$C,'MCC Margin Analysis'!$A$1,'TB & MCC Cost Audit 2020-Curren'!$D:$D,'MCC Margin Analysis'!N$3,'TB & MCC Cost Audit 2020-Curren'!$A:$A,'MCC Margin Analysis'!$B13) -> 0 | Q13: =IFERROR((C13-J13)/C13," - ") -> - | R13: =IFERROR((D13-K13)/D13," - ") -> - | S13: =IFERROR((E13-L13)/E13," - ") -> - | T13: =IFERROR((F13-M13)/F13," - ") -> - | U13: =IFERROR((G13-N13)/G13," - ") -> -
B14: Beverly Hills | C14: =SUMIFS('TB & MCC Cost Audit 2020-Curren'!$P:$P,'TB & MCC Cost Audit 2020-Curren'!$C:$C,'MCC Margin Analysis'!$A$1,'TB & MCC Cost Audit 2020-Curren'!$D:$D,'MCC Margin Analysis'!C$3,'TB & MCC Cost Audit 2020-Curren'!$A:$A,'MCC Margin Analysis'!$B14) -> 25403 | D14: =SUMIFS('TB & MCC Cost Audit 2020-Curren'!$P:$P,'TB & MCC Cost Audit 2020-Curren'!$C:$C,'MCC Margin Analysis'!$A$1,'TB & MCC Cost Audit 2020-Curren'!$D:$D,'MCC Margin Analysis'!D$3,'TB & MCC Cost Audit 2020-Curren'!$A:$A,'MCC Margin Analysis'!$B14) -> 14007 | E14: =SUMIFS('TB & MCC Cost Audit 2020-Curren'!$P:$P,'TB & MCC Cost Audit 2020-Curren'!$C:$C,'MCC Margin Analysis'!$A$1,'TB & MCC Cost Audit 2020-Curren'!$D:$D,'MCC Margin Analysis'!E$3,'TB & MCC Cost Audit 2020-Curren'!$A:$A,'MCC Margin Analysis'!$B14) -> 25403 | F14: =SUMIFS('TB & MCC Cost Audit 2020-Curren'!$P:$P,'TB & MCC Cost Audit 2020-Curren'!$C:$C,'MCC Margin Analysis'!$A$1,'TB & MCC Cost Audit 2020-Curren'!$D:$D,'MCC Margin Analysis'!F$3,'TB & MCC Cost Audit 2020-Curren'!$A:$A,'MCC Margin Analysis'!$B14) -> 25403 | G14: =SUMIFS('TB & MCC Cost Audit 2020-Curren'!$P:$P,'TB & MCC Cost Audit 2020-Curren'!$C:$C,'MCC Margin Analysis'!$A$1,'TB & MCC Cost Audit 2020-Curren'!$D:$D,'MCC Margin Analysis'!G$3,'TB & MCC Cost Audit 2020-Curren'!$A:$A,'MCC Margin Analysis'!$B14) -> 27437 | J14: =SUMIFS('TB & MCC Cost Audit 2020-Curren'!$W:$W,'TB & MCC Cost Audit 2020-Curren'!$C:$C,'MCC Margin Analysis'!$A$1,'TB & MCC Cost Audit 2020-Curren'!$D:$D,'MCC Margin Analysis'!J$3,'TB & MCC Cost Audit 2020-Curren'!$A:$A,'MCC Margin Analysis'!$B14) -> 6594.19 | K14: =SUMIFS('TB & MCC Cost Audit 2020-Curren'!$W:$W,'TB & MCC Cost Audit 2020-Curren'!$C:$C,'MCC Margin Analysis'!$A$1,'TB & MCC Cost Audit 2020-Curren'!$D:$D,'MCC Margin Analysis'!K$3,'TB & MCC Cost Audit 2020-Curren'!$A:$A,'MCC Margin Analysis'!$B14) -> 3321.06 | L14: =SUMIFS('TB & MCC Cost Audit 2020-Curren'!$W:$W,'TB & MCC Cost Audit 2020-Curren'!$C:$C,'MCC Margin Analysis'!$A$1,'TB & MCC Cost Audit 2020-Curren'!$D:$D,'MCC Margin Analysis'!L$3,'TB & MCC Cost Audit 2020-Curren'!$A:$A,'MCC Margin Analysis'!$B14) -> 3361.4 | M14: =SUMIFS('TB & MCC Cost Audit 2020-Curren'!$W:$W,'TB & MCC Cost Audit 2020-Curren'!$C:$C,'MCC Margin Analysis'!$A$1,'TB & MCC Cost Audit 2020-Curren'!$D:$D,'MCC Margin Analysis'!M$3,'TB & MCC Cost Audit 2020-Curren'!$A:$A,'MCC Margin Analysis'!$B14) -> 2951.93 | N14: =SUMIFS('TB & MCC Cost Audit 2020-Curren'!$W:$W,'TB & MCC Cost Audit 2020-Curren'!$C:$C,'MCC Margin Analysis'!$A$1,'TB & MCC Cost Audit 2020-Curren'!$D:$D,'MCC Margin Analysis'!N$3,'TB & MCC Cost Audit 2020-Curren'!$A:$A,'MCC Margin Analysis'!$B14) -> 4240.66 | Q14: =IFERROR((C14-J14)/C14," - ") -> 0.74041688 | R14: =IFERROR((D14-K14)/D14," - ") -> 0.76289998 | S14: =IFERROR((E14-L14)/E14," - ") -> 0.86767705 | T14: =IFERROR((F14-M14)/F14," - ") -> 0.88379601 | U14: =IFERROR((G14-N14)/G14," - ") -> 0.8454401
B15: Birmingham | C15: =SUMIFS('TB & MCC Cost Audit 2020-Curren'!$P:$P,'TB & MCC Cost Audit 2020-Curren'!$C:$C,'MCC Margin Analysis'!$A$1,'TB & MCC Cost Audit 2020-Curren'!$D:$D,'MCC Margin Analysis'!C$3,'TB & MCC Cost Audit 2020-Curren'!$A:$A,'MCC Margin Analysis'!$B15) -> 0 | D15: =SUMIFS('TB & MCC Cost Audit 2020-Curren'!$P:$P,'TB & MCC Cost Audit 2020-Curren'!$C:$C,'MCC Margin Analysis'!$A$1,'TB & MCC Cost Audit 2020-Curren'!$D:$D,'MCC Margin Analysis'!D$3,'TB & MCC Cost Audit 2020-Curren'!$A:$A,'MCC Margin Analysis'!$B15) -> 0 | E15: =SUMIFS('TB & MCC Cost Audit 2020-Curren'!$P:$P,'TB & MCC Cost Audit 2020-Curren'!$C:$C,'MCC Margin Analysis'!$A$1,'TB & MCC Cost Audit 2020-Curren'!$D:$D,'MCC Margin Analysis'!E$3,'TB & MCC Cost Audit 2020-Curren'!$A:$A,'MCC Margin Analysis'!$B15) -> 6188 | F15: =SUMIFS('TB & MCC Cost Audit 2020-Curren'!$P:$P,'TB & MCC Cost Audit 2020-Curren'!$C:$C,'MCC Margin Analysis'!$A$1,'TB & MCC Cost Audit 2020-Curren'!$D:$D,'MCC Margin Analysis'!F$3,'TB & MCC Cost Audit 2020-Curren'!$A:$A,'MCC Margin Analysis'!$B15) -> 0 | G15: =SUMIFS('TB & MCC Cost Audit 2020-Curren'!$P:$P,'TB & MCC Cost Audit 2020-Curren'!$C:$C,'MCC Margin Analysis'!$A$1,'TB & MCC Cost Audit 2020-Curren'!$D:$D,'MCC Margin Analysis'!G$3,'TB & MCC Cost Audit 2020-Curren'!$A:$A,'MCC Margin Analysis'!$B15) -> 0 | J15: =SUMIFS('TB & MCC Cost Audit 2020-Curren'!$W:$W,'TB & MCC Cost Audit 2020-Curren'!$C:$C,'MCC Margin Analysis'!$A$1,'TB & MCC Cost Audit 2020-Curren'!$D:$D,'MCC Margin Analysis'!J$3,'TB & MCC Cost Audit 2020-Curren'!$A:$A,'MCC Margin Analysis'!$B15) -> 0 | K15: =SUMIFS('TB & MCC Cost Audit 2020-Curren'!$W:$W,'TB & MCC Cost Audit 2020-Curren'!$C:$C,'MCC Margin Analysis'!$A$1,'TB & MCC Cost Audit 2020-Curren'!$D:$D,'MCC Margin Analysis'!K$3,'TB & MCC Cost Audit 2020-Curren'!$A:$A,'MCC Margin Analysis'!$B15) -> 0 | L15: =SUMIFS('TB & MCC Cost Audit 2020-Curren'!$W:$W,'TB & MCC Cost Audit 2020-Curren'!$C:$C,'MCC Margin Analysis'!$A$1,'TB & MCC Cost Audit 2020-Curren'!$D:$D,'MCC Margin Analysis'!L$3,'TB & MCC Cost Audit 2020-Curren'!$A:$A,'MCC Margin Analysis'!$B15) -> 830.28 | M15: =SUMIFS('TB & MCC Cost Audit 2020-Curren'!$W:$W,'TB & MCC Cost Audit 2020-Curren'!$C:$C,'MCC Margin Analysis'!$A$1,'TB & MCC Cost Audit 2020-Curren'!$D:$D,'MCC Margin Analysis'!M$3,'TB & MCC Cost Audit 2020-Curren'!$A:$A,'MCC Margin Analysis'!$B15) -> 0 | N15: =SUMIFS('TB & MCC Cost Audit 2020-Curren'!$W:$W,'TB & MCC Cost Audit 2020-Curren'!$C:$C,'MCC Margin Analysis'!$A$1,'TB & MCC Cost Audit 2020-Curren'!$D:$D,'MCC Margin Analysis'!N$3,'TB & MCC Cost Audit 2020-Curren'!$A:$A,'MCC Margin Analysis'!$B15) -> 0 | Q15: =IFERROR((C15-J15)/C15," - ") -> - | R15: =IFERROR((D15-K15)/D15," - ") -> - | S15: =IFERROR((E15-L15)/E15," - ") -> 0.86582418 | T15: =IFERROR((F15-M15)/F15," - ") -> - | U15: =IFERROR((G15-N15)/G15," - ") -> -
... B96: WSSC | C96: =SUMIFS('TB & MCC Cost Audit 2020-Curren'!$P:$P,'TB & MCC Cost Audit 2020-Curren'!$C:$C,'MCC Margin Analysis'!$A$1,'TB & MCC Cost Audit 2020-Curren'!$D:$D,'MCC Margin Analysis'!C$3,'TB & MCC Cost Audit 2020-Curren'!$A:$A,'MCC Margin Analysis'!$B96) -> 0 | D96: =SUMIFS('TB & MCC Cost Audit 2020-Curren'!$P:$P,'TB & MCC Cost Audit 2020-Curren'!$C:$C,'MCC Margin Analysis'!$A$1,'TB & MCC Cost Audit 2020-Curren'!$D:$D,'MCC Margin Analysis'!D$3,'TB & MCC Cost Audit 2020-Curren'!$A:$A,'MCC Margin Analysis'!$B96) -> 0 | E96: =SUMIFS('TB & MCC Cost Audit 2020-Curren'!$P:$P,'TB & MCC Cost Audit 2020-Curren'!$C:$C,'MCC Margin Analysis'!$A$1,'TB & MCC Cost Audit 2020-Curren'!$D:$D,'MCC Margin Analysis'!E$3,'TB & MCC Cost Audit 2020-Curren'!$A:$A,'MCC Margin Analysis'!$B96) -> 50646 | F96: =SUMIFS('TB & MCC Cost Audit 2020-Curren'!$P:$P,'TB & MCC Cost Audit 2020-Curren'!$C:$C,'MCC Margin Analysis'!$A$1,'TB & MCC Cost Audit 2020-Curren'!$D:$D,'MCC Margin Analysis'!F$3,'TB & MCC Cost Audit 2020-Curren'!$A:$A,'MCC Margin Analysis'!$B96) -> 53179 | G96: =SUMIFS('TB & MCC Cost Audit 2020-Curren'!$P:$P,'TB & MCC Cost Audit 2020-Curren'!$C:$C,'MCC Margin Analysis'!$A$1,'TB & MCC Cost Audit 2020-Curren'!$D:$D,'MCC Margin Analysis'!G$3,'TB & MCC Cost Audit 2020-Curren'!$A:$A,'MCC Margin Analysis'!$B96) -> 68641 | J96: =SUMIFS('TB & MCC Cost Audit 2020-Curren'!$W:$W,'TB & MCC Cost Audit 2020-Curren'!$C:$C,'MCC Margin Analysis'!$A$1,'TB & MCC Cost Audit 2020-Curren'!$D:$D,'MCC Margin Analysis'!J$3,'TB & MCC Cost Audit 2020-Curren'!$A:$A,'MCC Margin Analysis'!$B96) -> 0 | K96: =SUMIFS('TB & MCC Cost Audit 2020-Curren'!$W:$W,'TB & MCC Cost Audit 2020-Curren'!$C:$C,'MCC Margin Analysis'!$A$1,'TB & MCC Cost Audit 2020-Curren'!$D:$D,'MCC Margin Analysis'!K$3,'TB & MCC Cost Audit 2020-Curren'!$A:$A,'MCC Margin Analysis'!$B96) -> 0 | L96: =SUMIFS('TB & MCC Cost Audit 2020-Curren'!$W:$W,'TB & MCC Cost Audit 2020-Curren'!$C:$C,'MCC Margin Analysis'!$A$1,'TB & MCC Cost Audit 2020-Curren'!$D:$D,'MCC Margin Analysis'!L$3,'TB & MCC Cost Audit 2020-Curren'!$A:$A,'MCC Margin Analysis'!$B96) -> 8422.62 | M96: =SUMIFS('TB & MCC Cost Audit 2020-Curren'!$W:$W,'TB & MCC Cost Audit 2020-Curren'!$C:$C,'MCC Margin Analysis'!$A$1,'TB & MCC Cost Audit 2020-Curren'!$D:$D,'MCC Margin Analysis'!M$3,'TB & MCC Cost Audit 2020-Curren'!$A:$A,'MCC Margin Analysis'!$B96) -> 10801.52 | N96: =SUMIFS('TB & MCC Cost Audit 2020-Curren'!$W:$W,'TB & MCC Cost Audit 2020-Curren'!$C:$C,'MCC Margin Analysis'!$A$1,'TB & MCC Cost Audit 2020-Curren'!$D:$D,'MCC Margin Analysis'!N$3,'TB & MCC Cost Audit 2020-Curren'!$A:$A,'MCC Margin Analysis'!$B96) -> 7547.82 | Q96: =IFERROR((C96-J96)/C96," - ") -> - | R96: =IFERROR((D96-K96)/D96," - ") -> - | S96: =IFERROR((E96-L96)/E96," - ") -> 0.83369624 | T96: =IFERROR((F96-M96)/F96," - ") -> 0.79688373 | U96: =IFERROR((G96-N96)/G96," - ") -> 0.89003919

Sheet TB Type Margin Analysis
A1: TB
C2: =SUM(C4:C25) -> 3737600.8 | D2: =SUM(D4:D25) -> 4012052.8 | E2: =SUM(E4:E25) -> 3798485.8 | F2: =SUM(F4:F25) -> 5703742.2 | G2: =SUM(G4:G25) -> 4950309.3 | H2: =SUM(H4:H25) -> 7102651.4 | K2: =SUM(K4:K25) -> 1426781.2 | L2: =SUM(L4:L25) -> 1158465.4 | M2: =SUM(M4:M25) -> 944457.63 | N2: =SUM(N4:N25) -> 1496909.7 | O2: =SUM(O4:O25) -> 1179886.9 | P2: =SUM(P4:P25) -> 1437588 | S2: =IFERROR((C2-K2)/C2," - ") -> 0.61826282 | T2: =IFERROR((D2-L2)/D2," - ") -> 0.7112537 | U2: =IFERROR((E2-M2)/E2," - ") -> 0.75135944 | V2: =IFERROR((F2-N2)/F2," - ") -> 0.73755657 | W2: =IFERROR((G2-O2)/G2," - ") -> 0.7616539 | X2: =IFERROR((H2-P2)/H2," - ") -> 0.7975984
A3: Rev | B3: TB Type | C3: 2020 | D3: 2021 | E3: =D3+1 -> 2022 | F3: =E3+1 -> 2023 | G3: =F3+1 -> 2024 | H3: =G3+1 -> 2025 | J3: COGS | K3: 2020 | L3: 2021 | M3: =L3+1 -> 2022 | N3: =M3+1 -> 2023 | O3: =N3+1 -> 2024 | P3: =O3+1 -> 2025 | R3: GPM % | S3: 2020 | T3: 2021 | U3: =T3+1 -> 2022 | V3: =U3+1 -> 2023 | W3: =V3+1 -> 2024 | X3: =W3+1 -> 2025
B4: DISC | C4: =SUMIFS('TB & MCC Cost Audit 2020-Curren'!$P:$P,'TB & MCC Cost Audit 2020-Curren'!$C:$C,'TB Type Margin Analysis'!$B4,'TB & MCC Cost Audit 2020-Curren'!$D:$D,'TB Type Margin Analysis'!C$3) -> 0 | D4: =SUMIFS('TB & MCC Cost Audit 2020-Curren'!$P:$P,'TB & MCC Cost Audit 2020-Curren'!$C:$C,'TB Type Margin Analysis'!$B4,'TB & MCC Cost Audit 2020-Curren'!$D:$D,'TB Type Margin Analysis'!D$3) -> 0 | E4: =SUMIFS('TB & MCC Cost Audit 2020-Curren'!$P:$P,'TB & MCC Cost Audit 2020-Curren'!$C:$C,'TB Type Margin Analysis'!$B4,'TB & MCC Cost Audit 2020-Curren'!$D:$D,'TB Type Margin Analysis'!E$3) -> 0 | F4: =SUMIFS('TB & MCC Cost Audit 2020-Curren'!$P:$P,'TB & MCC Cost Audit 2020-Curren'!$C:$C,'TB Type Margin Analysis'!$B4,'TB & MCC Cost Audit 2020-Curren'!$D:$D,'TB Type Margin Analysis'!F$3) -> 0 | G4: =SUMIFS('TB & MCC Cost Audit 2020-Curren'!$P:$P,'TB & MCC Cost Audit 2020-Curren'!$C:$C,'TB Type Margin Analysis'!$B4,'TB & MCC Cost Audit 2020-Curren'!$D:$D,'TB Type Margin Analysis'!G$3) -> 0 | H4: =SUMIFS('TB & MCC Cost Audit 2020-Curren'!$P:$P,'TB & MCC Cost Audit 2020-Curren'!$C:$C,'TB Type Margin Analysis'!$B4,'TB & MCC Cost Audit 2020-Curren'!$D:$D,'TB Type Margin Analysis'!H$3) -> 0 | K4: =SUMIFS('TB & MCC Cost Audit 2020-Curren'!$W:$W,'TB & MCC Cost Audit 2020-Curren'!$C:$C,'TB Type Margin Analysis'!$B4,'TB & MCC Cost Audit 2020-Curren'!$D:$D,'TB Type Margin Analysis'!K$3) -> 0 | L4: =SUMIFS('TB & MCC Cost Audit 2020-Curren'!$W:$W,'TB & MCC Cost Audit 2020-Curren'!$C:$C,'TB Type Margin Analysis'!$B4,'TB & MCC Cost Audit 2020-Curren'!$D:$D,'TB Type Margin Analysis'!L$3) -> 0 | M4: =SUMIFS('TB & MCC Cost Audit 2020-Curren'!$W:$W,'TB & MCC Cost Audit 2020-Curren'!$C:$C,'TB Type Margin Analysis'!$B4,'TB & MCC Cost Audit 2020-Curren'!$D:$D,'TB Type Margin Analysis'!M$3) -> 0 | N4: =SUMIFS('TB & MCC Cost Audit 2020-Curren'!$W:$W,'TB & MCC Cost Audit 2020-Curren'!$C:$C,'TB Type Margin Analysis'!$B4,'TB & MCC Cost Audit 2020-Curren'!$D:$D,'TB Type Margin Analysis'!N$3) -> 0 | O4: =SUMIFS('TB & MCC Cost Audit 2020-Curren'!$W:$W,'TB & MCC Cost Audit 2020-Curren'!$C:$C,'TB Type Margin Analysis'!$B4,'TB & MCC Cost Audit 2020-Curren'!$D:$D,'TB Type Margin Analysis'!O$3) -> 0 | P4: =SUMIFS('TB & MCC Cost Audit 2020-Curren'!$W:$W,'TB & MCC Cost Audit 2020-Curren'!$C:$C,'TB Type Margin Analysis'!$B4,'TB & MCC Cost Audit 2020-Curren'!$D:$D,'TB Type Margin Analysis'!P$3) -> 0 | S4: =IFERROR((C4-K4)/C4," - ") -> - | T4: =IFERROR((D4-L4)/D4," - ") -> - | U4: =IFERROR((E4-M4)/E4," - ") -> - | V4: =IFERROR((F4-N4)/F4," - ") -> - | W4: =IFERROR((G4-O4)/G4," - ") -> - | X4: =IFERROR((H4-P4)/H4," - ") -> -
B5: DRM3 | C5: =SUMIFS('TB & MCC Cost Audit 2020-Curren'!$P:$P,'TB & MCC Cost Audit 2020-Curren'!$C:$C,'TB Type Margin Analysis'!$B5,'TB & MCC Cost Audit 2020-Curren'!$D:$D,'TB Type Margin Analysis'!C$3) -> 313901 | D5: =SUMIFS('TB & MCC Cost Audit 2020-Curren'!$P:$P,'TB & MCC Cost Audit 2020-Curren'!$C:$C,'TB Type Margin Analysis'!$B5,'TB & MCC Cost Audit 2020-Curren'!$D:$D,'TB Type Margin Analysis'!D$3) -> 451983.42 | E5: =SUMIFS('TB & MCC Cost Audit 2020-Curren'!$P:$P,'TB & MCC Cost Audit 2020-Curren'!$C:$C,'TB Type Margin Analysis'!$B5,'TB & MCC Cost Audit 2020-Curren'!$D:$D,'TB Type Margin Analysis'!E$3) -> 394747 | F5: =SUMIFS('TB & MCC Cost Audit 2020-Curren'!$P:$P,'TB & MCC Cost Audit 2020-Curren'!$C:$C,'TB Type Margin Analysis'!$B5,'TB & MCC Cost Audit 2020-Curren'!$D:$D,'TB Type Margin Analysis'!F$3) -> 552224 | G5: =SUMIFS('TB & MCC Cost Audit 2020-Curren'!$P:$P,'TB & MCC Cost Audit 2020-Curren'!$C:$C,'TB Type Margin Analysis'!$B5,'TB & MCC Cost Audit 2020-Curren'!$D:$D,'TB Type Margin Analysis'!G$3) -> 652359 | H5: =SUMIFS('TB & MCC Cost Audit 2020-Curren'!$P:$P,'TB & MCC Cost Audit 2020-Curren'!$C:$C,'TB Type Margin Analysis'!$B5,'TB & MCC Cost Audit 2020-Curren'!$D:$D,'TB Type Margin Analysis'!H$3) -> 977972 | K5: =SUMIFS('TB & MCC Cost Audit 2020-Curren'!$W:$W,'TB & MCC Cost Audit 2020-Curren'!$C:$C,'TB Type Margin Analysis'!$B5,'TB & MCC Cost Audit 2020-Curren'!$D:$D,'TB Type Margin Analysis'!K$3) -> 3901.15 | L5: =SUMIFS('TB & MCC Cost Audit 2020-Curren'!$W:$W,'TB & MCC Cost Audit 2020-Curren'!$C:$C,'TB Type Margin Analysis'!$B5,'TB & MCC Cost Audit 2020-Curren'!$D:$D,'TB Type Margin Analysis'!L$3) -> 16657.18 | M5: =SUMIFS('TB & MCC Cost Audit 2020-Curren'!$W:$W,'TB & MCC Cost Audit 2020-Curren'!$C:$C,'TB Type Margin Analysis'!$B5,'TB & MCC Cost Audit 2020-Curren'!$D:$D,'TB Type Margin Analysis'!M$3) -> 26161.57 | N5: =SUMIFS('TB & MCC Cost Audit 2020-Curren'!$W:$W,'TB & MCC Cost Audit 2020-Curren'!$C:$C,'TB Type Margin Analysis'!$B5,'TB & MCC Cost Audit 2020-Curren'!$D:$D,'TB Type Margin Analysis'!N$3) -> 21279.75 | O5: =SUMIFS('TB & MCC Cost Audit 2020-Curren'!$W:$W,'TB & MCC Cost Audit 2020-Curren'!$C:$C,'TB Type Margin Analysis'!$B5,'TB & MCC Cost Audit 2020-Curren'!$D:$D,'TB Type Margin Analysis'!O$3) -> 32999.21 | P5: =SUMIFS('TB & MCC Cost Audit 2020-Curren'!$W:$W,'TB & MCC Cost Audit 2020-Curren'!$C:$C,'TB Type Margin Analysis'!$B5,'TB & MCC Cost Audit 2020-Curren'!$D:$D,'TB Type Margin Analysis'!P$3) -> 42412.24 | S5: =IFERROR((C5-K5)/C5," - ") -> 0.98757204 | T5: =IFERROR((D5-L5)/D5," - ") -> 0.96314648 | U5: =IFERROR((E5-M5)/E5," - ") -> 0.93372573 | V5: =IFERROR((F5-N5)/F5," - ") -> 0.96146537 | W5: =IFERROR((G5-O5)/G5," - ") -> 0.94941557 | X5: =IFERROR((H5-P5)/H5," - ") -> 0.95663246
B6: DRMCC | C6: =SUMIFS('TB & MCC Cost Audit 2020-Curren'!$P:$P,'TB & MCC Cost Audit 2020-Curren'!$C:$C,'TB Type Margin Analysis'!$B6,'TB & MCC Cost Audit 2020-Curren'!$D:$D,'TB Type Margin Analysis'!C$3) -> 64320 | D6: =SUMIFS('TB & MCC Cost Audit 2020-Curren'!$P:$P,'TB & MCC Cost Audit 2020-Curren'!$C:$C,'TB Type Margin Analysis'!$B6,'TB & MCC Cost Audit 2020-Curren'!$D:$D,'TB Type Margin Analysis'!D$3) -> 115461.01 | E6: =SUMIFS('TB & MCC Cost Audit 2020-Curren'!$P:$P,'TB & MCC Cost Audit 2020-Curren'!$C:$C,'TB Type Margin Analysis'!$B6,'TB & MCC Cost Audit 2020-Curren'!$D:$D,'TB Type Margin Analysis'!E$3) -> 0 | F6: =SUMIFS('TB & MCC Cost Audit 2020-Curren'!$P:$P,'TB & MCC Cost Audit 2020-Curren'!$C:$C,'TB Type Margin Analysis'!$B6,'TB & MCC Cost Audit 2020-Curren'!$D:$D,'TB Type Margin Analysis'!F$3) -> 213663.68 | G6: =SUMIFS('TB & MCC Cost Audit 2020-Curren'!$P:$P,'TB & MCC Cost Audit 2020-Curren'!$C:$C,'TB Type Margin Analysis'!$B6,'TB & MCC Cost Audit 2020-Curren'!$D:$D,'TB Type Margin Analysis'!G$3) -> 0 | H6: =SUMIFS('TB & MCC Cost Audit 2020-Curren'!$P:$P,'TB & MCC Cost Audit 2020-Curren'!$C:$C,'TB Type Margin Analysis'!$B6,'TB & MCC Cost Audit 2020-Curren'!$D:$D,'TB Type Margin Analysis'!H$3) -> 0 | K6: =SUMIFS('TB & MCC Cost Audit 2020-Curren'!$W:$W,'TB & MCC Cost Audit 2020-Curren'!$C:$C,'TB Type Margin Analysis'!$B6,'TB & MCC Cost Audit 2020-Curren'!$D:$D,'TB Type Margin Analysis'!K$3) -> 0 | L6: =SUMIFS('TB & MCC Cost Audit 2020-Curren'!$W:$W,'TB & MCC Cost Audit 2020-Curren'!$C:$C,'TB Type Margin Analysis'!$B6,'TB & MCC Cost Audit 2020-Curren'!$D:$D,'TB Type Margin Analysis'!L$3) -> 0 | M6: =SUMIFS('TB & MCC Cost Audit 2020-Curren'!$W:$W,'TB & MCC Cost Audit 2020-Curren'!$C:$C,'TB Type Margin Analysis'!$B6,'TB & MCC Cost Audit 2020-Curren'!$D:$D,'TB Type Margin Analysis'!M$3) -> 0 | N6: =SUMIFS('TB & MCC Cost Audit 2020-Curren'!$W:$W,'TB & MCC Cost Audit 2020-Curren'!$C:$C,'TB Type Margin Analysis'!$B6,'TB & MCC Cost Audit 2020-Curren'!$D:$D,'TB Type Margin Analysis'!N$3) -> 0 | O6: =SUMIFS('TB & MCC Cost Audit 2020-Curren'!$W:$W,'TB & MCC Cost Audit 2020-Curren'!$C:$C,'TB Type Margin Analysis'!$B6,'TB & MCC Cost Audit 2020-Curren'!$D:$D,'TB Type Margin Analysis'!O$3) -> 0 | P6: =SUMIFS('TB & MCC Cost Audit 2020-Curren'!$W:$W,'TB & MCC Cost Audit 2020-Curren'!$C:$C,'TB Type Margin Analysis'!$B6,'TB & MCC Cost Audit 2020-Curren'!$D:$D,'TB Type Margin Analysis'!P$3) -> 0 | S6: =IFERROR((C6-K6)/C6," - ") -> 1 | T6: =IFERROR((D6-L6)/D6," - ") -> 1 | U6: =IFERROR((E6-M6)/E6," - ") -> - | V6: =IFERROR((F6-N6)/F6," - ") -> 1 | W6: =IFERROR((G6-O6)/G6," - ") -> - | X6: =IFERROR((H6-P6)/H6," - ") -> -
B7: DRTBIN | C7: =SUMIFS('TB & MCC Cost Audit 2020-Curren'!$P:$P,'TB & MCC Cost Audit 2020-Curren'!$C:$C,'TB Type Margin Analysis'!$B7,'TB & MCC Cost Audit 2020-Curren'!$D:$D,'TB Type Margin Analysis'!C$3) -> 0 | D7: =SUMIFS('TB & MCC Cost Audit 2020-Curren'!$P:$P,'TB & MCC Cost Audit 2020-Curren'!$C:$C,'TB Type Margin Analysis'!$B7,'TB & MCC Cost Audit 2020-Curren'!$D:$D,'TB Type Margin Analysis'!D$3) -> 28239.36 | E7: =SUMIFS('TB & MCC Cost Audit 2020-Curren'!$P:$P,'TB & MCC Cost Audit 2020-Curren'!$C:$C,'TB Type Margin Analysis'!$B7,'TB & MCC Cost Audit 2020-Curren'!$D:$D,'TB Type Margin Analysis'!E$3) -> 0 | F7: =SUMIFS('TB & MCC Cost Audit 2020-Curren'!$P:$P,'TB & MCC Cost Audit 2020-Curren'!$C:$C,'TB Type Margin Analysis'!$B7,'TB & MCC Cost Audit 2020-Curren'!$D:$D,'TB Type Margin Analysis'!F$3) -> 0 | G7: =SUMIFS('TB & MCC Cost Audit 2020-Curren'!$P:$P,'TB & MCC Cost Audit 2020-Curren'!$C:$C,'TB Type Margin Analysis'!$B7,'TB & MCC Cost Audit 2020-Curren'!$D:$D,'TB Type Margin Analysis'!G$3) -> 0 | H7: =SUMIFS('TB & MCC Cost Audit 2020-Curren'!$P:$P,'TB & MCC Cost Audit 2020-Curren'!$C:$C,'TB Type Margin Analysis'!$B7,'TB & MCC Cost Audit 2020-Curren'!$D:$D,'TB Type Margin Analysis'!H$3) -> 0 | K7: =SUMIFS('TB & MCC Cost Audit 2020-Curren'!$W:$W,'TB & MCC Cost Audit 2020-Curren'!$C:$C,'TB Type Margin Analysis'!$B7,'TB & MCC Cost Audit 2020-Curren'!$D:$D,'TB Type Margin Analysis'!K$3) -> 0 | L7: =SUMIFS('TB & MCC Cost Audit 2020-Curren'!$W:$W,'TB & MCC Cost Audit 2020-Curren'!$C:$C,'TB Type Margin Analysis'!$B7,'TB & MCC Cost Audit 2020-Curren'!$D:$D,'TB Type Margin Analysis'!L$3) -> 0 | M7: =SUMIFS('TB & MCC Cost Audit 2020-Curren'!$W:$W,'TB & MCC Cost Audit 2020-Curren'!$C:$C,'TB Type Margin Analysis'!$B7,'TB & MCC Cost Audit 2020-Curren'!$D:$D,'TB Type Margin Analysis'!M$3) -> 0 | N7: =SUMIFS('TB & MCC Cost Audit 2020-Curren'!$W:$W,'TB & MCC Cost Audit 2020-Curren'!$C:$C,'TB Type Margin Analysis'!$B7,'TB & MCC Cost Audit 2020-Curren'!$D:$D,'TB Type Margin Analysis'!N$3) -> 0 | O7: =SUMIFS('TB & MCC Cost Audit 2020-Curren'!$W:$W,'TB & MCC Cost Audit 2020-Curren'!$C:$C,'TB Type Margin Analysis'!$B7,'TB & MCC Cost Audit 2020-Curren'!$D:$D,'TB Type Margin Analysis'!O$3) -> 0 | P7: =SUMIFS('TB & MCC Cost Audit 2020-Curren'!$W:$W,'TB & MCC Cost Audit 2020-Curren'!$C:$C,'TB Type Margin Analysis'!$B7,'TB & MCC Cost Audit 2020-Curren'!$D:$D,'TB Type Margin Analysis'!P$3) -> 0 | S7: =IFERROR((C7-K7)/C7," - ") -> - | T7: =IFERROR((D7-L7)/D7," - ") -> 1 | U7: =IFERROR((E7-M7)/E7," - ") -> - | V7: =IFERROR((F7-N7)/F7," - ") -> - | W7: =IFERROR((G7-O7)/G7," - ") -> - | X7: =IFERROR((H7-P7)/H7," - ") -> -
B8: FFEE | C8: =SUMIFS('TB & MCC Cost Audit 2020-Curren'!$P:$P,'TB & MCC Cost Audit 2020-Curren'!$C:$C,'TB Type Margin Analysis'!$B8,'TB & MCC Cost Audit 2020-Curren'!$D:$D,'TB Type Margin Analysis'!C$3) -> 0 | D8: =SUMIFS('TB & MCC Cost Audit 2020-Curren'!$P:$P,'TB & MCC Cost Audit 2020-Curren'!$C:$C,'TB Type Margin Analysis'!$B8,'TB & MCC Cost Audit 2020-Curren'!$D:$D,'TB Type Margin Analysis'!D$3) -> 0 | E8: =SUMIFS('TB & MCC Cost Audit 2020-Curren'!$P:$P,'TB & MCC Cost Audit 2020-Curren'!$C:$C,'TB Type Margin Analysis'!$B8,'TB & MCC Cost Audit 2020-Curren'!$D:$D,'TB Type Margin Analysis'!E$3) -> 0 | F8: =SUMIFS('TB & MCC Cost Audit 2020-Curren'!$P:$P,'TB & MCC Cost Audit 2020-Curren'!$C:$C,'TB Type Margin Analysis'!$B8,'TB & MCC Cost Audit 2020-Curren'!$D:$D,'TB Type Margin Analysis'!F$3) -> 45403.05 | G8: =SUMIFS('TB & MCC Cost Audit 2020-Curren'!$P:$P,'TB & MCC Cost Audit 2020-Curren'!$C:$C,'TB Type Margin Analysis'!$B8,'TB & MCC Cost Audit 2020-Curren'!$D:$D,'TB Type Margin Analysis'!G$3) -> 0 | H8: =SUMIFS('TB & MCC Cost Audit 2020-Curren'!$P:$P,'TB & MCC Cost Audit 2020-Curren'!$C:$C,'TB Type Margin Analysis'!$B8,'TB & MCC Cost Audit 2020-Curren'!$D:$D,'TB Type Margin Analysis'!H$3) -> 0 | K8: =SUMIFS('TB & MCC Cost Audit 2020-Curren'!$W:$W,'TB & MCC Cost Audit 2020-Curren'!$C:$C,'TB Type Margin Analysis'!$B8,'TB & MCC Cost Audit 2020-Curren'!$D:$D,'TB Type Margin Analysis'!K$3) -> 0 | L8: =SUMIFS('TB & MCC Cost Audit 2020-Curren'!$W:$W,'TB & MCC Cost Audit 2020-Curren'!$C:$C,'TB Type Margin Analysis'!$B8,'TB & MCC Cost Audit 2020-Curren'!$D:$D,'TB Type Margin Analysis'!L$3) -> 0 | M8: =SUMIFS('TB & MCC Cost Audit 2020-Curren'!$W:$W,'TB & MCC Cost Audit 2020-Curren'!$C:$C,'TB Type Margin Analysis'!$B8,'TB & MCC Cost Audit 2020-Curren'!$D:$D,'TB Type Margin Analysis'!M$3) -> 0 | N8: =SUMIFS('TB & MCC Cost Audit 2020-Curren'!$W:$W,'TB & MCC Cost Audit 2020-Curren'!$C:$C,'TB Type Margin Analysis'!$B8,'TB & MCC Cost Audit 2020-Curren'!$D:$D,'TB Type Margin Analysis'!N$3) -> 45403 | O8: =SUMIFS('TB & MCC Cost Audit 2020-Curren'!$W:$W,'TB & MCC Cost Audit 2020-Curren'!$C:$C,'TB Type Margin Analysis'!$B8,'TB & MCC Cost Audit 2020-Curren'!$D:$D,'TB Type Margin Analysis'!O$3) -> 0 | P8: =SUMIFS('TB & MCC Cost Audit 2020-Curren'!$W:$W,'TB & MCC Cost Audit 2020-Curren'!$C:$C,'TB Type Margin Analysis'!$B8,'TB & MCC Cost Audit 2020-Curren'!$D:$D,'TB Type Margin Analysis'!P$3) -> 0 | S8: =IFERROR((C8-K8)/C8," - ") -> - | T8: =IFERROR((D8-L8)/D8," - ") -> - | U8: =IFERROR((E8-M8)/E8," - ") -> - | V8: =IFERROR((F8-N8)/F8," - ") -> 1.1012476e-06 | W8: =IFERROR((G8-O8)/G8," - ") -> - | X8: =IFERROR((H8-P8)/H8," - ") -> -
B9: FSPT | C9: =SUMIFS('TB & MCC Cost Audit 2020-Curren'!$P:$P,'TB & MCC Cost Audit 2020-Curren'!$C:$C,'TB Type Margin Analysis'!$B9,'TB & MCC Cost Audit 2020-Curren'!$D:$D,'TB Type Margin Analysis'!C$3) -> 11154.45 | D9: =SUMIFS('TB & MCC Cost Audit 2020-Curren'!$P:$P,'TB & MCC Cost Audit 2020-Curren'!$C:$C,'TB Type Margin Analysis'!$B9,'TB & MCC Cost Audit 2020-Curren'!$D:$D,'TB Type Margin Analysis'!D$3) -> 0 | E9: =SUMIFS('TB & MCC Cost Audit 2020-Curren'!$P:$P,'TB & MCC Cost Audit 2020-Curren'!$C:$C,'TB Type Margin Analysis'!$B9,'TB & MCC Cost Audit 2020-Curren'!$D:$D,'TB Type Margin Analysis'!E$3) -> 0 | F9: =SUMIFS('TB & MCC Cost Audit 2020-Curren'!$P:$P,'TB & MCC Cost Audit 2020-Curren'!$C:$C,'TB Type Margin Analysis'!$B9,'TB & MCC Cost Audit 2020-Curren'!$D:$D,'TB Type Margin Analysis'!F$3) -> 0 | G9: =SUMIFS('TB & MCC Cost Audit 2020-Curren'!$P:$P,'TB & MCC Cost Audit 2020-Curren'!$C:$C,'TB Type Margin Analysis'!$B9,'TB & MCC Cost Audit 2020-Curren'!$D:$D,'TB Type Margin Analysis'!G$3) -> 0 | H9: =SUMIFS('TB & MCC Cost Audit 2020-Curren'!$P:$P,'TB & MCC Cost Audit 2020-Curren'!$C:$C,'TB Type Margin Analysis'!$B9,'TB & MCC Cost Audit 2020-Curren'!$D:$D,'TB Type Margin Analysis'!H$3) -> 0 | K9: =SUMIFS('TB & MCC Cost Audit 2020-Curren'!$W:$W,'TB & MCC Cost Audit 2020-Curren'!$C:$C,'TB Type Margin Analysis'!$B9,'TB & MCC Cost Audit 2020-Curren'!$D:$D,'TB Type Margin Analysis'!K$3) -> 7110.1 | L9: =SUMIFS('TB & MCC Cost Audit 2020-Curren'!$W:$W,'TB & MCC Cost Audit 2020-Curren'!$C:$C,'TB Type Margin Analysis'!$B9,'TB & MCC Cost Audit 2020-Curren'!$D:$D,'TB Type Margin Analysis'!L$3) -> 0 | M9: =SUMIFS('TB & MCC Cost Audit 2020-Curren'!$W:$W,'TB & MCC Cost Audit 2020-Curren'!$C:$C,'TB Type Margin Analysis'!$B9,'TB & MCC Cost Audit 2020-Curren'!$D:$D,'TB Type Margin Analysis'!M$3) -> 0 | N9: =SUMIFS('TB & MCC Cost Audit 2020-Curren'!$W:$W,'TB & MCC Cost Audit 2020-Curren'!$C:$C,'TB Type Margin Analysis'!$B9,'TB & MCC Cost Audit 2020-Curren'!$D:$D,'TB Type Margin Analysis'!N$3) -> 0 | O9: =SUMIFS('TB & MCC Cost Audit 2020-Curren'!$W:$W,'TB & MCC Cost Audit 2020-Curren'!$C:$C,'TB Type Margin Analysis'!$B9,'TB & MCC Cost Audit 2020-Curren'!$D:$D,'TB Type Margin Analysis'!O$3) -> 0 | P9: =SUMIFS('TB & MCC Cost Audit 2020-Curren'!$W:$W,'TB & MCC Cost Audit 2020-Curren'!$C:$C,'TB Type Margin Analysis'!$B9,'TB & MCC Cost Audit 2020-Curren'!$D:$D,'TB Type Margin Analysis'!P$3) -> 0 | S9: =IFERROR((C9-K9)/C9," - ") -> 0.36257727 | T9: =IFERROR((D9-L9)/D9," - ") -> - | U9: =IFERROR((E9-M9)/E9," - ") -> - | V9: =IFERROR((F9-N9)/F9," - ") -> - | W9: =IFERROR((G9-O9)/G9," - ") -> - | X9: =IFERROR((H9-P9)/H9," - ") -> -
B10: M3IN | C10: =SUMIFS('TB & MCC Cost Audit 2020-Curren'!$P:$P,'TB & MCC Cost Audit 2020-Curren'!$C:$C,'TB Type Margin Analysis'!$B10,'TB & MCC Cost Audit 2020-Curren'!$D:$D,'TB Type Margin Analysis'!C$3) -> 158437 | D10: =SUMIFS('TB & MCC Cost Audit 2020-Curren'!$P:$P,'TB & MCC Cost Audit 2020-Curren'!$C:$C,'TB Type Margin Analysis'!$B10,'TB & MCC Cost Audit 2020-Curren'!$D:$D,'TB Type Margin Analysis'!D$3) -> 112807.05 | E10: =SUMIFS('TB & MCC Cost Audit 2020-Curren'!$P:$P,'TB & MCC Cost Audit 2020-Curren'!$C:$C,'TB Type Margin Analysis'!$B10,'TB & MCC Cost Audit 2020-Curren'!$D:$D,'TB Type Margin Analysis'!E$3) -> 41875 | F10: =SUMIFS('TB & MCC Cost Audit 2020-Curren'!$P:$P,'TB & MCC Cost Audit 2020-Curren'!$C:$C,'TB Type Margin Analysis'!$B10,'TB & MCC Cost Audit 2020-Curren'!$D:$D,'TB Type Margin Analysis'!F$3) -> 95486 | G10: =SUMIFS('TB & MCC Cost Audit 2020-Curren'!$P:$P,'TB & MCC Cost Audit 2020-Curren'!$C:$C,'TB Type Margin Analysis'!$B10,'TB & MCC Cost Audit 2020-Curren'!$D:$D,'TB Type Margin Analysis'!G$3) -> 149148 | H10: =SUMIFS('TB & MCC Cost Audit 2020-Curren'!$P:$P,'TB & MCC Cost Audit 2020-Curren'!$C:$C,'TB Type Margin Analysis'!$B10,'TB & MCC Cost Audit 2020-Curren'!$D:$D,'TB Type Margin Analysis'!H$3) -> 472321 | K10: =SUMIFS('TB & MCC Cost Audit 2020-Curren'!$W:$W,'TB & MCC Cost Audit 2020-Curren'!$C:$C,'TB Type Margin Analysis'!$B10,'TB & MCC Cost Audit 2020-Curren'!$D:$D,'TB Type Margin Analysis'!K$3) -> 66020.4 | L10: =SUMIFS('TB & MCC Cost Audit 2020-Curren'!$W:$W,'TB & MCC Cost Audit 2020-Curren'!$C:$C,'TB Type Margin Analysis'!$B10,'TB & MCC Cost Audit 2020-Curren'!$D:$D,'TB Type Margin Analysis'!L$3) -> 44813.93 | M10: =SUMIFS('TB & MCC Cost Audit 2020-Curren'!$W:$W,'TB & MCC Cost Audit 2020-Curren'!$C:$C,'TB Type Margin Analysis'!$B10,'TB & MCC Cost Audit 2020-Curren'!$D:$D,'TB Type Margin Analysis'!M$3) -> 16004.3 | N10: =SUMIFS('TB & MCC Cost Audit 2020-Curren'!$W:$W,'TB & MCC Cost Audit 2020-Curren'!$C:$C,'TB Type Margin Analysis'!$B10,'TB & MCC Cost Audit 2020-Curren'!$D:$D,'TB Type Margin Analysis'!N$3) -> 47112.33 | O10: =SUMIFS('TB & MCC Cost Audit 2020-Curren'!$W:$W,'TB & MCC Cost Audit 2020-Curren'!$C:$C,'TB Type Margin Analysis'!$B10,'TB & MCC Cost Audit 2020-Curren'!$D:$D,'TB Type Margin Analysis'!O$3) -> 58532.42 | P10: =SUMIFS('TB & MCC Cost Audit 2020-Curren'!$W:$W,'TB & MCC Cost Audit 2020-Curren'!$C:$C,'TB Type Margin Analysis'!$B10,'TB & MCC Cost Audit 2020-Curren'!$D:$D,'TB Type Margin Analysis'!P$3) -> 47275.53 | S10: =IFERROR((C10-K10)/C10," - ") -> 0.58330188 | T10: =IFERROR((D10-L10)/D10," - ") -> 0.60273822 | U10: =IFERROR((E10-M10)/E10," - ") -> 0.61780776 | V10: =IFERROR((F10-N10)/F10," - ") -> 0.50660484 | W10: =IFERROR((G10-O10)/G10," - ") -> 0.60755478 | X10: =IFERROR((H10-P10)/H10," - ") -> 0.89990805
B11: M3IT | C11: =SUMIFS('TB & MCC Cost Audit 2020-Curren'!$P:$P,'TB & MCC Cost Audit 2020-Curren'!$C:$C,'TB Type Margin Analysis'!$B11,'TB & MCC Cost Audit 2020-Curren'!$D:$D,'TB Type Margin Analysis'!C$3) -> 20797 | D11: =SUMIFS('TB & MCC Cost Audit 2020-Curren'!$P:$P,'TB & MCC Cost Audit 2020-Curren'!$C:$C,'TB Type Margin Analysis'!$B11,'TB & MCC Cost Audit 2020-Curren'!$D:$D,'TB Type Margin Analysis'!D$3) -> 0 | E11: =SUMIFS('TB & MCC Cost Audit 2020-Curren'!$P:$P,'TB & MCC Cost Audit 2020-Curren'!$C:$C,'TB Type Margin Analysis'!$B11,'TB & MCC Cost Audit 2020-Curren'!$D:$D,'TB Type Margin Analysis'!E$3) -> 0 | F11: =SUMIFS('TB & MCC Cost Audit 2020-Curren'!$P:$P,'TB & MCC Cost Audit 2020-Curren'!$C:$C,'TB Type Margin Analysis'!$B11,'TB & MCC Cost Audit 2020-Curren'!$D:$D,'TB Type Margin Analysis'!F$3) -> 0 | G11: =SUMIFS('TB & MCC Cost Audit 2020-Curren'!$P:$P,'TB & MCC Cost Audit 2020-Curren'!$C:$C,'TB Type Margin Analysis'!$B11,'TB & MCC Cost Audit 2020-Curren'!$D:$D,'TB Type Margin Analysis'!G$3) -> 0 | H11: =SUMIFS('TB & MCC Cost Audit 2020-Curren'!$P:$P,'TB & MCC Cost Audit 2020-Curren'!$C:$C,'TB Type Margin Analysis'!$B11,'TB & MCC Cost Audit 2020-Curren'!$D:$D,'TB Type Margin Analysis'!H$3) -> 0 | K11: =SUMIFS('TB & MCC Cost Audit 2020-Curren'!$W:$W,'TB & MCC Cost Audit 2020-Curren'!$C:$C,'TB Type Margin Analysis'!$B11,'TB & MCC Cost Audit 2020-Curren'!$D:$D,'TB Type Margin Analysis'!K$3) -> 10459.6 | L11: =SUMIFS('TB & MCC Cost Audit 2020-Curren'!$W:$W,'TB & MCC Cost Audit 2020-Curren'!$C:$C,'TB Type Margin Analysis'!$B11,'TB & MCC Cost Audit 2020-Curren'!$D:$D,'TB Type Margin Analysis'!L$3) -> 0 | M11: =SUMIFS('TB & MCC Cost Audit 2020-Curren'!$W:$W,'TB & MCC Cost Audit 2020-Curren'!$C:$C,'TB Type Margin Analysis'!$B11,'TB & MCC Cost Audit 2020-Curren'!$D:$D,'TB Type Margin Analysis'!M$3) -> 0 | N11: =SUMIFS('TB & MCC Cost Audit 2020-Curren'!$W:$W,'TB & MCC Cost Audit 2020-Curren'!$C:$C,'TB Type Margin Analysis'!$B11,'TB & MCC Cost Audit 2020-Curren'!$D:$D,'TB Type Margin Analysis'!N$3) -> 0 | O11: =SUMIFS('TB & MCC Cost Audit 2020-Curren'!$W:$W,'TB & MCC Cost Audit 2020-Curren'!$C:$C,'TB Type Margin Analysis'!$B11,'TB & MCC Cost Audit 2020-Curren'!$D:$D,'TB Type Margin Analysis'!O$3) -> 0 | P11: =SUMIFS('TB & MCC Cost Audit 2020-Curren'!$W:$W,'TB & MCC Cost Audit 2020-Curren'!$C:$C,'TB Type Margin Analysis'!$B11,'TB & MCC Cost Audit 2020-Curren'!$D:$D,'TB Type Margin Analysis'!P$3) -> 0 | S11: =IFERROR((C11-K11)/C11," - ") -> 0.49706208 | T11: =IFERROR((D11-L11)/D11," - ") -> - | U11: =IFERROR((E11-M11)/E11," - ") -> - | V11: =IFERROR((F11-N11)/F11," - ") -> - | W11: =IFERROR((G11-O11)/G11," - ") -> - | X11: =IFERROR((H11-P11)/H11," - ") -> -
B12: M3IU | C12: =SUMIFS('TB & MCC Cost Audit 2020-Curren'!$P:$P,'TB & MCC Cost Audit 2020-Curren'!$C:$C,'TB Type Margin Analysis'!$B12,'TB & MCC Cost Audit 2020-Curren'!$D:$D,'TB Type Margin Analysis'!C$3) -> 0 | D12: =SUMIFS('TB & MCC Cost Audit 2020-Curren'!$P:$P,'TB & MCC Cost Audit 2020-Curren'!$C:$C,'TB Type Margin Analysis'!$B12,'TB & MCC Cost Audit 2020-Curren'!$D:$D,'TB Type Margin Analysis'!D$3) -> 0 | E12: =SUMIFS('TB & MCC Cost Audit 2020-Curren'!$P:$P,'TB & MCC Cost Audit 2020-Curren'!$C:$C,'TB Type Margin Analysis'!$B12,'TB & MCC Cost Audit 2020-Curren'!$D:$D,'TB Type Margin Analysis'!E$3) -> 105665 | F12: =SUMIFS('TB & MCC Cost Audit 2020-Curren'!$P:$P,'TB & MCC Cost Audit 2020-Curren'!$C:$C,'TB Type Margin Analysis'!$B12,'TB & MCC Cost Audit 2020-Curren'!$D:$D,'TB Type Margin Analysis'!F$3) -> 9523 | G12: =SUMIFS('TB & MCC Cost Audit 2020-Curren'!$P:$P,'TB & MCC Cost Audit 2020-Curren'!$C:$C,'TB Type Margin Analysis'!$B12,'TB & MCC Cost Audit 2020-Curren'!$D:$D,'TB Type Margin Analysis'!G$3) -> 10238 | H12: =SUMIFS('TB & MCC Cost Audit 2020-Curren'!$P:$P,'TB & MCC Cost Audit 2020-Curren'!$C:$C,'TB Type Margin Analysis'!$B12,'TB & MCC Cost Audit 2020-Curren'!$D:$D,'TB Type Margin Analysis'!H$3) -> 42793 | K12: =SUMIFS('TB & MCC Cost Audit 2020-Curren'!$W:$W,'TB & MCC Cost Audit 2020-Curren'!$C:$C,'TB Type Margin Analysis'!$B12,'TB & MCC Cost Audit 2020-Curren'!$D:$D,'TB Type Margin Analysis'!K$3) -> 0 | L12: =SUMIFS('TB & MCC Cost Audit 2020-Curren'!$W:$W,'TB & MCC Cost Audit 2020-Curren'!$C:$C,'TB Type Margin Analysis'!$B12,'TB & MCC Cost Audit 2020-Curren'!$D:$D,'TB Type Margin Analysis'!L$3) -> 0 | M12: =SUMIFS('TB & MCC Cost Audit 2020-Curren'!$W:$W,'TB & MCC Cost Audit 2020-Curren'!$C:$C,'TB Type Margin Analysis'!$B12,'TB & MCC Cost Audit 2020-Curren'!$D:$D,'TB Type Margin Analysis'!M$3) -> 14383.92 | N12: =SUMIFS('TB & MCC Cost Audit 2020-Curren'!$W:$W,'TB & MCC Cost Audit 2020-Curren'!$C:$C,'TB Type Margin Analysis'!$B12,'TB & MCC Cost Audit 2020-Curren'!$D:$D,'TB Type Margin Analysis'!N$3) -> 8742.04 | O12: =SUMIFS('TB & MCC Cost Audit 2020-Curren'!$W:$W,'TB & MCC Cost Audit 2020-Curren'!$C:$C,'TB Type Margin Analysis'!$B12,'TB & MCC Cost Audit 2020-Curren'!$D:$D,'TB Type Margin Analysis'!O$3) -> 6134.22 | P12: =SUMIFS('TB & MCC Cost Audit 2020-Curren'!$W:$W,'TB & MCC Cost Audit 2020-Curren'!$C:$C,'TB Type Margin Analysis'!$B12,'TB & MCC Cost Audit 2020-Curren'!$D:$D,'TB Type Margin Analysis'!P$3) -> 7086.37 | S12: =IFERROR((C12-K12)/C12," - ") -> - | T12: =IFERROR((D12-L12)/D12," - ") -> - | U12: =IFERROR((E12-M12)/E12," - ") -> 0.86387243 | V12: =IFERROR((F12-N12)/F12," - ") -> 0.082007771 | W12: =IFERROR((G12-O12)/G12," - ") -> 0.40083805 | X12: =IFERROR((H12-P12)/H12," - ") -> 0.83440352
B13: M3N | C13: =SUMIFS('TB & MCC Cost Audit 2020-Curren'!$P:$P,'TB & MCC Cost Audit 2020-Curren'!$C:$C,'TB Type Margin Analysis'!$B13,'TB & MCC Cost Audit 2020-Curren'!$D:$D,'TB Type Margin Analysis'!C$3) -> 0 | D13: =SUMIFS('TB & MCC Cost Audit 2020-Curren'!$P:$P,'TB & MCC Cost Audit 2020-Curren'!$C:$C,'TB Type Margin Analysis'!$B13,'TB & MCC Cost Audit 2020-Curren'!$D:$D,'TB Type Margin Analysis'!D$3) -> 0 | E13: =SUMIFS('TB & MCC Cost Audit 2020-Curren'!$P:$P,'TB & MCC Cost Audit 2020-Curren'!$C:$C,'TB Type Margin Analysis'!$B13,'TB & MCC Cost Audit 2020-Curren'!$D:$D,'TB Type Margin Analysis'!E$3) -> 0 | F13: =SUMIFS('TB & MCC Cost Audit 2020-Curren'!$P:$P,'TB & MCC Cost Audit 2020-Curren'!$C:$C,'TB Type Margin Analysis'!$B13,'TB & MCC Cost Audit 2020-Curren'!$D:$D,'TB Type Margin Analysis'!F$3) -> 0 | G13: =SUMIFS('TB & MCC Cost Audit 2020-Curren'!$P:$P,'TB & MCC Cost Audit 2020-Curren'!$C:$C,'TB Type Margin Analysis'!$B13,'TB & MCC Cost Audit 2020-Curren'!$D:$D,'TB Type Margin Analysis'!G$3) -> 0 | H13: =SUMIFS('TB & MCC Cost Audit 2020-Curren'!$P:$P,'TB & MCC Cost Audit 2020-Curren'!$C:$C,'TB Type Margin Analysis'!$B13,'TB & MCC Cost Audit 2020-Curren'!$D:$D,'TB Type Margin Analysis'!H$3) -> 0 | K13: =SUMIFS('TB & MCC Cost Audit 2020-Curren'!$W:$W,'TB & MCC Cost Audit 2020-Curren'!$C:$C,'TB Type Margin Analysis'!$B13,'TB & MCC Cost Audit 2020-Curren'!$D:$D,'TB Type Margin Analysis'!K$3) -> 0 | L13: =SUMIFS('TB & MCC Cost Audit 2020-Curren'!$W:$W,'TB & MCC Cost Audit 2020-Curren'!$C:$C,'TB Type Margin Analysis'!$B13,'TB & MCC Cost Audit 2020-Curren'!$D:$D,'TB Type Margin Analysis'!L$3) -> 0 | M13: =SUMIFS('TB & MCC Cost Audit 2020-Curren'!$W:$W,'TB & MCC Cost Audit 2020-Curren'!$C:$C,'TB Type Margin Analysis'!$B13,'TB & MCC Cost Audit 2020-Curren'!$D:$D,'TB Type Margin Analysis'!M$3) -> 0 | N13: =SUMIFS('TB & MCC Cost Audit 2020-Curren'!$W:$W,'TB & MCC Cost Audit 2020-Curren'!$C:$C,'TB Type Margin Analysis'!$B13,'TB & MCC Cost Audit 2020-Curren'!$D:$D,'TB Type Margin Analysis'!N$3) -> 0 | O13: =SUMIFS('TB & MCC Cost Audit 2020-Curren'!$W:$W,'TB & MCC Cost Audit 2020-Curren'!$C:$C,'TB Type Margin Analysis'!$B13,'TB & MCC Cost Audit 2020-Curren'!$D:$D,'TB Type Margin Analysis'!O$3) -> 0 | P13: =SUMIFS('TB & MCC Cost Audit 2020-Curren'!$W:$W,'TB & MCC Cost Audit 2020-Curren'!$C:$C,'TB Type Margin Analysis'!$B13,'TB & MCC Cost Audit 2020-Curren'!$D:$D,'TB Type Margin Analysis'!P$3) -> 0 | S13: =IFERROR((C13-K13)/C13," - ") -> - | T13: =IFERROR((D13-L13)/D13," - ") -> - | U13: =IFERROR((E13-M13)/E13," - ") -> - | V13: =IFERROR((F13-N13)/F13," - ") -> - | W13: =IFERROR((G13-O13)/G13," - ") -> - | X13: =IFERROR((H13-P13)/H13," - ") -> -
B14: MCC | C14: =SUMIFS('TB & MCC Cost Audit 2020-Curren'!$P:$P,'TB & MCC Cost Audit 2020-Curren'!$C:$C,'TB Type Margin Analysis'!$B14,'TB & MCC Cost Audit 2020-Curren'!$D:$D,'TB Type Margin Analysis'!C$3) -> 9680 | D14: =SUMIFS('TB & MCC Cost Audit 2020-Curren'!$P:$P,'TB & MCC Cost Audit 2020-Curren'!$C:$C,'TB Type Margin Analysis'!$B14,'TB & MCC Cost Audit 2020-Curren'!$D:$D,'TB Type Margin Analysis'!D$3) -> 998172.39 | E14: =SUMIFS('TB & MCC Cost Audit 2020-Curren'!$P:$P,'TB & MCC Cost Audit 2020-Curren'!$C:$C,'TB Type Margin Analysis'!$B14,'TB & MCC Cost Audit 2020-Curren'!$D:$D,'TB Type Margin Analysis'!E$3) -> 867072.68 | F14: =SUMIFS('TB & MCC Cost Audit 2020-Curren'!$P:$P,'TB & MCC Cost Audit 2020-Curren'!$C:$C,'TB Type Margin Analysis'!$B14,'TB & MCC Cost Audit 2020-Curren'!$D:$D,'TB Type Margin Analysis'!F$3) -> 1238812.9 | G14: =SUMIFS('TB & MCC Cost Audit 2020-Curren'!$P:$P,'TB & MCC Cost Audit 2020-Curren'!$C:$C,'TB Type Margin Analysis'!$B14,'TB & MCC Cost Audit 2020-Curren'!$D:$D,'TB Type Margin Analysis'!G$3) -> 1483949.3 | H14: =SUMIFS('TB & MCC Cost Audit 2020-Curren'!$P:$P,'TB & MCC Cost Audit 2020-Curren'!$C:$C,'TB Type Margin Analysis'!$B14,'TB & MCC Cost Audit 2020-Curren'!$D:$D,'TB Type Margin Analysis'!H$3) -> 1409647.9 | K14: =SUMIFS('TB & MCC Cost Audit 2020-Curren'!$W:$W,'TB & MCC Cost Audit 2020-Curren'!$C:$C,'TB Type Margin Analysis'!$B14,'TB & MCC Cost Audit 2020-Curren'!$D:$D,'TB Type Margin Analysis'!K$3) -> 3825.06 | L14: =SUMIFS('TB & MCC Cost Audit 2020-Curren'!$W:$W,'TB & MCC Cost Audit 2020-Curren'!$C:$C,'TB Type Margin Analysis'!$B14,'TB & MCC Cost Audit 2020-Curren'!$D:$D,'TB Type Margin Analysis'!L$3) -> 220860.36 | M14: =SUMIFS('TB & MCC Cost Audit 2020-Curren'!$W:$W,'TB & MCC Cost Audit 2020-Curren'!$C:$C,'TB Type Margin Analysis'!$B14,'TB & MCC Cost Audit 2020-Curren'!$D:$D,'TB Type Margin Analysis'!M$3) -> 191411.83 | N14: =SUMIFS('TB & MCC Cost Audit 2020-Curren'!$W:$W,'TB & MCC Cost Audit 2020-Curren'!$C:$C,'TB Type Margin Analysis'!$B14,'TB & MCC Cost Audit 2020-Curren'!$D:$D,'TB Type Margin Analysis'!N$3) -> 244322.27 | O14: =SUMIFS('TB & MCC Cost Audit 2020-Curren'!$W:$W,'TB & MCC Cost Audit 2020-Curren'!$C:$C,'TB Type Margin Analysis'!$B14,'TB & MCC Cost Audit 2020-Curren'!$D:$D,'TB Type Margin Analysis'!O$3) -> 334257.67 | P14: =SUMIFS('TB & MCC Cost Audit 2020-Curren'!$W:$W,'TB & MCC Cost Audit 2020-Curren'!$C:$C,'TB Type Margin Analysis'!$B14,'TB & MCC Cost Audit 2020-Curren'!$D:$D,'TB Type Margin Analysis'!P$3) -> 302641.94 | S14: =IFERROR((C14-K14)/C14," - ") -> 0.60484917 | T14: =IFERROR((D14-L14)/D14," - ") -> 0.77873525 | U14: =IFERROR((E14-M14)/E14," - ") -> 0.77924361 | V14: =IFERROR((F14-N14)/F14," - ") -> 0.8027771 | W14: =IFERROR((G14-O14)/G14," - ") -> 0.7747513 | X14: =IFERROR((H14-P14)/H14," - ") -> 0.78530672
B15: PM | C15: =SUMIFS('TB & MCC Cost Audit 2020-Curren'!$P:$P,'TB & MCC Cost Audit 2020-Curren'!$C:$C,'TB Type Margin Analysis'!$B15,'TB & MCC Cost Audit 2020-Curren'!$D:$D,'TB Type Margin Analysis'!C$3) -> 0 | D15: =SUMIFS('TB & MCC Cost Audit 2020-Curren'!$P:$P,'TB & MCC Cost Audit 2020-Curren'!$C:$C,'TB Type Margin Analysis'!$B15,'TB & MCC Cost Audit 2020-Curren'!$D:$D,'TB Type Margin Analysis'!D$3) -> 55410 | E15: =SUMIFS('TB & MCC Cost Audit 2020-Curren'!$P:$P,'TB & MCC Cost Audit 2020-Curren'!$C:$C,'TB Type Margin Analysis'!$B15,'TB & MCC Cost Audit 2020-Curren'!$D:$D,'TB Type Margin Analysis'!E$3) -> 137454 | F15: =SUMIFS('TB & MCC Cost Audit 2020-Curren'!$P:$P,'TB & MCC Cost Audit 2020-Curren'!$C:$C,'TB Type Margin Analysis'!$B15,'TB & MCC Cost Audit 2020-Curren'!$D:$D,'TB Type Margin Analysis'!F$3) -> 110252 | G15: =SUMIFS('TB & MCC Cost Audit 2020-Curren'!$P:$P,'TB & MCC Cost Audit 2020-Curren'!$C:$C,'TB Type Margin Analysis'!$B15,'TB & MCC Cost Audit 2020-Curren'!$D:$D,'TB Type Margin Analysis'!G$3) -> 166800 | H15: =SUMIFS('TB & MCC Cost Audit 2020-Curren'!$P:$P,'TB & MCC Cost Audit 2020-Curren'!$C:$C,'TB Type Margin Analysis'!$B15,'TB & MCC Cost Audit 2020-Curren'!$D:$D,'TB Type Margin Analysis'!H$3) -> 288586.79 | K15: =SUMIFS('TB & MCC Cost Audit 2020-Curren'!$W:$W,'TB & MCC Cost Audit 2020-Curren'!$C:$C,'TB Type Margin Analysis'!$B15,'TB & MCC Cost Audit 2020-Curren'!$D:$D,'TB Type Margin Analysis'!K$3) -> 0 | L15: =SUMIFS('TB & MCC Cost Audit 2020-Curren'!$W:$W,'TB & MCC Cost Audit 2020-Curren'!$C:$C,'TB Type Margin Analysis'!$B15,'TB & MCC Cost Audit 2020-Curren'!$D:$D,'TB Type Margin Analysis'!L$3) -> 0 | M15: =SUMIFS('TB & MCC Cost Audit 2020-Curren'!$W:$W,'TB & MCC Cost Audit 2020-Curren'!$C:$C,'TB Type Margin Analysis'!$B15,'TB & MCC Cost Audit 2020-Curren'!$D:$D,'TB Type Margin Analysis'!M$3) -> 10647.96 | N15: =SUMIFS('TB & MCC Cost Audit 2020-Curren'!$W:$W,'TB & MCC Cost Audit 2020-Curren'!$C:$C,'TB Type Margin Analysis'!$B15,'TB & MCC Cost Audit 2020-Curren'!$D:$D,'TB Type Margin Analysis'!N$3) -> 8411.85 | O15: =SUMIFS('TB & MCC Cost Audit 2020-Curren'!$W:$W,'TB & MCC Cost Audit 2020-Curren'!$C:$C,'TB Type Margin Analysis'!$B15,'TB & MCC Cost Audit 2020-Curren'!$D:$D,'TB Type Margin Analysis'!O$3) -> 7860.45 | P15: =SUMIFS('TB & MCC Cost Audit 2020-Curren'!$W:$W,'TB & MCC Cost Audit 2020-Curren'!$C:$C,'TB Type Margin Analysis'!$B15,'TB & MCC Cost Audit 2020-Curren'!$D:$D,'TB Type Margin Analysis'!P$3) -> 11229.22 | S15: =IFERROR((C15-K15)/C15," - ") -> - | T15: =IFERROR((D15-L15)/D15," - ") -> 1 | U15: =IFERROR((E15-M15)/E15," - ") -> 0.92253438 | V15: =IFERROR((F15-N15)/F15," - ") -> 0.92370342 | W15: =IFERROR((G15-O15)/G15," - ") -> 0.952875 | X15: =IFERROR((H15-P15)/H15," - ") -> 0.96108893
... B25: TNG | C25: =SUMIFS('TB & MCC Cost Audit 2020-Curren'!$P:$P,'TB & MCC Cost Audit 2020-Curren'!$C:$C,'TB Type Margin Analysis'!$B25,'TB & MCC Cost Audit 2020-Curren'!$D:$D,'TB Type Margin Analysis'!C$3) -> 0 | D25: =SUMIFS('TB & MCC Cost Audit 2020-Curren'!$P:$P,'TB & MCC Cost Audit 2020-Curren'!$C:$C,'TB Type Margin Analysis'!$B25,'TB & MCC Cost Audit 2020-Curren'!$D:$D,'TB Type Margin Analysis'!D$3) -> 0 | E25: =SUMIFS('TB & MCC Cost Audit 2020-Curren'!$P:$P,'TB & MCC Cost Audit 2020-Curren'!$C:$C,'TB Type Margin Analysis'!$B25,'TB & MCC Cost Audit 2020-Curren'!$D:$D,'TB Type Margin Analysis'!E$3) -> 0 | F25: =SUMIFS('TB & MCC Cost Audit 2020-Curren'!$P:$P,'TB & MCC Cost Audit 2020-Curren'!$C:$C,'TB Type Margin Analysis'!$B25,'TB & MCC Cost Audit 2020-Curren'!$D:$D,'TB Type Margin Analysis'!F$3) -> 0 | G25: =SUMIFS('TB & MCC Cost Audit 2020-Curren'!$P:$P,'TB & MCC Cost Audit 2020-Curren'!$C:$C,'TB Type Margin Analysis'!$B25,'TB & MCC Cost Audit 2020-Curren'!$D:$D,'TB Type Margin Analysis'!G$3) -> 9250 | H25: =SUMIFS('TB & MCC Cost Audit 2020-Curren'!$P:$P,'TB & MCC Cost Audit 2020-Curren'!$C:$C,'TB Type Margin Analysis'!$B25,'TB & MCC Cost Audit 2020-Curren'!$D:$D,'TB Type Margin Analysis'!H$3) -> 0 | K25: =SUMIFS('TB & MCC Cost Audit 2020-Curren'!$W:$W,'TB & MCC Cost Audit 2020-Curren'!$C:$C,'TB Type Margin Analysis'!$B25,'TB & MCC Cost Audit 2020-Curren'!$D:$D,'TB Type Margin Analysis'!K$3) -> 0 | L25: =SUMIFS('TB & MCC Cost Audit 2020-Curren'!$W:$W,'TB & MCC Cost Audit 2020-Curren'!$C:$C,'TB Type Margin Analysis'!$B25,'TB & MCC Cost Audit 2020-Curren'!$D:$D,'TB Type Margin Analysis'!L$3) -> 0 | M25: =SUMIFS('TB & MCC Cost Audit 2020-Curren'!$W:$W,'TB & MCC Cost Audit 2020-Curren'!$C:$C,'TB Type Margin Analysis'!$B25,'TB & MCC Cost Audit 2020-Curren'!$D:$D,'TB Type Margin Analysis'!M$3) -> 0 | N25: =SUMIFS('TB & MCC Cost Audit 2020-Curren'!$W:$W,'TB & MCC Cost Audit 2020-Curren'!$C:$C,'TB Type Margin Analysis'!$B25,'TB & MCC Cost Audit 2020-Curren'!$D:$D,'TB Type Margin Analysis'!N$3) -> 0 | O25: =SUMIFS('TB & MCC Cost Audit 2020-Curren'!$W:$W,'TB & MCC Cost Audit 2020-Curren'!$C:$C,'TB Type Margin Analysis'!$B25,'TB & MCC Cost Audit 2020-Curren'!$D:$D,'TB Type Margin Analysis'!O$3) -> 1731.21 | P25: =SUMIFS('TB & MCC Cost Audit 2020-Curren'!$W:$W,'TB & MCC Cost Audit 2020-Curren'!$C:$C,'TB Type Margin Analysis'!$B25,'TB & MCC Cost Audit 2020-Curren'!$D:$D,'TB Type Margin Analysis'!P$3) -> 0 | S25: =IFERROR((C25-K25)/C25," - ") -> - | T25: =IFERROR((D25-L25)/D25," - ") -> - | U25: =IFERROR((E25-M25)/E25," - ") -> - | V25: =IFERROR((F25-N25)/F25," - ") -> - | W25: =IFERROR((G25-O25)/G25," - ") -> 0.81284216 | X25: =IFERROR((H25-P25)/H25," - ") -> -

Sheet TB All Check
A6: Revenue | C6: Audit | D6: NS | G6: Revenue | I6: Audit | J6: NS | M6: Revenue | O6: Audit | P6: NS
A7: 2022 | B7: MCC | C7: =SUM(C8:C999) -> 867072.68 | D7: =SUM(D8:D999) -> 856143.07 | E7: =C7-D7 -> 10929.606 | G7: 2023 | H7: TBEN | I7: =SUM(I8:I999) -> 2902671 | J7: =SUM(J8:J999) -> 2902671 | K7: =I7-J7 -> 0 | M7: 2024 | N7: MCC | O7: =SUM(O8:O999) -> 1456166.3 | P7: =SUM(P8:P999) -> 1443409.1 | Q7: =P7-O7 -> -12757.253
A8: Alameda | B8: Alameda County Water District | C8: =SUMIFS('TB & MCC Cost Audit 2020-Curren'!$P:$P,'TB & MCC Cost Audit 2020-Curren'!$A:$A,'TB All Check'!$A8,'TB & MCC Cost Audit 2020-Curren'!$C:$C,'TB All Check'!$B$7,'TB & MCC Cost Audit 2020-Curren'!$D:$D,'TB All Check'!$A$7) -> 31320 | D8: =SUMIFS('2022 Partial Rev - NS'!$N:$N,'2022 Partial Rev - NS'!$G:$G,'TB All Check'!$B8,'2022 Partial Rev - NS'!$P:$P,'TB All Check'!$B$7) -> 31320 | E8: =C8-D8 -> 0 | G8: Alameda | H8: Alameda County Water District | I8: =SUMIFS('TB & MCC Cost Audit 2020-Curren'!$P:$P,'TB & MCC Cost Audit 2020-Curren'!$A:$A,'TB All Check'!$A8,'TB & MCC Cost Audit 2020-Curren'!$C:$C,'TB All Check'!$H$7,'TB & MCC Cost Audit 2020-Curren'!$D:$D,'TB All Check'!$G$7) -> 0 | J8: =SUMIFS('2023 Rev - NS'!$N:$N,'2023 Rev - NS'!$G:$G,'TB All Check'!$H8,'2023 Rev - NS'!$P:$P,'TB All Check'!$H$7) -> 0 | K8: =I8-J8 -> 0 | M8: Alameda | N8: Alameda County Water District | O8: =SUMIFS('TB & MCC Cost Audit 2020-Curren'!$P:$P,'TB & MCC Cost Audit 2020-Curren'!$A:$A,'TB All Check'!$M8,'TB & MCC Cost Audit 2020-Curren'!$C:$C,'TB All Check'!$N$7,'TB & MCC Cost Audit 2020-Curren'!$D:$D,'TB All Check'!$M$7) -> 32584 | P8: =SUMIFS('2024 Rev - NS'!$N:$N,'2024 Rev - NS'!$G:$G,'TB All Check'!$N8,'2024 Rev - NS'!$P:$P,'TB All Check'!$N$7) -> 32584 | Q8: =P8-O8 -> 0
A9: Albemarle | B9: Albemarle County Service Authority | C9: =SUMIFS('TB & MCC Cost Audit 2020-Curren'!$P:$P,'TB & MCC Cost Audit 2020-Curren'!$A:$A,'TB All Check'!$A9,'TB & MCC Cost Audit 2020-Curren'!$C:$C,'TB All Check'!$B$7,'TB & MCC Cost Audit 2020-Curren'!$D:$D,'TB All Check'!$A$7) -> 0 | D9: =SUMIFS('2022 Partial Rev - NS'!$N:$N,'2022 Partial Rev - NS'!$G:$G,'TB All Check'!$B9,'2022 Partial Rev - NS'!$P:$P,'TB All Check'!$B$7) -> 0 | E9: =C9-D9 -> 0 | G9: Albemarle | H9: Albemarle County Service Authority | I9: =SUMIFS('TB & MCC Cost Audit 2020-Curren'!$P:$P,'TB & MCC Cost Audit 2020-Curren'!$A:$A,'TB All Check'!$A9,'TB & MCC Cost Audit 2020-Curren'!$C:$C,'TB All Check'!$H$7,'TB & MCC Cost Audit 2020-Curren'!$D:$D,'TB All Check'!$G$7) -> 0 | J9: =SUMIFS('2023 Rev - NS'!$N:$N,'2023 Rev - NS'!$G:$G,'TB All Check'!$H9,'2023 Rev - NS'!$P:$P,'TB All Check'!$H$7) -> 0 | K9: =I9-J9 -> 0 | M9: Albemarle | N9: Albemarle County Service Authority | O9: =SUMIFS('TB & MCC Cost Audit 2020-Curren'!$P:$P,'TB & MCC Cost Audit 2020-Curren'!$A:$A,'TB All Check'!$M9,'TB & MCC Cost Audit 2020-Curren'!$C:$C,'TB All Check'!$N$7,'TB & MCC Cost Audit 2020-Curren'!$D:$D,'TB All Check'!$M$7) -> 0 | P9: =SUMIFS('2024 Rev - NS'!$N:$N,'2024 Rev - NS'!$G:$G,'TB All Check'!$N9,'2024 Rev - NS'!$P:$P,'TB All Check'!$N$7) -> 0 | Q9: =P9-O9 -> 0
A10: Allen | B10: Allen, City of | C10: =SUMIFS('TB & MCC Cost Audit 2020-Curren'!$P:$P,'TB & MCC Cost Audit 2020-Curren'!$A:$A,'TB All Check'!$A10,'TB & MCC Cost Audit 2020-Curren'!$C:$C,'TB All Check'!$B$7,'TB & MCC Cost Audit 2020-Curren'!$D:$D,'TB All Check'!$A$7) -> 0 | D10: =SUMIFS('2022 Partial Rev - NS'!$N:$N,'2022 Partial Rev - NS'!$G:$G,'TB All Check'!$B10,'2022 Partial Rev - NS'!$P:$P,'TB All Check'!$B$7) -> 0 | E10: =C10-D10 -> 0 | G10: Allen | H10: Allen, City of | I10: =SUMIFS('TB & MCC Cost Audit 2020-Curren'!$P:$P,'TB & MCC Cost Audit 2020-Curren'!$A:$A,'TB All Check'!$A10,'TB & MCC Cost Audit 2020-Curren'!$C:$C,'TB All Check'!$H$7,'TB & MCC Cost Audit 2020-Curren'!$D:$D,'TB All Check'!$G$7) -> 0 | J10: =SUMIFS('2023 Rev - NS'!$N:$N,'2023 Rev - NS'!$G:$G,'TB All Check'!$H10,'2023 Rev - NS'!$P:$P,'TB All Check'!$H$7) -> 0 | K10: =I10-J10 -> 0 | M10: Allen | N10: Allen, City of | O10: =SUMIFS('TB & MCC Cost Audit 2020-Curren'!$P:$P,'TB & MCC Cost Audit 2020-Curren'!$A:$A,'TB All Check'!$M10,'TB & MCC Cost Audit 2020-Curren'!$C:$C,'TB All Check'!$N$7,'TB & MCC Cost Audit 2020-Curren'!$D:$D,'TB All Check'!$M$7) -> 9680 | P10: =SUMIFS('2024 Rev - NS'!$N:$N,'2024 Rev - NS'!$G:$G,'TB All Check'!$N10,'2024 Rev - NS'!$P:$P,'TB All Check'!$N$7) -> 9680 | Q10: =P10-O10 -> 0
A11: Anne Arundel | B11: Anne Arundel County | C11: =SUMIFS('TB & MCC Cost Audit 2020-Curren'!$P:$P,'TB & MCC Cost Audit 2020-Curren'!$A:$A,'TB All Check'!$A11,'TB & MCC Cost Audit 2020-Curren'!$C:$C,'TB All Check'!$B$7,'TB & MCC Cost Audit 2020-Curren'!$D:$D,'TB All Check'!$A$7) -> 9353 | D11: 9353 | E11: =C11-D11 -> 0 | G11: Anne Arundel | H11: Anne Arundel County | I11: =SUMIFS('TB & MCC Cost Audit 2020-Curren'!$P:$P,'TB & MCC Cost Audit 2020-Curren'!$A:$A,'TB All Check'!$A11,'TB & MCC Cost Audit 2020-Curren'!$C:$C,'TB All Check'!$H$7,'TB & MCC Cost Audit 2020-Curren'!$D:$D,'TB All Check'!$G$7) -> 0 | J11: =SUMIFS('2023 Rev - NS'!$N:$N,'2023 Rev - NS'!$G:$G,'TB All Check'!$H11,'2023 Rev - NS'!$P:$P,'TB All Check'!$H$7) -> 0 | K11: =I11-J11 -> 0 | M11: Anne Arundel | N11: Anne Arundel County | O11: =SUMIFS('TB & MCC Cost Audit 2020-Curren'!$P:$P,'TB & MCC Cost Audit 2020-Curren'!$A:$A,'TB All Check'!$M11,'TB & MCC Cost Audit 2020-Curren'!$C:$C,'TB All Check'!$N$7,'TB & MCC Cost Audit 2020-Curren'!$D:$D,'TB All Check'!$M$7) -> 9353 | P11: =SUMIFS('2024 Rev - NS'!$N:$N,'2024 Rev - NS'!$G:$G,'TB All Check'!$N11,'2024 Rev - NS'!$P:$P,'TB All Check'!$N$7) -> 9353 | Q11: =P11-O11 -> 0
A12: Apex | B12: Apex, Town of | C12: =SUMIFS('TB & MCC Cost Audit 2020-Curren'!$P:$P,'TB & MCC Cost Audit 2020-Curren'!$A:$A,'TB All Check'!$A12,'TB & MCC Cost Audit 2020-Curren'!$C:$C,'TB All Check'!$B$7,'TB & MCC Cost Audit 2020-Curren'!$D:$D,'TB All Check'!$A$7) -> 9116 | D12: =SUMIFS('2022 Partial Rev - NS'!$N:$N,'2022 Partial Rev - NS'!$G:$G,'TB All Check'!$B12,'2022 Partial Rev - NS'!$P:$P,'TB All Check'!$B$7) -> 9116 | E12: =C12-D12 -> 0 | G12: Apex | H12: Apex, Town of | I12: =SUMIFS('TB & MCC Cost Audit 2020-Curren'!$P:$P,'TB & MCC Cost Audit 2020-Curren'!$A:$A,'TB All Check'!$A12,'TB & MCC Cost Audit 2020-Curren'!$C:$C,'TB All Check'!$H$7,'TB & MCC Cost Audit 2020-Curren'!$D:$D,'TB All Check'!$G$7) -> 0 | J12: =SUMIFS('2023 Rev - NS'!$N:$N,'2023 Rev - NS'!$G:$G,'TB All Check'!$H12,'2023 Rev - NS'!$P:$P,'TB All Check'!$H$7) -> 0 | K12: =I12-J12 -> 0 | M12: Apex | N12: Apex, Town of | O12: =SUMIFS('TB & MCC Cost Audit 2020-Curren'!$P:$P,'TB & MCC Cost Audit 2020-Curren'!$A:$A,'TB All Check'!$M12,'TB & MCC Cost Audit 2020-Curren'!$C:$C,'TB All Check'!$N$7,'TB & MCC Cost Audit 2020-Curren'!$D:$D,'TB All Check'!$M$7) -> 12084 | P12: =SUMIFS('2024 Rev - NS'!$N:$N,'2024 Rev - NS'!$G:$G,'TB All Check'!$N12,'2024 Rev - NS'!$P:$P,'TB All Check'!$N$7) -> 12084 | Q12: =P12-O12 -> 0
A13: Aqua Penn | B13: Aqua Pennsylvania, Inc. | C13: =SUMIFS('TB & MCC Cost Audit 2020-Curren'!$P:$P,'TB & MCC Cost Audit 2020-Curren'!$A:$A,'TB All Check'!$A13,'TB & MCC Cost Audit 2020-Curren'!$C:$C,'TB All Check'!$B$7,'TB & MCC Cost Audit 2020-Curren'!$D:$D,'TB All Check'!$A$7) -> 0 | D13: =SUMIFS('2022 Partial Rev - NS'!$N:$N,'2022 Partial Rev - NS'!$G:$G,'TB All Check'!$B13,'2022 Partial Rev - NS'!$P:$P,'TB All Check'!$B$7) -> 0 | E13: =C13-D13 -> 0 | G13: Aqua Penn | H13: Aqua Pennsylvania, Inc. | I13: =SUMIFS('TB & MCC Cost Audit 2020-Curren'!$P:$P,'TB & MCC Cost Audit 2020-Curren'!$A:$A,'TB All Check'!$A13,'TB & MCC Cost Audit 2020-Curren'!$C:$C,'TB All Check'!$H$7,'TB & MCC Cost Audit 2020-Curren'!$D:$D,'TB All Check'!$G$7) -> 0 | J13: =SUMIFS('2023 Rev - NS'!$N:$N,'2023 Rev - NS'!$G:$G,'TB All Check'!$H13,'2023 Rev - NS'!$P:$P,'TB All Check'!$H$7) -> 0 | K13: =I13-J13 -> 0 | M13: Aqua Penn | N13: Aqua Pennsylvania, Inc. | O13: =SUMIFS('TB & MCC Cost Audit 2020-Curren'!$P:$P,'TB & MCC Cost Audit 2020-Curren'!$A:$A,'TB All Check'!$M13,'TB & MCC Cost Audit 2020-Curren'!$C:$C,'TB All Check'!$N$7,'TB & MCC Cost Audit 2020-Curren'!$D:$D,'TB All Check'!$M$7) -> 44749 | P13: =SUMIFS('2024 Rev - NS'!$N:$N,'2024 Rev - NS'!$G:$G,'TB All Check'!$N13,'2024 Rev - NS'!$P:$P,'TB All Check'!$N$7) -> 44749 | Q13: =P13-O13 -> 0
A14: Artesian Resources | B14: Artesian Resources Corporation | C14: =SUMIFS('TB & MCC Cost Audit 2020-Curren'!$P:$P,'TB & MCC Cost Audit 2020-Curren'!$A:$A,'TB All Check'!$A14,'TB & MCC Cost Audit 2020-Curren'!$C:$C,'TB All Check'!$B$7,'TB & MCC Cost Audit 2020-Curren'!$D:$D,'TB All Check'!$A$7) -> 0 | D14: =SUMIFS('2022 Partial Rev - NS'!$N:$N,'2022 Partial Rev - NS'!$G:$G,'TB All Check'!$B14,'2022 Partial Rev - NS'!$P:$P,'TB All Check'!$B$7) -> 0 | E14: =C14-D14 -> 0 | G14: Artesian Resources | H14: Artesian Resources Corporation | I14: =SUMIFS('TB & MCC Cost Audit 2020-Curren'!$P:$P,'TB & MCC Cost Audit 2020-Curren'!$A:$A,'TB All Check'!$A14,'TB & MCC Cost Audit 2020-Curren'!$C:$C,'TB All Check'!$H$7,'TB & MCC Cost Audit 2020-Curren'!$D:$D,'TB All Check'!$G$7) -> 0 | J14: =SUMIFS('2023 Rev - NS'!$N:$N,'2023 Rev - NS'!$G:$G,'TB All Check'!$H14,'2023 Rev - NS'!$P:$P,'TB All Check'!$H$7) -> 0 | K14: =I14-J14 -> 0 | M14: Artesian Resources | N14: Artesian Resources Corporation | O14: =SUMIFS('TB & MCC Cost Audit 2020-Curren'!$P:$P,'TB & MCC Cost Audit 2020-Curren'!$A:$A,'TB All Check'!$M14,'TB & MCC Cost Audit 2020-Curren'!$C:$C,'TB All Check'!$N$7,'TB & MCC Cost Audit 2020-Curren'!$D:$D,'TB All Check'!$M$7) -> 0 | P14: =SUMIFS('2024 Rev - NS'!$N:$N,'2024 Rev - NS'!$G:$G,'TB All Check'!$N14,'2024 Rev - NS'!$P:$P,'TB All Check'!$N$7) -> 0 | Q14: =P14-O14 -> 0
A15: Aruba | B15: W.E.B. Aruba N.V. | C15: =SUMIFS('TB & MCC Cost Audit 2020-Curren'!$P:$P,'TB & MCC Cost Audit 2020-Curren'!$A:$A,'TB All Check'!$A15,'TB & MCC Cost Audit 2020-Curren'!$C:$C,'TB All Check'!$B$7,'TB & MCC Cost Audit 2020-Curren'!$D:$D,'TB All Check'!$A$7) -> 0 | D15: =SUMIFS('2022 Partial Rev - NS'!$N:$N,'2022 Partial Rev - NS'!$G:$G,'TB All Check'!$B15,'2022 Partial Rev - NS'!$P:$P,'TB All Check'!$B$7) -> 0 | E15: =C15-D15 -> 0 | G15: Aruba | H15: W.E.B. Aruba N.V. | I15: =SUMIFS('TB & MCC Cost Audit 2020-Curren'!$P:$P,'TB & MCC Cost Audit 2020-Curren'!$A:$A,'TB All Check'!$A15,'TB & MCC Cost Audit 2020-Curren'!$C:$C,'TB All Check'!$H$7,'TB & MCC Cost Audit 2020-Curren'!$D:$D,'TB All Check'!$G$7) -> 0 | J15: =SUMIFS('2023 Rev - NS'!$N:$N,'2023 Rev - NS'!$G:$G,'TB All Check'!$H15,'2023 Rev - NS'!$P:$P,'TB All Check'!$H$7) -> 0 | K15: =I15-J15 -> 0 | M15: Aruba | N15: W.E.B. Aruba N.V. | O15: =SUMIFS('TB & MCC Cost Audit 2020-Curren'!$P:$P,'TB & MCC Cost Audit 2020-Curren'!$A:$A,'TB All Check'!$M15,'TB & MCC Cost Audit 2020-Curren'!$C:$C,'TB All Check'!$N$7,'TB & MCC Cost Audit 2020-Curren'!$D:$D,'TB All Check'!$M$7) -> 0 | P15: =SUMIFS('2024 Rev - NS'!$N:$N,'2024 Rev - NS'!$G:$G,'TB All Check'!$N15,'2024 Rev - NS'!$P:$P,'TB All Check'!$N$7) -> 0 | Q15: =P15-O15 -> 0
A16: Austin | B16: Austin, City of | C16: =SUMIFS('TB & MCC Cost Audit 2020-Curren'!$P:$P,'TB & MCC Cost Audit 2020-Curren'!$A:$A,'TB All Check'!$A16,'TB & MCC Cost Audit 2020-Curren'!$C:$C,'TB All Check'!$B$7,'TB & MCC Cost Audit 2020-Curren'!$D:$D,'TB All Check'!$A$7) -> 20445 | D16: =SUMIFS('2022 Partial Rev - NS'!$N:$N,'2022 Partial Rev - NS'!$G:$G,'TB All Check'!$B16,'2022 Partial Rev - NS'!$P:$P,'TB All Check'!$B$7) -> 20445 | E16: =C16-D16 -> 0 | G16: Austin | H16: Austin, City of | I16: =SUMIFS('TB & MCC Cost Audit 2020-Curren'!$P:$P,'TB & MCC Cost Audit 2020-Curren'!$A:$A,'TB All Check'!$A16,'TB & MCC Cost Audit 2020-Curren'!$C:$C,'TB All Check'!$H$7,'TB & MCC Cost Audit 2020-Curren'!$D:$D,'TB All Check'!$G$7) -> 0 | J16: =SUMIFS('2023 Rev - NS'!$N:$N,'2023 Rev - NS'!$G:$G,'TB All Check'!$H16,'2023 Rev - NS'!$P:$P,'TB All Check'!$H$7) -> 0 | K16: =I16-J16 -> 0 | M16: Austin | N16: Austin, City of | O16: =SUMIFS('TB & MCC Cost Audit 2020-Curren'!$P:$P,'TB & MCC Cost Audit 2020-Curren'!$A:$A,'TB All Check'!$M16,'TB & MCC Cost Audit 2020-Curren'!$C:$C,'TB All Check'!$N$7,'TB & MCC Cost Audit 2020-Curren'!$D:$D,'TB All Check'!$M$7) -> 19269 | P16: =SUMIFS('2024 Rev - NS'!$N:$N,'2024 Rev - NS'!$G:$G,'TB All Check'!$N16,'2024 Rev - NS'!$P:$P,'TB All Check'!$N$7) -> 19269 | Q16: =P16-O16 -> 0
A17: Badger | B17: Badger Meter | C17: =SUMIFS('TB & MCC Cost Audit 2020-Curren'!$P:$P,'TB & MCC Cost Audit 2020-Curren'!$A:$A,'TB All Check'!$A17,'TB & MCC Cost Audit 2020-Curren'!$C:$C,'TB All Check'!$B$7,'TB & MCC Cost Audit 2020-Curren'!$D:$D,'TB All Check'!$A$7) -> 0 | D17: =SUMIFS('2022 Partial Rev - NS'!$N:$N,'2022 Partial Rev - NS'!$G:$G,'TB All Check'!$B17,'2022 Partial Rev - NS'!$P:$P,'TB All Check'!$B$7) -> 0 | E17: =C17-D17 -> 0 | G17: Badger | H17: Badger Meter | I17: =SUMIFS('TB & MCC Cost Audit 2020-Curren'!$P:$P,'TB & MCC Cost Audit 2020-Curren'!$A:$A,'TB All Check'!$A17,'TB & MCC Cost Audit 2020-Curren'!$C:$C,'TB All Check'!$H$7,'TB & MCC Cost Audit 2020-Curren'!$D:$D,'TB All Check'!$G$7) -> 188126 | J17: =SUMIFS('2023 Rev - NS'!$N:$N,'2023 Rev - NS'!$G:$G,'TB All Check'!$H17,'2023 Rev - NS'!$P:$P,'TB All Check'!$H$7) -> 188126 | K17: =I17-J17 -> 0 | M17: Badger | N17: Badger Meter | O17: =SUMIFS('TB & MCC Cost Audit 2020-Curren'!$P:$P,'TB & MCC Cost Audit 2020-Curren'!$A:$A,'TB All Check'!$M17,'TB & MCC Cost Audit 2020-Curren'!$C:$C,'TB All Check'!$N$7,'TB & MCC Cost Audit 2020-Curren'!$D:$D,'TB All Check'!$M$7) -> 0 | P17: =SUMIFS('2024 Rev - NS'!$N:$N,'2024 Rev - NS'!$G:$G,'TB All Check'!$N17,'2024 Rev - NS'!$P:$P,'TB All Check'!$N$7) -> 0 | Q17: =P17-O17 -> 0
A18: Beverly Hills | B18: Beverly Hills, City of | C18: =SUMIFS('TB & MCC Cost Audit 2020-Curren'!$P:$P,'TB & MCC Cost Audit 2020-Curren'!$A:$A,'TB All Check'!$A18,'TB & MCC Cost Audit 2020-Curren'!$C:$C,'TB All Check'!$B$7,'TB & MCC Cost Audit 2020-Curren'!$D:$D,'TB All Check'!$A$7) -> 14007 | D18: =SUMIFS('2022 Partial Rev - NS'!$N:$N,'2022 Partial Rev - NS'!$G:$G,'TB All Check'!$B18,'2022 Partial Rev - NS'!$P:$P,'TB All Check'!$B$7) -> 14007 | E18: =C18-D18 -> 0 | G18: Beverly Hills | H18: Beverly Hills, City of | I18: =SUMIFS('TB & MCC Cost Audit 2020-Curren'!$P:$P,'TB & MCC Cost Audit 2020-Curren'!$A:$A,'TB All Check'!$A18,'TB & MCC Cost Audit 2020-Curren'!$C:$C,'TB All Check'!$H$7,'TB & MCC Cost Audit 2020-Curren'!$D:$D,'TB All Check'!$G$7) -> 0 | J18: =SUMIFS('2023 Rev - NS'!$N:$N,'2023 Rev - NS'!$G:$G,'TB All Check'!$H18,'2023 Rev - NS'!$P:$P,'TB All Check'!$H$7) -> 0 | K18: =I18-J18 -> 0 | M18: Beverly Hills | N18: Beverly Hills, City of | O18: =SUMIFS('TB & MCC Cost Audit 2020-Curren'!$P:$P,'TB & MCC Cost Audit 2020-Curren'!$A:$A,'TB All Check'!$M18,'TB & MCC Cost Audit 2020-Curren'!$C:$C,'TB All Check'!$N$7,'TB & MCC Cost Audit 2020-Curren'!$D:$D,'TB All Check'!$M$7) -> 25403 | P18: =SUMIFS('2024 Rev - NS'!$N:$N,'2024 Rev - NS'!$G:$G,'TB All Check'!$N18,'2024 Rev - NS'!$P:$P,'TB All Check'!$N$7) -> 25403 | Q18: =P18-O18 -> 0
A19: Birmingham | B19: Birmingham Water Works | C19: =SUMIFS('TB & MCC Cost Audit 2020-Curren'!$P:$P,'TB & MCC Cost Audit 2020-Curren'!$A:$A,'TB All Check'!$A19,'TB & MCC Cost Audit 2020-Curren'!$C:$C,'TB All Check'!$B$7,'TB & MCC Cost Audit 2020-Curren'!$D:$D,'TB All Check'!$A$7) -> 0 | D19: =SUMIFS('2022 Partial Rev - NS'!$N:$N,'2022 Partial Rev - NS'!$G:$G,'TB All Check'!$B19,'2022 Partial Rev - NS'!$P:$P,'TB All Check'!$B$7) -> 0 | E19: =C19-D19 -> 0 | G19: Birmingham | H19: Birmingham Water Works | I19: =SUMIFS('TB & MCC Cost Audit 2020-Curren'!$P:$P,'TB & MCC Cost Audit 2020-Curren'!$A:$A,'TB All Check'!$A19,'TB & MCC Cost Audit 2020-Curren'!$C:$C,'TB All Check'!$H$7,'TB & MCC Cost Audit 2020-Curren'!$D:$D,'TB All Check'!$G$7) -> 0 | J19: =SUMIFS('2023 Rev - NS'!$N:$N,'2023 Rev - NS'!$G:$G,'TB All Check'!$H19,'2023 Rev - NS'!$P:$P,'TB All Check'!$H$7) -> 0 | K19: =I19-J19 -> 0 | M19: Birmingham | N19: Birmingham Water Works | O19: =SUMIFS('TB & MCC Cost Audit 2020-Curren'!$P:$P,'TB & MCC Cost Audit 2020-Curren'!$A:$A,'TB All Check'!$M19,'TB & MCC Cost Audit 2020-Curren'!$C:$C,'TB All Check'!$N$7,'TB & MCC Cost Audit 2020-Curren'!$D:$D,'TB All Check'!$M$7) -> 0 | P19: =SUMIFS('2024 Rev - NS'!$N:$N,'2024 Rev - NS'!$G:$G,'TB All Check'!$N19,'2024 Rev - NS'!$P:$P,'TB All Check'!$N$7) -> 0 | Q19: =P19-O19 -> 0
A20: Boston | B20: Boston Water & Sewer Commission | C20: =SUMIFS('TB & MCC Cost Audit 2020-Curren'!$P:$P,'TB & MCC Cost Audit 2020-Curren'!$A:$A,'TB All Check'!$A20,'TB & MCC Cost Audit 2020-Curren'!$C:$C,'TB All Check'!$B$7,'TB & MCC Cost Audit 2020-Curren'!$D:$D,'TB All Check'!$A$7) -> 0 | D20: =SUMIFS('2022 Partial Rev - NS'!$N:$N,'2022 Partial Rev - NS'!$G:$G,'TB All Check'!$B20,'2022 Partial Rev - NS'!$P:$P,'TB All Check'!$B$7) -> 0 | E20: =C20-D20 -> 0 | G20: Boston | H20: Boston Water & Sewer Commission | I20: =SUMIFS('TB & MCC Cost Audit 2020-Curren'!$P:$P,'TB & MCC Cost Audit 2020-Curren'!$A:$A,'TB All Check'!$A20,'TB & MCC Cost Audit 2020-Curren'!$C:$C,'TB All Check'!$H$7,'TB & MCC Cost Audit 2020-Curren'!$D:$D,'TB All Check'!$G$7) -> 0 | J20: =SUMIFS('2023 Rev - NS'!$N:$N,'2023 Rev - NS'!$G:$G,'TB All Check'!$H20,'2023 Rev - NS'!$P:$P,'TB All Check'!$H$7) -> 0 | K20: =I20-J20 -> 0 | M20: Boston | N20: Boston Water & Sewer Commission | O20: =SUMIFS('TB & MCC Cost Audit 2020-Curren'!$P:$P,'TB & MCC Cost Audit 2020-Curren'!$A:$A,'TB All Check'!$M20,'TB & MCC Cost Audit 2020-Curren'!$C:$C,'TB All Check'!$N$7,'TB & MCC Cost Audit 2020-Curren'!$D:$D,'TB All Check'!$M$7) -> 28891 | P20: =SUMIFS('2024 Rev - NS'!$N:$N,'2024 Rev - NS'!$G:$G,'TB All Check'!$N20,'2024 Rev - NS'!$P:$P,'TB All Check'!$N$7) -> 28891 | Q20: =P20-O20 -> 0
A21: CD'A | B21: Coeur D' Alene, City of | C21: =SUMIFS('TB & MCC Cost Audit 2020-Curren'!$P:$P,'TB & MCC Cost Audit 2020-Curren'!$A:$A,'TB All Check'!$A21,'TB & MCC Cost Audit 2020-Curren'!$C:$C,'TB All Check'!$B$7,'TB & MCC Cost Audit 2020-Curren'!$D:$D,'TB All Check'!$A$7) -> 22926.96 | D21: =SUMIFS('2022 Partial Rev - NS'!$N:$N,'2022 Partial Rev - NS'!$G:$G,'TB All Check'!$B21,'2022 Partial Rev - NS'!$P:$P,'TB All Check'!$B$7) -> 22926.96 | E21: =C21-D21 -> 0 | G21: CD'A | H21: Coeur D' Alene, City of | I21: =SUMIFS('TB & MCC Cost Audit 2020-Curren'!$P:$P,'TB & MCC Cost Audit 2020-Curren'!$A:$A,'TB All Check'!$A21,'TB & MCC Cost Audit 2020-Curren'!$C:$C,'TB All Check'!$H$7,'TB & MCC Cost Audit 2020-Curren'!$D:$D,'TB All Check'!$G$7) -> 0 | J21: =SUMIFS('2023 Rev - NS'!$N:$N,'2023 Rev - NS'!$G:$G,'TB All Check'!$H21,'2023 Rev - NS'!$P:$P,'TB All Check'!$H$7) -> 0 | K21: =I21-J21 -> 0 | M21: CD'A | N21: Coeur D' Alene, City of | O21: =SUMIFS('TB & MCC Cost Audit 2020-Curren'!$P:$P,'TB & MCC Cost Audit 2020-Curren'!$A:$A,'TB All Check'!$M21,'TB & MCC Cost Audit 2020-Curren'!$C:$C,'TB All Check'!$N$7,'TB & MCC Cost Audit 2020-Curren'!$D:$D,'TB All Check'!$M$7) -> 31795 | P21: =SUMIFS('2024 Rev - NS'!$N:$N,'2024 Rev - NS'!$G:$G,'TB All Check'!$N21,'2024 Rev - NS'!$P:$P,'TB All Check'!$N$7) -> 31795 | Q21: =P21-O21 -> 0
A22: Chicago | B22: Chicago, City of | C22: =SUMIFS('TB & MCC Cost Audit 2020-Curren'!$P:$P,'TB & MCC Cost Audit 2020-Curren'!$A:$A,'TB All Check'!$A22,'TB & MCC Cost Audit 2020-Curren'!$C:$C,'TB All Check'!$B$7,'TB & MCC Cost Audit 2020-Curren'!$D:$D,'TB All Check'!$A$7) -> 32114.996 | D22: =SUMIFS('2022 Partial Rev - NS'!$N:$N,'2022 Partial Rev - NS'!$G:$G,'TB All Check'!$B22,'2022 Partial Rev - NS'!$P:$P,'TB All Check'!$B$7) -> 32115 | E22: =C22-D22 -> -0.004 | G22: Chicago | H22: Chicago, City of | I22: =SUMIFS('TB & MCC Cost Audit 2020-Curren'!$P:$P,'TB & MCC Cost Audit 2020-Curren'!$A:$A,'TB All Check'!$A22,'TB & MCC Cost Audit 2020-Curren'!$C:$C,'TB All Check'!$H$7,'TB & MCC Cost Audit 2020-Curren'!$D:$D,'TB All Check'!$G$7) -> 0 | J22: =SUMIFS('2023 Rev - NS'!$N:$N,'2023 Rev - NS'!$G:$G,'TB All Check'!$H22,'2023 Rev - NS'!$P:$P,'TB All Check'!$H$7) -> 0 | K22: =I22-J22 -> 0 | M22: Chicago | N22: Chicago, City of | O22: =SUMIFS('TB & MCC Cost Audit 2020-Curren'!$P:$P,'TB & MCC Cost Audit 2020-Curren'!$A:$A,'TB All Check'!$M22,'TB & MCC Cost Audit 2020-Curren'!$C:$C,'TB All Check'!$N$7,'TB & MCC Cost Audit 2020-Curren'!$D:$D,'TB All Check'!$M$7) -> 28480 | P22: =SUMIFS('2024 Rev - NS'!$N:$N,'2024 Rev - NS'!$G:$G,'TB All Check'!$N22,'2024 Rev - NS'!$P:$P,'TB All Check'!$N$7) -> 28480 | Q22: =P22-O22 -> 0
A23: Cleveland | B23: Cleveland, City of | C23: =SUMIFS('TB & MCC Cost Audit 2020-Curren'!$P:$P,'TB & MCC Cost Audit 2020-Curren'!$A:$A,'TB All Check'!$A23,'TB & MCC Cost Audit 2020-Curren'!$C:$C,'TB All Check'!$B$7,'TB & MCC Cost Audit 2020-Curren'!$D:$D,'TB All Check'!$A$7) -> 29746 | D23: =SUMIFS('2022 Partial Rev - NS'!$N:$N,'2022 Partial Rev - NS'!$G:$G,'TB All Check'!$B23,'2022 Partial Rev - NS'!$P:$P,'TB All Check'!$B$7) -> 29746 | E23: =C23-D23 -> 0 | G23: Cleveland | H23: Cleveland, City of | I23: =SUMIFS('TB & MCC Cost Audit 2020-Curren'!$P:$P,'TB & MCC Cost Audit 2020-Curren'!$A:$A,'TB All Check'!$A23,'TB & MCC Cost Audit 2020-Curren'!$C:$C,'TB All Check'!$H$7,'TB & MCC Cost Audit 2020-Curren'!$D:$D,'TB All Check'!$G$7) -> 0 | J23: =SUMIFS('2023 Rev - NS'!$N:$N,'2023 Rev - NS'!$G:$G,'TB All Check'!$H23,'2023 Rev - NS'!$P:$P,'TB All Check'!$H$7) -> 0 | K23: =I23-J23 -> 0 | M23: Cleveland | N23: Cleveland, City of | O23: =SUMIFS('TB & MCC Cost Audit 2020-Curren'!$P:$P,'TB & MCC Cost Audit 2020-Curren'!$A:$A,'TB All Check'!$M23,'TB & MCC Cost Audit 2020-Curren'!$C:$C,'TB All Check'!$N$7,'TB & MCC Cost Audit 2020-Curren'!$D:$D,'TB All Check'!$M$7) -> 38684 | P23: =SUMIFS('2024 Rev - NS'!$N:$N,'2024 Rev - NS'!$G:$G,'TB All Check'!$N23,'2024 Rev - NS'!$P:$P,'TB All Check'!$N$7) -> 38684 | Q23: =P23-O23 -> 0
... A30: DC Water | B30: D.C. Water & Sewer | C30: =SUMIFS('TB & MCC Cost Audit 2020-Curren'!$P:$P,'TB & MCC Cost Audit 2020-Curren'!$A:$A,'TB All Check'!$A30,'TB & MCC Cost Audit 2020-Curren'!$C:$C,'TB All Check'!$B$7,'TB & MCC Cost Audit 2020-Curren'!$D:$D,'TB All Check'!$A$7) -> 36196.33 | D30: =SUMIFS('2022 Partial Rev - NS'!$N:$N,'2022 Partial Rev - NS'!$G:$G,'TB All Check'!$B30,'2022 Partial Rev - NS'!$P:$P,'TB All Check'!$B$7) -> 36196.33 | E30: =C30-D30 -> 0 | G30: DC Water | H30: D.C. Water & Sewer | I30: =SUMIFS('TB & MCC Cost Audit 2020-Curren'!$P:$P,'TB & MCC Cost Audit 2020-Curren'!$A:$A,'TB All Check'!$A30,'TB & MCC Cost Audit 2020-Curren'!$C:$C,'TB All Check'!$H$7,'TB & MCC Cost Audit 2020-Curren'!$D:$D,'TB All Check'!$G$7) -> 0 | J30: =SUMIFS('2023 Rev - NS'!$N:$N,'2023 Rev - NS'!$G:$G,'TB All Check'!$H30,'2023 Rev - NS'!$P:$P,'TB All Check'!$H$7) -> 0 | K30: =I30-J30 -> 0 | M30: DC Water | N30: D.C. Water & Sewer | O30: =SUMIFS('TB & MCC Cost Audit 2020-Curren'!$P:$P,'TB & MCC Cost Audit 2020-Curren'!$A:$A,'TB All Check'!$M30,'TB & MCC Cost Audit 2020-Curren'!$C:$C,'TB All Check'!$N$7,'TB & MCC Cost Audit 2020-Curren'!$D:$D,'TB All Check'!$M$7) -> 39103.593 | P30: =SUMIFS('2024 Rev - NS'!$N:$N,'2024 Rev - NS'!$G:$G,'TB All Check'!$N30,'2024 Rev - NS'!$P:$P,'TB All Check'!$N$7) -> 39103.59 | Q30: =P30-O30 -> -0.0033333333
A31: Dekalb | B31: Dekalb County Water Department | C31: =SUMIFS('TB & MCC Cost Audit 2020-Curren'!$P:$P,'TB & MCC Cost Audit 2020-Curren'!$A:$A,'TB All Check'!$A31,'TB & MCC Cost Audit 2020-Curren'!$C:$C,'TB All Check'!$B$7,'TB & MCC Cost Audit 2020-Curren'!$D:$D,'TB All Check'!$A$7) -> 15498 | D31: 15498 | E31: =C31-D31 -> 0 | G31: Dekalb | H31: Dekalb County Water Department | I31: =SUMIFS('TB & MCC Cost Audit 2020-Curren'!$P:$P,'TB & MCC Cost Audit 2020-Curren'!$A:$A,'TB All Check'!$A31,'TB & MCC Cost Audit 2020-Curren'!$C:$C,'TB All Check'!$H$7,'TB & MCC Cost Audit 2020-Curren'!$D:$D,'TB All Check'!$G$7) -> 0 | J31: =SUMIFS('2023 Rev - NS'!$N:$N,'2023 Rev - NS'!$G:$G,'TB All Check'!$H31,'2023 Rev - NS'!$P:$P,'TB All Check'!$H$7) -> 0 | K31: =I31-J31 -> 0 | M31: Dekalb | N31: Dekalb County Water Department | O31: =SUMIFS('TB & MCC Cost Audit 2020-Curren'!$P:$P,'TB & MCC Cost Audit 2020-Curren'!$A:$A,'TB All Check'!$M31,'TB & MCC Cost Audit 2020-Curren'!$C:$C,'TB All Check'!$N$7,'TB & MCC Cost Audit 2020-Curren'!$D:$D,'TB All Check'!$M$7) -> 17086 | P31: =SUMIFS('2024 Rev - NS'!$N:$N,'2024 Rev - NS'!$G:$G,'TB All Check'!$N31,'2024 Rev - NS'!$P:$P,'TB All Check'!$N$7) -> 17086 | Q31: =P31-O31 -> 0
A32: Denton | B32: Denton, City of | C32: =SUMIFS('TB & MCC Cost Audit 2020-Curren'!$P:$P,'TB & MCC Cost Audit 2020-Curren'!$A:$A,'TB All Check'!$A32,'TB & MCC Cost Audit 2020-Curren'!$C:$C,'TB All Check'!$B$7,'TB & MCC Cost Audit 2020-Curren'!$D:$D,'TB All Check'!$A$7) -> 0 | D32: =SUMIFS('2022 Partial Rev - NS'!$N:$N,'2022 Partial Rev - NS'!$G:$G,'TB All Check'!$B32,'2022 Partial Rev - NS'!$P:$P,'TB All Check'!$B$7) -> 0 | E32: =C32-D32 -> 0 | G32: Denton | H32: Denton, City of | I32: =SUMIFS('TB & MCC Cost Audit 2020-Curren'!$P:$P,'TB & MCC Cost Audit 2020-Curren'!$A:$A,'TB All Check'!$A32,'TB & MCC Cost Audit 2020-Curren'!$C:$C,'TB All Check'!$H$7,'TB & MCC Cost Audit 2020-Curren'!$D:$D,'TB All Check'!$G$7) -> 311511 | J32: =SUMIFS('2023 Rev - NS'!$N:$N,'2023 Rev - NS'!$G:$G,'TB All Check'!$H32,'2023 Rev - NS'!$P:$P,'TB All Check'!$H$7) -> 311511 | K32: =I32-J32 -> 0 | M32: Denton | N32: Denton, City of | O32: =SUMIFS('TB & MCC Cost Audit 2020-Curren'!$P:$P,'TB & MCC Cost Audit 2020-Curren'!$A:$A,'TB All Check'!$M32,'TB & MCC Cost Audit 2020-Curren'!$C:$C,'TB All Check'!$N$7,'TB & MCC Cost Audit 2020-Curren'!$D:$D,'TB All Check'!$M$7) -> 21344 | P32: =SUMIFS('2024 Rev - NS'!$N:$N,'2024 Rev - NS'!$G:$G,'TB All Check'!$N32,'2024 Rev - NS'!$P:$P,'TB All Check'!$N$7) -> 21344 | Q32: =P32-O32 -> 0
A33: Denver | B33: Denver Water | C33: =SUMIFS('TB & MCC Cost Audit 2020-Curren'!$P:$P,'TB & MCC Cost Audit 2020-Curren'!$A:$A,'TB All Check'!$A33,'TB & MCC Cost Audit 2020-Curren'!$C:$C,'TB All Check'!$B$7,'TB & MCC Cost Audit 2020-Curren'!$D:$D,'TB All Check'!$A$7) -> 23470.49 | D33: =SUMIFS('2022 Partial Rev - NS'!$N:$N,'2022 Partial Rev - NS'!$G:$G,'TB All Check'!$B33,'2022 Partial Rev - NS'!$P:$P,'TB All Check'!$B$7) -> 23470.49 | E33: =C33-D33 -> 0 | G33: Denver | H33: Denver Water | I33: =SUMIFS('TB & MCC Cost Audit 2020-Curren'!$P:$P,'TB & MCC Cost Audit 2020-Curren'!$A:$A,'TB All Check'!$A33,'TB & MCC Cost Audit 2020-Curren'!$C:$C,'TB All Check'!$H$7,'TB & MCC Cost Audit 2020-Curren'!$D:$D,'TB All Check'!$G$7) -> 0 | J33: =SUMIFS('2023 Rev - NS'!$N:$N,'2023 Rev - NS'!$G:$G,'TB All Check'!$H33,'2023 Rev - NS'!$P:$P,'TB All Check'!$H$7) -> 0 | K33: =I33-J33 -> 0 | M33: Denver | N33: Denver Water | O33: =SUMIFS('TB & MCC Cost Audit 2020-Curren'!$P:$P,'TB & MCC Cost Audit 2020-Curren'!$A:$A,'TB All Check'!$M33,'TB & MCC Cost Audit 2020-Curren'!$C:$C,'TB All Check'!$N$7,'TB & MCC Cost Audit 2020-Curren'!$D:$D,'TB All Check'!$M$7) -> 0 | P33: =SUMIFS('2024 Rev - NS'!$N:$N,'2024 Rev - NS'!$G:$G,'TB All Check'!$N33,'2024 Rev - NS'!$P:$P,'TB All Check'!$N$7) -> 0 | Q33: =P33-O33 -> 0
A34: Detroit | B34: Detroit, City of | C34: =SUMIFS('TB & MCC Cost Audit 2020-Curren'!$P:$P,'TB & MCC Cost Audit 2020-Curren'!$A:$A,'TB All Check'!$A34,'TB & MCC Cost Audit 2020-Curren'!$C:$C,'TB All Check'!$B$7,'TB & MCC Cost Audit 2020-Curren'!$D:$D,'TB All Check'!$A$7) -> 35058 | D34: =SUMIFS('2022 Partial Rev - NS'!$N:$N,'2022 Partial Rev - NS'!$G:$G,'TB All Check'!$B34,'2022 Partial Rev - NS'!$P:$P,'TB All Check'!$B$7) -> 35058 | E34: =C34-D34 -> 0 | G34: Detroit | H34: Detroit, City of | I34: =SUMIFS('TB & MCC Cost Audit 2020-Curren'!$P:$P,'TB & MCC Cost Audit 2020-Curren'!$A:$A,'TB All Check'!$A34,'TB & MCC Cost Audit 2020-Curren'!$C:$C,'TB All Check'!$H$7,'TB & MCC Cost Audit 2020-Curren'!$D:$D,'TB All Check'!$G$7) -> 0 | J34: =SUMIFS('2023 Rev - NS'!$N:$N,'2023 Rev - NS'!$G:$G,'TB All Check'!$H34,'2023 Rev - NS'!$P:$P,'TB All Check'!$H$7) -> 0 | K34: =I34-J34 -> 0 | M34: Detroit | N34: Detroit, City of | O34: =SUMIFS('TB & MCC Cost Audit 2020-Curren'!$P:$P,'TB & MCC Cost Audit 2020-Curren'!$A:$A,'TB All Check'!$M34,'TB & MCC Cost Audit 2020-Curren'!$C:$C,'TB All Check'!$N$7,'TB & MCC Cost Audit 2020-Curren'!$D:$D,'TB All Check'!$M$7) -> 46713 | P34: =SUMIFS('2024 Rev - NS'!$N:$N,'2024 Rev - NS'!$G:$G,'TB All Check'!$N34,'2024 Rev - NS'!$P:$P,'TB All Check'!$N$7) -> 46713 | Q34: =P34-O34 -> 0
A35: EBMUD | B35: East Bay Mud | C35: =SUMIFS('TB & MCC Cost Audit 2020-Curren'!$P:$P,'TB & MCC Cost Audit 2020-Curren'!$A:$A,'TB All Check'!$A35,'TB & MCC Cost Audit 2020-Curren'!$C:$C,'TB All Check'!$B$7,'TB & MCC Cost Audit 2020-Curren'!$D:$D,'TB All Check'!$A$7) -> 31647 | D35: =SUMIFS('2022 Partial Rev - NS'!$N:$N,'2022 Partial Rev - NS'!$G:$G,'TB All Check'!$B35,'2022 Partial Rev - NS'!$P:$P,'TB All Check'!$B$7) -> 31647 | E35: =C35-D35 -> 0 | G35: EBMUD | H35: East Bay Mud | I35: =SUMIFS('TB & MCC Cost Audit 2020-Curren'!$P:$P,'TB & MCC Cost Audit 2020-Curren'!$A:$A,'TB All Check'!$A35,'TB & MCC Cost Audit 2020-Curren'!$C:$C,'TB All Check'!$H$7,'TB & MCC Cost Audit 2020-Curren'!$D:$D,'TB All Check'!$G$7) -> 0 | J35: =SUMIFS('2023 Rev - NS'!$N:$N,'2023 Rev - NS'!$G:$G,'TB All Check'!$H35,'2023 Rev - NS'!$P:$P,'TB All Check'!$H$7) -> 0 | K35: =I35-J35 -> 0 | M35: EBMUD | N35: East Bay Mud | O35: =SUMIFS('TB & MCC Cost Audit 2020-Curren'!$P:$P,'TB & MCC Cost Audit 2020-Curren'!$A:$A,'TB All Check'!$M35,'TB & MCC Cost Audit 2020-Curren'!$C:$C,'TB All Check'!$N$7,'TB & MCC Cost Audit 2020-Curren'!$D:$D,'TB All Check'!$M$7) -> 31648 | P35: =SUMIFS('2024 Rev - NS'!$N:$N,'2024 Rev - NS'!$G:$G,'TB All Check'!$N35,'2024 Rev - NS'!$P:$P,'TB All Check'!$N$7) -> 31648 | Q35: =P35-O35 -> 0
A36: El Dorado | B36: El Dorado Irrigation District | C36: =SUMIFS('TB & MCC Cost Audit 2020-Curren'!$P:$P,'TB & MCC Cost Audit 2020-Curren'!$A:$A,'TB All Check'!$A36,'TB & MCC Cost Audit 2020-Curren'!$C:$C,'TB All Check'!$B$7,'TB & MCC Cost Audit 2020-Curren'!$D:$D,'TB All Check'!$A$7) -> 16486 | D36: 16486 | E36: =C36-D36 -> 0 | G36: El Dorado | H36: El Dorado Irrigation District | I36: =SUMIFS('TB & MCC Cost Audit 2020-Curren'!$P:$P,'TB & MCC Cost Audit 2020-Curren'!$A:$A,'TB All Check'!$A36,'TB & MCC Cost Audit 2020-Curren'!$C:$C,'TB All Check'!$H$7,'TB & MCC Cost Audit 2020-Curren'!$D:$D,'TB All Check'!$G$7) -> 0 | J36: =SUMIFS('2023 Rev - NS'!$N:$N,'2023 Rev - NS'!$G:$G,'TB All Check'!$H36,'2023 Rev - NS'!$P:$P,'TB All Check'!$H$7) -> 0 | K36: =I36-J36 -> 0 | M36: El Dorado | N36: El Dorado Irrigation District | O36: =SUMIFS('TB & MCC Cost Audit 2020-Curren'!$P:$P,'TB & MCC Cost Audit 2020-Curren'!$A:$A,'TB All Check'!$M36,'TB & MCC Cost Audit 2020-Curren'!$C:$C,'TB All Check'!$N$7,'TB & MCC Cost Audit 2020-Curren'!$D:$D,'TB All Check'!$M$7) -> 17017 | P36: =SUMIFS('2024 Rev - NS'!$N:$N,'2024 Rev - NS'!$G:$G,'TB All Check'!$N36,'2024 Rev - NS'!$P:$P,'TB All Check'!$N$7) -> 17017 | Q36: =P36-O36 -> 0
A37: Emerald Coast | B37: Emerald Coast Utilities Authority | C37: =SUMIFS('TB & MCC Cost Audit 2020-Curren'!$P:$P,'TB & MCC Cost Audit 2020-Curren'!$A:$A,'TB All Check'!$A37,'TB & MCC Cost Audit 2020-Curren'!$C:$C,'TB All Check'!$B$7,'TB & MCC Cost Audit 2020-Curren'!$D:$D,'TB All Check'!$A$7) -> 0 | D37: =SUMIFS('2022 Partial Rev - NS'!$N:$N,'2022 Partial Rev - NS'!$G:$G,'TB All Check'!$B37,'2022 Partial Rev - NS'!$P:$P,'TB All Check'!$B$7) -> 0 | E37: =C37-D37 -> 0 | G37: Emerald Coast | H37: Emerald Coast Utilities Authority | I37: =SUMIFS('TB & MCC Cost Audit 2020-Curren'!$P:$P,'TB & MCC Cost Audit 2020-Curren'!$A:$A,'TB All Check'!$A37,'TB & MCC Cost Audit 2020-Curren'!$C:$C,'TB All Check'!$H$7,'TB & MCC Cost Audit 2020-Curren'!$D:$D,'TB All Check'!$G$7) -> 196758 | J37: =SUMIFS('2023 Rev - NS'!$N:$N,'2023 Rev - NS'!$G:$G,'TB All Check'!$H37,'2023 Rev - NS'!$P:$P,'TB All Check'!$H$7) -> 196758 | K37: =I37-J37 -> 0 | M37: Emerald Coast | N37: Emerald Coast Utilities Authority | O37: =SUMIFS('TB & MCC Cost Audit 2020-Curren'!$P:$P,'TB & MCC Cost Audit 2020-Curren'!$A:$A,'TB All Check'!$M37,'TB & MCC Cost Audit 2020-Curren'!$C:$C,'TB All Check'!$N$7,'TB & MCC Cost Audit 2020-Curren'!$D:$D,'TB All Check'!$M$7) -> 0 | P37: =SUMIFS('2024 Rev - NS'!$N:$N,'2024 Rev - NS'!$G:$G,'TB All Check'!$N37,'2024 Rev - NS'!$P:$P,'TB All Check'!$N$7) -> 0 | Q37: =P37-O37 -> 0
A38: Fairfax | B38: Fairfax County Water | C38: =SUMIFS('TB & MCC Cost Audit 2020-Curren'!$P:$P,'TB & MCC Cost Audit 2020-Curren'!$A:$A,'TB All Check'!$A38,'TB & MCC Cost Audit 2020-Curren'!$C:$C,'TB All Check'!$B$7,'TB & MCC Cost Audit 2020-Curren'!$D:$D,'TB All Check'!$A$7) -> 0 | D38: =SUMIFS('2022 Partial Rev - NS'!$N:$N,'2022 Partial Rev - NS'!$G:$G,'TB All Check'!$B38,'2022 Partial Rev - NS'!$P:$P,'TB All Check'!$B$7) -> 0 | E38: =C38-D38 -> 0 | G38: Fairfax | H38: Fairfax County Water | I38: =SUMIFS('TB & MCC Cost Audit 2020-Curren'!$P:$P,'TB & MCC Cost Audit 2020-Curren'!$A:$A,'TB All Check'!$A38,'TB & MCC Cost Audit 2020-Curren'!$C:$C,'TB All Check'!$H$7,'TB & MCC Cost Audit 2020-Curren'!$D:$D,'TB All Check'!$G$7) -> 712216 | J38: =SUMIFS('2023 Rev - NS'!$N:$N,'2023 Rev - NS'!$G:$G,'TB All Check'!$H38,'2023 Rev - NS'!$P:$P,'TB All Check'!$H$7) -> 712216 | K38: =I38-J38 -> 0 | M38: Fairfax | N38: Fairfax County Water | O38: =SUMIFS('TB & MCC Cost Audit 2020-Curren'!$P:$P,'TB & MCC Cost Audit 2020-Curren'!$A:$A,'TB All Check'!$M38,'TB & MCC Cost Audit 2020-Curren'!$C:$C,'TB All Check'!$N$7,'TB & MCC Cost Audit 2020-Curren'!$D:$D,'TB All Check'!$M$7) -> 0 | P38: =SUMIFS('2024 Rev - NS'!$N:$N,'2024 Rev - NS'!$G:$G,'TB All Check'!$N38,'2024 Rev - NS'!$P:$P,'TB All Check'!$N$7) -> 0 | Q38: =P38-O38 -> 0
A39: FGUA | B39: Florida Governmental Utility A | C39: =SUMIFS('TB & MCC Cost Audit 2020-Curren'!$P:$P,'TB & MCC Cost Audit 2020-Curren'!$A:$A,'TB All Check'!$A39,'TB & MCC Cost Audit 2020-Curren'!$C:$C,'TB All Check'!$B$7,'TB & MCC Cost Audit 2020-Curren'!$D:$D,'TB All Check'!$A$7) -> 0 | D39: =SUMIFS('2022 Partial Rev - NS'!$N:$N,'2022 Partial Rev - NS'!$G:$G,'TB All Check'!$B39,'2022 Partial Rev - NS'!$P:$P,'TB All Check'!$B$7) -> 0 | E39: =C39-D39 -> 0 | G39: FGUA | H39: Florida Governmental Utility A | I39: =SUMIFS('TB & MCC Cost Audit 2020-Curren'!$P:$P,'TB & MCC Cost Audit 2020-Curren'!$A:$A,'TB All Check'!$A39,'TB & MCC Cost Audit 2020-Curren'!$C:$C,'TB All Check'!$H$7,'TB & MCC Cost Audit 2020-Curren'!$D:$D,'TB All Check'!$G$7) -> 0 | J39: =SUMIFS('2023 Rev - NS'!$N:$N,'2023 Rev - NS'!$G:$G,'TB All Check'!$H39,'2023 Rev - NS'!$P:$P,'TB All Check'!$H$7) -> 0 | K39: =I39-J39 -> 0 | M39: FGUA | N39: Florida Governmental Utility A | O39: =SUMIFS('TB & MCC Cost Audit 2020-Curren'!$P:$P,'TB & MCC Cost Audit 2020-Curren'!$A:$A,'TB All Check'!$M39,'TB & MCC Cost Audit 2020-Curren'!$C:$C,'TB All Check'!$N$7,'TB & MCC Cost Audit 2020-Curren'!$D:$D,'TB All Check'!$M$7) -> 0 | P39: =SUMIFS('2024 Rev - NS'!$N:$N,'2024 Rev - NS'!$G:$G,'TB All Check'!$N39,'2024 Rev - NS'!$P:$P,'TB All Check'!$N$7) -> 0 | Q39: =P39-O39 -> 0
A40: Folsom | B40: Folsom, City of | C40: =SUMIFS('TB & MCC Cost Audit 2020-Curren'!$P:$P,'TB & MCC Cost Audit 2020-Curren'!$A:$A,'TB All Check'!$A40,'TB & MCC Cost Audit 2020-Curren'!$C:$C,'TB All Check'!$B$7,'TB & MCC Cost Audit 2020-Curren'!$D:$D,'TB All Check'!$A$7) -> 0 | D40: =SUMIFS('2022 Partial Rev - NS'!$N:$N,'2022 Partial Rev - NS'!$G:$G,'TB All Check'!$B40,'2022 Partial Rev - NS'!$P:$P,'TB All Check'!$B$7) -> 0 | E40: =C40-D40 -> 0 | G40: Folsom | H40: Folsom, City of | I40: =SUMIFS('TB & MCC Cost Audit 2020-Curren'!$P:$P,'TB & MCC Cost Audit 2020-Curren'!$A:$A,'TB All Check'!$A40,'TB & MCC Cost Audit 2020-Curren'!$C:$C,'TB All Check'!$H$7,'TB & MCC Cost Audit 2020-Curren'!$D:$D,'TB All Check'!$G$7) -> 0 | J40: =SUMIFS('2023 Rev - NS'!$N:$N,'2023 Rev - NS'!$G:$G,'TB All Check'!$H40,'2023 Rev - NS'!$P:$P,'TB All Check'!$H$7) -> 0 | K40: =I40-J40 -> 0 | M40: Folsom | N40: Folsom, City of | O40: =SUMIFS('TB & MCC Cost Audit 2020-Curren'!$P:$P,'TB & MCC Cost Audit 2020-Curren'!$A:$A,'TB All Check'!$M40,'TB & MCC Cost Audit 2020-Curren'!$C:$C,'TB All Check'!$N$7,'TB & MCC Cost Audit 2020-Curren'!$D:$D,'TB All Check'!$M$7) -> 0 | P40: =SUMIFS('2024 Rev - NS'!$N:$N,'2024 Rev - NS'!$G:$G,'TB All Check'!$N40,'2024 Rev - NS'!$P:$P,'TB All Check'!$N$7) -> 0 | Q40: =P40-O40 -> 0
A41: Fontana | B41: San Gabriel Valley Water Company : Fontana Water Company | C41: =SUMIFS('TB & MCC Cost Audit 2020-Curren'!$P:$P,'TB & MCC Cost Audit 2020-Curren'!$A:$A,'TB All Check'!$A41,'TB & MCC Cost Audit 2020-Curren'!$C:$C,'TB All Check'!$B$7,'TB & MCC Cost Audit 2020-Curren'!$D:$D,'TB All Check'!$A$7) -> 0 | D41: =SUMIFS('2022 Partial Rev - NS'!$N:$N,'2022 Partial Rev - NS'!$G:$G,'TB All Check'!$B41,'2022 Partial Rev - NS'!$P:$P,'TB All Check'!$B$7) -> 0 | E41: =C41-D41 -> 0 | G41: Fontana | H41: San Gabriel Valley Water Company : Fontana Water Company | I41: =SUMIFS('TB & MCC Cost Audit 2020-Curren'!$P:$P,'TB & MCC Cost Audit 2020-Curren'!$A:$A,'TB All Check'!$A41,'TB & MCC Cost Audit 2020-Curren'!$C:$C,'TB All Check'!$H$7,'TB & MCC Cost Audit 2020-Curren'!$D:$D,'TB All Check'!$G$7) -> 229969 | J41: =SUMIFS('2023 Rev - NS'!$N:$N,'2023 Rev - NS'!$G:$G,'TB All Check'!$H41,'2023 Rev - NS'!$P:$P,'TB All Check'!$H$7) -> 229969 | K41: =I41-J41 -> 0 | M41: Fontana | N41: San Gabriel Valley Water Company : Fontana Water Company | O41: =SUMIFS('TB & MCC Cost Audit 2020-Curren'!$P:$P,'TB & MCC Cost Audit 2020-Curren'!$A:$A,'TB All Check'!$M41,'TB & MCC Cost Audit 2020-Curren'!$C:$C,'TB All Check'!$N$7,'TB & MCC Cost Audit 2020-Curren'!$D:$D,'TB All Check'!$M$7) -> 0 | P41: =SUMIFS('2024 Rev - NS'!$N:$N,'2024 Rev - NS'!$H:$H,'TB All Check'!$N41,'2024 Rev - NS'!$P:$P,'TB All Check'!$N$7) -> 0 | Q41: =P41-O41 -> 0
A42: Ft. Smith | B42: Fort Smith, City of | C42: =SUMIFS('TB & MCC Cost Audit 2020-Curren'!$P:$P,'TB & MCC Cost Audit 2020-Curren'!$A:$A,'TB All Check'!$A42,'TB & MCC Cost Audit 2020-Curren'!$C:$C,'TB All Check'!$B$7,'TB & MCC Cost Audit 2020-Curren'!$D:$D,'TB All Check'!$A$7) -> 9389 | D42: =SUMIFS('2022 Partial Rev - NS'!$N:$N,'2022 Partial Rev - NS'!$G:$G,'TB All Check'!$B42,'2022 Partial Rev - NS'!$P:$P,'TB All Check'!$B$7) -> 9389 | E42: =C42-D42 -> 0 | G42: Ft. Smith | H42: Fort Smith, City of | I42: =SUMIFS('TB & MCC Cost Audit 2020-Curren'!$P:$P,'TB & MCC Cost Audit 2020-Curren'!$A:$A,'TB All Check'!$A42,'TB & MCC Cost Audit 2020-Curren'!$C:$C,'TB All Check'!$H$7,'TB & MCC Cost Audit 2020-Curren'!$D:$D,'TB All Check'!$G$7) -> 0 | J42: =SUMIFS('2023 Rev - NS'!$N:$N,'2023 Rev - NS'!$G:$G,'TB All Check'!$H42,'2023 Rev - NS'!$P:$P,'TB All Check'!$H$7) -> 0 | K42: =I42-J42 -> 0 | M42: Ft. Smith | N42: Fort Smith, City of | O42: =SUMIFS('TB & MCC Cost Audit 2020-Curren'!$P:$P,'TB & MCC Cost Audit 2020-Curren'!$A:$A,'TB All Check'!$M42,'TB & MCC Cost Audit 2020-Curren'!$C:$C,'TB All Check'!$N$7,'TB & MCC Cost Audit 2020-Curren'!$D:$D,'TB All Check'!$M$7) -> 9961 | P42: =SUMIFS('2024 Rev - NS'!$N:$N,'2024 Rev - NS'!$G:$G,'TB All Check'!$N42,'2024 Rev - NS'!$P:$P,'TB All Check'!$N$7) -> 9961 | Q42: =P42-O42 -> 0
A43: Greeley | B43: Greeley, City of | C43: =SUMIFS('TB & MCC Cost Audit 2020-Curren'!$P:$P,'TB & MCC Cost Audit 2020-Curren'!$A:$A,'TB All Check'!$A43,'TB & MCC Cost Audit 2020-Curren'!$C:$C,'TB All Check'!$B$7,'TB & MCC Cost Audit 2020-Curren'!$D:$D,'TB All Check'!$A$7) -> 0 | D43: =SUMIFS('2022 Partial Rev - NS'!$N:$N,'2022 Partial Rev - NS'!$G:$G,'TB All Check'!$B43,'2022 Partial Rev - NS'!$P:$P,'TB All Check'!$B$7) -> 0 | E43: =C43-D43 -> 0 | G43: Greeley | H43: Greeley, City of | I43: =SUMIFS('TB & MCC Cost Audit 2020-Curren'!$P:$P,'TB & MCC Cost Audit 2020-Curren'!$A:$A,'TB All Check'!$A43,'TB & MCC Cost Audit 2020-Curren'!$C:$C,'TB All Check'!$H$7,'TB & MCC Cost Audit 2020-Curren'!$D:$D,'TB All Check'!$G$7) -> 317501 | J43: =SUMIFS('2023 Rev - NS'!$N:$N,'2023 Rev - NS'!$G:$G,'TB All Check'!$H43,'2023 Rev - NS'!$P:$P,'TB All Check'!$H$7) -> 317501 | K43: =I43-J43 -> 0 | M43: Greeley | N43: Greeley, City of | O43: =SUMIFS('TB & MCC Cost Audit 2020-Curren'!$P:$P,'TB & MCC Cost Audit 2020-Curren'!$A:$A,'TB All Check'!$M43,'TB & MCC Cost Audit 2020-Curren'!$C:$C,'TB All Check'!$N$7,'TB & MCC Cost Audit 2020-Curren'!$D:$D,'TB All Check'!$M$7) -> 12876 | P43: =SUMIFS('2024 Rev - NS'!$N:$N,'2024 Rev - NS'!$G:$G,'TB All Check'!$N43,'2024 Rev - NS'!$P:$P,'TB All Check'!$N$7) -> 12876 | Q43: =P43-O43 -> 0
A44: Greensboro | B44: Greensboro, City of | C44: =SUMIFS('TB & MCC Cost Audit 2020-Curren'!$P:$P,'TB & MCC Cost Audit 2020-Curren'!$A:$A,'TB All Check'!$A44,'TB & MCC Cost Audit 2020-Curren'!$C:$C,'TB All Check'!$B$7,'TB & MCC Cost Audit 2020-Curren'!$D:$D,'TB All Check'!$A$7) -> 0 | D44: =SUMIFS('2022 Partial Rev - NS'!$N:$N,'2022 Partial Rev - NS'!$G:$G,'TB All Check'!$B44,'2022 Partial Rev - NS'!$P:$P,'TB All Check'!$B$7) -> 0 | E44: =C44-D44 -> 0 | G44: Greensboro | H44: Greensboro, City of | I44: =SUMIFS('TB & MCC Cost Audit 2020-Curren'!$P:$P,'TB & MCC Cost Audit 2020-Curren'!$A:$A,'TB All Check'!$A44,'TB & MCC Cost Audit 2020-Curren'!$C:$C,'TB All Check'!$H$7,'TB & MCC Cost Audit 2020-Curren'!$D:$D,'TB All Check'!$G$7) -> 0 | J44: =SUMIFS('2023 Rev - NS'!$N:$N,'2023 Rev - NS'!$G:$G,'TB All Check'!$H44,'2023 Rev - NS'!$P:$P,'TB All Check'!$H$7) -> 0 | K44: =I44-J44 -> 0 | M44: Greensboro | N44: Greensboro, City of | O44: =SUMIFS('TB & MCC Cost Audit 2020-Curren'!$P:$P,'TB & MCC Cost Audit 2020-Curren'!$A:$A,'TB All Check'!$M44,'TB & MCC Cost Audit 2020-Curren'!$C:$C,'TB All Check'!$N$7,'TB & MCC Cost Audit 2020-Curren'!$D:$D,'TB All Check'!$M$7) -> 15756 | P44: =SUMIFS('2024 Rev - NS'!$N:$N,'2024 Rev - NS'!$G:$G,'TB All Check'!$N44,'2024 Rev - NS'!$P:$P,'TB All Check'!$N$7) -> 15756 | Q44: =P44-O44 -> 0
A45: Highland Village | B45: Highland Village, City of | C45: =SUMIFS('TB & MCC Cost Audit 2020-Curren'!$P:$P,'TB & MCC Cost Audit 2020-Curren'!$A:$A,'TB All Check'!$A45,'TB & MCC Cost Audit 2020-Curren'!$C:$C,'TB All Check'!$B$7,'TB & MCC Cost Audit 2020-Curren'!$D:$D,'TB All Check'!$A$7) -> 0 | D45: =SUMIFS('2022 Partial Rev - NS'!$N:$N,'2022 Partial Rev - NS'!$G:$G,'TB All Check'!$B45,'2022 Partial Rev - NS'!$P:$P,'TB All Check'!$B$7) -> 0 | E45: =C45-D45 -> 0 | G45: Highland Village | H45: Highland Village, City of | I45: =SUMIFS('TB & MCC Cost Audit 2020-Curren'!$P:$P,'TB & MCC Cost Audit 2020-Curren'!$A:$A,'TB All Check'!$A45,'TB & MCC Cost Audit 2020-Curren'!$C:$C,'TB All Check'!$H$7,'TB & MCC Cost Audit 2020-Curren'!$D:$D,'TB All Check'!$G$7) -> 0 | J45: =SUMIFS('2023 Rev - NS'!$N:$N,'2023 Rev - NS'!$G:$G,'TB All Check'!$H45,'2023 Rev - NS'!$P:$P,'TB All Check'!$H$7) -> 0 | K45: =I45-J45 -> 0 | M45: Highland Village | N45: Highland Village, City of | O45: =SUMIFS('TB & MCC Cost Audit 2020-Curren'!$P:$P,'TB & MCC Cost Audit 2020-Curren'!$A:$A,'TB All Check'!$M45,'TB & MCC Cost Audit 2020-Curren'!$C:$C,'TB All Check'!$N$7,'TB & MCC Cost Audit 2020-Curren'!$D:$D,'TB All Check'!$M$7) -> 8865 | P45: =SUMIFS('2024 Rev - NS'!$N:$N,'2024 Rev - NS'!$G:$G,'TB All Check'!$N45,'2024 Rev - NS'!$P:$P,'TB All Check'!$N$7) -> 8865 | Q45: =P45-O45 -> 0
A46: Houston | B46: Houston, City of | C46: =SUMIFS('TB & MCC Cost Audit 2020-Curren'!$P:$P,'TB & MCC Cost Audit 2020-Curren'!$A:$A,'TB All Check'!$A46,'TB & MCC Cost Audit 2020-Curren'!$C:$C,'TB All Check'!$B$7,'TB & MCC Cost Audit 2020-Curren'!$D:$D,'TB All Check'!$A$7) -> 9572 | D46: =SUMIFS('2022 Partial Rev - NS'!$N:$N,'2022 Partial Rev - NS'!$G:$G,'TB All Check'!$B46,'2022 Partial Rev - NS'!$P:$P,'TB All Check'!$B$7) -> 9572 | E46: =C46-D46 -> 0 | G46: Houston | H46: Houston, City of | I46: =SUMIFS('TB & MCC Cost Audit 2020-Curren'!$P:$P,'TB & MCC Cost Audit 2020-Curren'!$A:$A,'TB All Check'!$A46,'TB & MCC Cost Audit 2020-Curren'!$C:$C,'TB All Check'!$H$7,'TB & MCC Cost Audit 2020-Curren'!$D:$D,'TB All Check'!$G$7) -> 0 | J46: =SUMIFS('2023 Rev - NS'!$N:$N,'2023 Rev - NS'!$G:$G,'TB All Check'!$H46,'2023 Rev - NS'!$P:$P,'TB All Check'!$H$7) -> 0 | K46: =I46-J46 -> 0 | M46: Houston | N46: Houston, City of | O46: =SUMIFS('TB & MCC Cost Audit 2020-Curren'!$P:$P,'TB & MCC Cost Audit 2020-Curren'!$A:$A,'TB All Check'!$M46,'TB & MCC Cost Audit 2020-Curren'!$C:$C,'TB All Check'!$N$7,'TB & MCC Cost Audit 2020-Curren'!$D:$D,'TB All Check'!$M$7) -> 11062 | P46: =SUMIFS('2024 Rev - NS'!$N:$N,'2024 Rev - NS'!$G:$G,'TB All Check'!$N46,'2024 Rev - NS'!$P:$P,'TB All Check'!$N$7) -> 11062 | Q46: =P46-O46 -> 0
A47: Jal | B47: #N/A | C47: =SUMIFS('TB & MCC Cost Audit 2020-Curren'!$P:$P,'TB & MCC Cost Audit 2020-Curren'!$A:$A,'TB All Check'!$A47,'TB & MCC Cost Audit 2020-Curren'!$C:$C,'TB All Check'!$B$7,'TB & MCC Cost Audit 2020-Curren'!$D:$D,'TB All Check'!$A$7) -> 0 | D47: =SUMIFS('2022 Partial Rev - NS'!$N:$N,'2022 Partial Rev - NS'!$G:$G,'TB All Check'!$B47,'2022 Partial Rev - NS'!$P:$P,'TB All Check'!$B$7) -> 0 | E47: =C47-D47 -> 0 | G47: Jal | H47: #N/A | I47: =SUMIFS('TB & MCC Cost Audit 2020-Curren'!$P:$P,'TB & MCC Cost Audit 2020-Curren'!$A:$A,'TB All Check'!$A47,'TB & MCC Cost Audit 2020-Curren'!$C:$C,'TB All Check'!$H$7,'TB & MCC Cost Audit 2020-Curren'!$D:$D,'TB All Check'!$G$7) -> 0 | J47: =SUMIFS('2023 Rev - NS'!$N:$N,'2023 Rev - NS'!$G:$G,'TB All Check'!$H47,'2023 Rev - NS'!$P:$P,'TB All Check'!$H$7) -> 0 | K47: =I47-J47 -> 0 | M47: Jal | N47: #N/A | O47: =SUMIFS('TB & MCC Cost Audit 2020-Curren'!$P:$P,'TB & MCC Cost Audit 2020-Curren'!$A:$A,'TB All Check'!$M47,'TB & MCC Cost Audit 2020-Curren'!$C:$C,'TB All Check'!$N$7,'TB & MCC Cost Audit 2020-Curren'!$D:$D,'TB All Check'!$M$7) -> 0 | P47: =SUMIFS('2024 Rev - NS'!$N:$N,'2024 Rev - NS'!$G:$G,'TB All Check'!$N47,'2024 Rev - NS'!$P:$P,'TB All Check'!$N$7) -> 0 | Q47: =P47-O47 -> 0
A48: Kansas City | B48: Kansas City Missouri Dept | C48: =SUMIFS('TB & MCC Cost Audit 2020-Curren'!$P:$P,'TB & MCC Cost Audit 2020-Curren'!$A:$A,'TB All Check'!$A48,'TB & MCC Cost Audit 2020-Curren'!$C:$C,'TB All Check'!$B$7,'TB & MCC Cost Audit 2020-Curren'!$D:$D,'TB All Check'!$A$7) -> 15087 | D48: =SUMIFS('2022 Partial Rev - NS'!$N:$N,'2022 Partial Rev - NS'!$G:$G,'TB All Check'!$B48,'2022 Partial Rev - NS'!$P:$P,'TB All Check'!$B$7) -> 15087 | E48: =C48-D48 -> 0 | G48: Kansas City | H48: Kansas City Missouri Dept | I48: =SUMIFS('TB & MCC Cost Audit 2020-Curren'!$P:$P,'TB & MCC Cost Audit 2020-Curren'!$A:$A,'TB All Check'!$A48,'TB & MCC Cost Audit 2020-Curren'!$C:$C,'TB All Check'!$H$7,'TB & MCC Cost Audit 2020-Curren'!$D:$D,'TB All Check'!$G$7) -> 0 | J48: =SUMIFS('2023 Rev - NS'!$N:$N,'2023 Rev - NS'!$G:$G,'TB All Check'!$H48,'2023 Rev - NS'!$P:$P,'TB All Check'!$H$7) -> 0 | K48: =I48-J48 -> 0 | M48: Kansas City | N48: Kansas City Missouri Dept | O48: =SUMIFS('TB & MCC Cost Audit 2020-Curren'!$P:$P,'TB & MCC Cost Audit 2020-Curren'!$A:$A,'TB All Check'!$M48,'TB & MCC Cost Audit 2020-Curren'!$C:$C,'TB All Check'!$N$7,'TB & MCC Cost Audit 2020-Curren'!$D:$D,'TB All Check'!$M$7) -> 27819 | P48: =SUMIFS('2024 Rev - NS'!$N:$N,'2024 Rev - NS'!$G:$G,'TB All Check'!$N48,'2024 Rev - NS'!$P:$P,'TB All Check'!$N$7) -> 27819 | Q48: =P48-O48 -> 0
A49: LADWP | B49: Los Angeles Department of Water and Power (LADWP) | C49: =SUMIFS('TB & MCC Cost Audit 2020-Curren'!$P:$P,'TB & MCC Cost Audit 2020-Curren'!$A:$A,'TB All Check'!$A49,'TB & MCC Cost Audit 2020-Curren'!$C:$C,'TB All Check'!$B$7,'TB & MCC Cost Audit 2020-Curren'!$D:$D,'TB All Check'!$A$7) -> 0 | D49: =SUMIFS('2022 Partial Rev - NS'!$N:$N,'2022 Partial Rev - NS'!$G:$G,'TB All Check'!$B49,'2022 Partial Rev - NS'!$P:$P,'TB All Check'!$B$7) -> 0 | E49: =C49-D49 -> 0 | G49: LADWP | H49: Los Angeles Department of Water and Power (LADWP) | I49: =SUMIFS('TB & MCC Cost Audit 2020-Curren'!$P:$P,'TB & MCC Cost Audit 2020-Curren'!$A:$A,'TB All Check'!$A49,'TB & MCC Cost Audit 2020-Curren'!$C:$C,'TB All Check'!$H$7,'TB & MCC Cost Audit 2020-Curren'!$D:$D,'TB All Check'!$G$7) -> 0 | J49: =SUMIFS('2023 Rev - NS'!$N:$N,'2023 Rev - NS'!$G:$G,'TB All Check'!$H49,'2023 Rev - NS'!$P:$P,'TB All Check'!$H$7) -> 0 | K49: =I49-J49 -> 0 | M49: LADWP | N49: Los Angeles Department of Water and Power (LADWP) | O49: =SUMIFS('TB & MCC Cost Audit 2020-Curren'!$P:$P,'TB & MCC Cost Audit 2020-Curren'!$A:$A,'TB All Check'!$M49,'TB & MCC Cost Audit 2020-Curren'!$C:$C,'TB All Check'!$N$7,'TB & MCC Cost Audit 2020-Curren'!$D:$D,'TB All Check'!$M$7) -> 0 | P49: =SUMIFS('2024 Rev - NS'!$N:$N,'2024 Rev - NS'!$G:$G,'TB All Check'!$N49,'2024 Rev - NS'!$P:$P,'TB All Check'!$N$7) -> 0 | Q49: =P49-O49 -> 0
A50: LADWP Central | B50: Los Angeles Department of Water and Power (LADWP) | C50: =SUMIFS('TB & MCC Cost Audit 2020-Curren'!$P:$P,'TB & MCC Cost Audit 2020-Curren'!$A:$A,'TB All Check'!$A50,'TB & MCC Cost Audit 2020-Curren'!$C:$C,'TB All Check'!$B$7,'TB & MCC Cost Audit 2020-Curren'!$D:$D,'TB All Check'!$A$7) -> 0 | D50: =SUMIFS('2022 Partial Rev - NS'!$N:$N,'2022 Partial Rev - NS'!$G:$G,'TB All Check'!$B50,'2022 Partial Rev - NS'!$P:$P,'TB All Check'!$B$7) -> 0 | E50: =C50-D50 -> 0 | G50: LADWP Central | H50: LADWP Central | I50: =SUMIFS('TB & MCC Cost Audit 2020-Curren'!$P:$P,'TB & MCC Cost Audit 2020-Curren'!$A:$A,'TB All Check'!$A50,'TB & MCC Cost Audit 2020-Curren'!$C:$C,'TB All Check'!$H$7,'TB & MCC Cost Audit 2020-Curren'!$D:$D,'TB All Check'!$G$7) -> 0 | J50: =SUMIFS('2023 Rev - NS'!$N:$N,'2023 Rev - NS'!$G:$G,'TB All Check'!$H50,'2023 Rev - NS'!$P:$P,'TB All Check'!$H$7) -> 0 | K50: =I50-J50 -> 0 | M50: LADWP Central | N50: LADWP Central | O50: =SUMIFS('TB & MCC Cost Audit 2020-Curren'!$P:$P,'TB & MCC Cost Audit 2020-Curren'!$A:$A,'TB All Check'!$M50,'TB & MCC Cost Audit 2020-Curren'!$C:$C,'TB All Check'!$N$7,'TB & MCC Cost Audit 2020-Curren'!$D:$D,'TB All Check'!$M$7) -> 55240.53 | P50: =SUMIFS('2024 Rev - NS'!$N:$N,'2024 Rev - NS'!$G:$G,'TB All Check'!$N50,'2024 Rev - NS'!$P:$P,'TB All Check'!$N$7) -> 55240.53 | Q50: =P50-O50 -> 0
A51: LADWP West | B51: Los Angeles Department of Water and Power (LADWP) | C51: =SUMIFS('TB & MCC Cost Audit 2020-Curren'!$P:$P,'TB & MCC Cost Audit 2020-Curren'!$A:$A,'TB All Check'!$A51,'TB & MCC Cost Audit 2020-Curren'!$C:$C,'TB All Check'!$B$7,'TB & MCC Cost Audit 2020-Curren'!$D:$D,'TB All Check'!$A$7) -> 0 | D51: =SUMIFS('2022 Partial Rev - NS'!$N:$N,'2022 Partial Rev - NS'!$G:$G,'TB All Check'!$B51,'2022 Partial Rev - NS'!$P:$P,'TB All Check'!$B$7) -> 0 | E51: =C51-D51 -> 0 | G51: LADWP West | H51: LADWP West | I51: =SUMIFS('TB & MCC Cost Audit 2020-Curren'!$P:$P,'TB & MCC Cost Audit 2020-Curren'!$A:$A,'TB All Check'!$A51,'TB & MCC Cost Audit 2020-Curren'!$C:$C,'TB All Check'!$H$7,'TB & MCC Cost Audit 2020-Curren'!$D:$D,'TB All Check'!$G$7) -> 0 | J51: =SUMIFS('2023 Rev - NS'!$N:$N,'2023 Rev - NS'!$G:$G,'TB All Check'!$H51,'2023 Rev - NS'!$P:$P,'TB All Check'!$H$7) -> 0 | K51: =I51-J51 -> 0 | M51: LADWP West | N51: LADWP West | O51: =SUMIFS('TB & MCC Cost Audit 2020-Curren'!$P:$P,'TB & MCC Cost Audit 2020-Curren'!$A:$A,'TB All Check'!$M51,'TB & MCC Cost Audit 2020-Curren'!$C:$C,'TB All Check'!$N$7,'TB & MCC Cost Audit 2020-Curren'!$D:$D,'TB All Check'!$M$7) -> 42343.98 | P51: =SUMIFS('2024 Rev - NS'!$N:$N,'2024 Rev - NS'!$G:$G,'TB All Check'!$N51,'2024 Rev - NS'!$P:$P,'TB All Check'!$N$7) -> 42343.98 | Q51: =P51-O51 -> 0
A52: Las Vegas | B52: Las Vegas Valley Water District | C52: =SUMIFS('TB & MCC Cost Audit 2020-Curren'!$P:$P,'TB & MCC Cost Audit 2020-Curren'!$A:$A,'TB All Check'!$A52,'TB & MCC Cost Audit 2020-Curren'!$C:$C,'TB All Check'!$B$7,'TB & MCC Cost Audit 2020-Curren'!$D:$D,'TB All Check'!$A$7) -> 0 | D52: =SUMIFS('2022 Partial Rev - NS'!$N:$N,'2022 Partial Rev - NS'!$G:$G,'TB All Check'!$B52,'2022 Partial Rev - NS'!$P:$P,'TB All Check'!$B$7) -> 0 | E52: =C52-D52 -> 0 | G52: Las Vegas | H52: Las Vegas Valley Water District | I52: =SUMIFS('TB & MCC Cost Audit 2020-Curren'!$P:$P,'TB & MCC Cost Audit 2020-Curren'!$A:$A,'TB All Check'!$A52,'TB & MCC Cost Audit 2020-Curren'!$C:$C,'TB All Check'!$H$7,'TB & MCC Cost Audit 2020-Curren'!$D:$D,'TB All Check'!$G$7) -> 0 | J52: =SUMIFS('2023 Rev - NS'!$N:$N,'2023 Rev - NS'!$G:$G,'TB All Check'!$H52,'2023 Rev - NS'!$P:$P,'TB All Check'!$H$7) -> 0 | K52: =I52-J52 -> 0 | M52: Las Vegas | N52: Las Vegas Valley Water District | O52: =SUMIFS('TB & MCC Cost Audit 2020-Curren'!$P:$P,'TB & MCC Cost Audit 2020-Curren'!$A:$A,'TB All Check'!$M52,'TB & MCC Cost Audit 2020-Curren'!$C:$C,'TB All Check'!$N$7,'TB & MCC Cost Audit 2020-Curren'!$D:$D,'TB All Check'!$M$7) -> 0 | P52: =SUMIFS('2024 Rev - NS'!$N:$N,'2024 Rev - NS'!$G:$G,'TB All Check'!$N52,'2024 Rev - NS'!$P:$P,'TB All Check'!$N$7) -> 0 | Q52: =P52-O52 -> 0
A53: Leesburg | B53: Leesburg, Town of | C53: =SUMIFS('TB & MCC Cost Audit 2020-Curren'!$P:$P,'TB & MCC Cost Audit 2020-Curren'!$A:$A,'TB All Check'!$A53,'TB & MCC Cost Audit 2020-Curren'!$C:$C,'TB All Check'!$B$7,'TB & MCC Cost Audit 2020-Curren'!$D:$D,'TB All Check'!$A$7) -> 7870 | D53: =SUMIFS('2022 Partial Rev - NS'!$N:$N,'2022 Partial Rev - NS'!$G:$G,'TB All Check'!$B53,'2022 Partial Rev - NS'!$P:$P,'TB All Check'!$B$7) -> 7870 | E53: =C53-D53 -> 0 | G53: Leesburg | H53: Leesburg, Town of | I53: =SUMIFS('TB & MCC Cost Audit 2020-Curren'!$P:$P,'TB & MCC Cost Audit 2020-Curren'!$A:$A,'TB All Check'!$A53,'TB & MCC Cost Audit 2020-Curren'!$C:$C,'TB All Check'!$H$7,'TB & MCC Cost Audit 2020-Curren'!$D:$D,'TB All Check'!$G$7) -> 0 | J53: =SUMIFS('2023 Rev - NS'!$N:$N,'2023 Rev - NS'!$G:$G,'TB All Check'!$H53,'2023 Rev - NS'!$P:$P,'TB All Check'!$H$7) -> 0 | K53: =I53-J53 -> 0 | M53: Leesburg | N53: Leesburg, Town of | O53: =SUMIFS('TB & MCC Cost Audit 2020-Curren'!$P:$P,'TB & MCC Cost Audit 2020-Curren'!$A:$A,'TB All Check'!$M53,'TB & MCC Cost Audit 2020-Curren'!$C:$C,'TB All Check'!$N$7,'TB & MCC Cost Audit 2020-Curren'!$D:$D,'TB All Check'!$M$7) -> 7870 | P53: =SUMIFS('2024 Rev - NS'!$N:$N,'2024 Rev - NS'!$G:$G,'TB All Check'!$N53,'2024 Rev - NS'!$P:$P,'TB All Check'!$N$7) -> 7870 | Q53: =P53-O53 -> 0
A54: Lodi | B54: Lodi, City of | C54: =SUMIFS('TB & MCC Cost Audit 2020-Curren'!$P:$P,'TB & MCC Cost Audit 2020-Curren'!$A:$A,'TB All Check'!$A54,'TB & MCC Cost Audit 2020-Curren'!$C:$C,'TB All Check'!$B$7,'TB & MCC Cost Audit 2020-Curren'!$D:$D,'TB All Check'!$A$7) -> 0 | D54: =SUMIFS('2022 Partial Rev - NS'!$N:$N,'2022 Partial Rev - NS'!$G:$G,'TB All Check'!$B54,'2022 Partial Rev - NS'!$P:$P,'TB All Check'!$B$7) -> 0 | E54: =C54-D54 -> 0 | G54: Lodi | H54: Lodi, City of | I54: =SUMIFS('TB & MCC Cost Audit 2020-Curren'!$P:$P,'TB & MCC Cost Audit 2020-Curren'!$A:$A,'TB All Check'!$A54,'TB & MCC Cost Audit 2020-Curren'!$C:$C,'TB All Check'!$H$7,'TB & MCC Cost Audit 2020-Curren'!$D:$D,'TB All Check'!$G$7) -> 138467 | J54: =SUMIFS('2023 Rev - NS'!$N:$N,'2023 Rev - NS'!$G:$G,'TB All Check'!$H54,'2023 Rev - NS'!$P:$P,'TB All Check'!$H$7) -> 138467 | K54: =I54-J54 -> 0 | M54: Lodi | N54: Lodi, City of | O54: =SUMIFS('TB & MCC Cost Audit 2020-Curren'!$P:$P,'TB & MCC Cost Audit 2020-Curren'!$A:$A,'TB All Check'!$M54,'TB & MCC Cost Audit 2020-Curren'!$C:$C,'TB All Check'!$N$7,'TB & MCC Cost Audit 2020-Curren'!$D:$D,'TB All Check'!$M$7) -> 22864 | P54: =SUMIFS('2024 Rev - NS'!$N:$N,'2024 Rev - NS'!$G:$G,'TB All Check'!$N54,'2024 Rev - NS'!$P:$P,'TB All Check'!$N$7) -> 22864 | Q54: =P54-O54 -> 0
A55: Lubbock | B55: Lubbock, City of | C55: =SUMIFS('TB & MCC Cost Audit 2020-Curren'!$P:$P,'TB & MCC Cost Audit 2020-Curren'!$A:$A,'TB All Check'!$A55,'TB & MCC Cost Audit 2020-Curren'!$C:$C,'TB All Check'!$B$7,'TB & MCC Cost Audit 2020-Curren'!$D:$D,'TB All Check'!$A$7) -> 9680 | D55: =SUMIFS('2022 Partial Rev - NS'!$N:$N,'2022 Partial Rev - NS'!$G:$G,'TB All Check'!$B55,'2022 Partial Rev - NS'!$P:$P,'TB All Check'!$B$7) -> 9680 | E55: =C55-D55 -> 0 | G55: Lubbock | H55: Lubbock, City of | I55: =SUMIFS('TB & MCC Cost Audit 2020-Curren'!$P:$P,'TB & MCC Cost Audit 2020-Curren'!$A:$A,'TB All Check'!$A55,'TB & MCC Cost Audit 2020-Curren'!$C:$C,'TB All Check'!$H$7,'TB & MCC Cost Audit 2020-Curren'!$D:$D,'TB All Check'!$G$7) -> 0 | J55: =SUMIFS('2023 Rev - NS'!$N:$N,'2023 Rev - NS'!$G:$G,'TB All Check'!$H55,'2023 Rev - NS'!$P:$P,'TB All Check'!$H$7) -> 0 | K55: =I55-J55 -> 0 | M55: Lubbock | N55: Lubbock, City of | O55: =SUMIFS('TB & MCC Cost Audit 2020-Curren'!$P:$P,'TB & MCC Cost Audit 2020-Curren'!$A:$A,'TB All Check'!$M55,'TB & MCC Cost Audit 2020-Curren'!$C:$C,'TB All Check'!$N$7,'TB & MCC Cost Audit 2020-Curren'!$D:$D,'TB All Check'!$M$7) -> 9680 | P55: =SUMIFS('2024 Rev - NS'!$N:$N,'2024 Rev - NS'!$G:$G,'TB All Check'!$N55,'2024 Rev - NS'!$P:$P,'TB All Check'!$N$7) -> 9680 | Q55: =P55-O55 -> 0
A56: Marion County | B56: Marion County Utilities | C56: =SUMIFS('TB & MCC Cost Audit 2020-Curren'!$P:$P,'TB & MCC Cost Audit 2020-Curren'!$A:$A,'TB All Check'!$A56,'TB & MCC Cost Audit 2020-Curren'!$C:$C,'TB All Check'!$B$7,'TB & MCC Cost Audit 2020-Curren'!$D:$D,'TB All Check'!$A$7) -> 7670 | D56: 7670 | E56: =C56-D56 -> 0 | G56: Marion County | H56: Marion County Utilities | I56: =SUMIFS('TB & MCC Cost Audit 2020-Curren'!$P:$P,'TB & MCC Cost Audit 2020-Curren'!$A:$A,'TB All Check'!$A56,'TB & MCC Cost Audit 2020-Curren'!$C:$C,'TB All Check'!$H$7,'TB & MCC Cost Audit 2020-Curren'!$D:$D,'TB All Check'!$G$7) -> 0 | J56: =SUMIFS('2023 Rev - NS'!$N:$N,'2023 Rev - NS'!$G:$G,'TB All Check'!$H56,'2023 Rev - NS'!$P:$P,'TB All Check'!$H$7) -> 0 | K56: =I56-J56 -> 0 | M56: Marion County | N56: Marion County Utilities | O56: =SUMIFS('TB & MCC Cost Audit 2020-Curren'!$P:$P,'TB & MCC Cost Audit 2020-Curren'!$A:$A,'TB All Check'!$M56,'TB & MCC Cost Audit 2020-Curren'!$C:$C,'TB All Check'!$N$7,'TB & MCC Cost Audit 2020-Curren'!$D:$D,'TB All Check'!$M$7) -> 8865 | P56: =SUMIFS('2024 Rev - NS'!$N:$N,'2024 Rev - NS'!$G:$G,'TB All Check'!$N56,'2024 Rev - NS'!$P:$P,'TB All Check'!$N$7) -> 8865 | Q56: =P56-O56 -> 0
A57: McKinney | B57: McKinney, City of | C57: =SUMIFS('TB & MCC Cost Audit 2020-Curren'!$P:$P,'TB & MCC Cost Audit 2020-Curren'!$A:$A,'TB All Check'!$A57,'TB & MCC Cost Audit 2020-Curren'!$C:$C,'TB All Check'!$B$7,'TB & MCC Cost Audit 2020-Curren'!$D:$D,'TB All Check'!$A$7) -> 0 | D57: =SUMIFS('2022 Partial Rev - NS'!$N:$N,'2022 Partial Rev - NS'!$G:$G,'TB All Check'!$B57,'2022 Partial Rev - NS'!$P:$P,'TB All Check'!$B$7) -> 0 | E57: =C57-D57 -> 0 | G57: McKinney | H57: McKinney, City of | I57: =SUMIFS('TB & MCC Cost Audit 2020-Curren'!$P:$P,'TB & MCC Cost Audit 2020-Curren'!$A:$A,'TB All Check'!$A57,'TB & MCC Cost Audit 2020-Curren'!$C:$C,'TB All Check'!$H$7,'TB & MCC Cost Audit 2020-Curren'!$D:$D,'TB All Check'!$G$7) -> 0 | J57: =SUMIFS('2023 Rev - NS'!$N:$N,'2023 Rev - NS'!$G:$G,'TB All Check'!$H57,'2023 Rev - NS'!$P:$P,'TB All Check'!$H$7) -> 0 | K57: =I57-J57 -> 0 | M57: McKinney | N57: McKinney, City of | O57: =SUMIFS('TB & MCC Cost Audit 2020-Curren'!$P:$P,'TB & MCC Cost Audit 2020-Curren'!$A:$A,'TB All Check'!$M57,'TB & MCC Cost Audit 2020-Curren'!$C:$C,'TB All Check'!$N$7,'TB & MCC Cost Audit 2020-Curren'!$D:$D,'TB All Check'!$M$7) -> 8865 | P57: =SUMIFS('2024 Rev - NS'!$N:$N,'2024 Rev - NS'!$G:$G,'TB All Check'!$N57,'2024 Rev - NS'!$P:$P,'TB All Check'!$N$7) -> 8865 | Q57: =P57-O57 -> 0
A58: MDC | B58: Metropolitan District, The | C58: =SUMIFS('TB & MCC Cost Audit 2020-Curren'!$P:$P,'TB & MCC Cost Audit 2020-Curren'!$A:$A,'TB All Check'!$A58,'TB & MCC Cost Audit 2020-Curren'!$C:$C,'TB All Check'!$B$7,'TB & MCC Cost Audit 2020-Curren'!$D:$D,'TB All Check'!$A$7) -> 0 | D58: =SUMIFS('2022 Partial Rev - NS'!$N:$N,'2022 Partial Rev - NS'!$G:$G,'TB All Check'!$B58,'2022 Partial Rev - NS'!$P:$P,'TB All Check'!$B$7) -> 0 | E58: =C58-D58 -> 0 | G58: MDC | H58: Metropolitan District, The | I58: =SUMIFS('TB & MCC Cost Audit 2020-Curren'!$P:$P,'TB & MCC Cost Audit 2020-Curren'!$A:$A,'TB All Check'!$A58,'TB & MCC Cost Audit 2020-Curren'!$C:$C,'TB All Check'!$H$7,'TB & MCC Cost Audit 2020-Curren'!$D:$D,'TB All Check'!$G$7) -> 195096 | J58: =SUMIFS('2023 Rev - NS'!$N:$N,'2023 Rev - NS'!$G:$G,'TB All Check'!$H58,'2023 Rev - NS'!$P:$P,'TB All Check'!$H$7) -> 195096 | K58: =I58-J58 -> 0 | M58: MDC | N58: Metropolitan District, The | O58: =SUMIFS('TB & MCC Cost Audit 2020-Curren'!$P:$P,'TB & MCC Cost Audit 2020-Curren'!$A:$A,'TB All Check'!$M58,'TB & MCC Cost Audit 2020-Curren'!$C:$C,'TB All Check'!$N$7,'TB & MCC Cost Audit 2020-Curren'!$D:$D,'TB All Check'!$M$7) -> 12190 | P58: =SUMIFS('2024 Rev - NS'!$N:$N,'2024 Rev - NS'!$G:$G,'TB All Check'!$N58,'2024 Rev - NS'!$P:$P,'TB All Check'!$N$7) -> 12190 | Q58: =P58-O58 -> 0
A59: Medford | B59: Medford Water Commission | C59: =SUMIFS('TB & MCC Cost Audit 2020-Curren'!$P:$P,'TB & MCC Cost Audit 2020-Curren'!$A:$A,'TB All Check'!$A59,'TB & MCC Cost Audit 2020-Curren'!$C:$C,'TB All Check'!$B$7,'TB & MCC Cost Audit 2020-Curren'!$D:$D,'TB All Check'!$A$7) -> 0 | D59: =SUMIFS('2022 Partial Rev - NS'!$N:$N,'2022 Partial Rev - NS'!$G:$G,'TB All Check'!$B59,'2022 Partial Rev - NS'!$P:$P,'TB All Check'!$B$7) -> 0 | E59: =C59-D59 -> 0 | G59: Medford | H59: Medford Water Commission | I59: =SUMIFS('TB & MCC Cost Audit 2020-Curren'!$P:$P,'TB & MCC Cost Audit 2020-Curren'!$A:$A,'TB All Check'!$A59,'TB & MCC Cost Audit 2020-Curren'!$C:$C,'TB All Check'!$H$7,'TB & MCC Cost Audit 2020-Curren'!$D:$D,'TB All Check'!$G$7) -> 0 | J59: =SUMIFS('2023 Rev - NS'!$N:$N,'2023 Rev - NS'!$G:$G,'TB All Check'!$H59,'2023 Rev - NS'!$P:$P,'TB All Check'!$H$7) -> 0 | K59: =I59-J59 -> 0 | M59: Medford | N59: Medford Water Commission | O59: =SUMIFS('TB & MCC Cost Audit 2020-Curren'!$P:$P,'TB & MCC Cost Audit 2020-Curren'!$A:$A,'TB All Check'!$M59,'TB & MCC Cost Audit 2020-Curren'!$C:$C,'TB All Check'!$N$7,'TB & MCC Cost Audit 2020-Curren'!$D:$D,'TB All Check'!$M$7) -> 0 | P59: =SUMIFS('2024 Rev - NS'!$N:$N,'2024 Rev - NS'!$G:$G,'TB All Check'!$N59,'2024 Rev - NS'!$P:$P,'TB All Check'!$N$7) -> 0 | Q59: =P59-O59 -> 0
A60: Mesa | B60: Mesa, City of | C60: =SUMIFS('TB & MCC Cost Audit 2020-Curren'!$P:$P,'TB & MCC Cost Audit 2020-Curren'!$A:$A,'TB All Check'!$A60,'TB & MCC Cost Audit 2020-Curren'!$C:$C,'TB All Check'!$B$7,'TB & MCC Cost Audit 2020-Curren'!$D:$D,'TB All Check'!$A$7) -> 0 | D60: =SUMIFS('2022 Partial Rev - NS'!$N:$N,'2022 Partial Rev - NS'!$G:$G,'TB All Check'!$B60,'2022 Partial Rev - NS'!$P:$P,'TB All Check'!$B$7) -> 0 | E60: =C60-D60 -> 0 | G60: Mesa | H60: Mesa, City of | I60: =SUMIFS('TB & MCC Cost Audit 2020-Curren'!$P:$P,'TB & MCC Cost Audit 2020-Curren'!$A:$A,'TB All Check'!$A60,'TB & MCC Cost Audit 2020-Curren'!$C:$C,'TB All Check'!$H$7,'TB & MCC Cost Audit 2020-Curren'!$D:$D,'TB All Check'!$G$7) -> 0 | J60: =SUMIFS('2023 Rev - NS'!$N:$N,'2023 Rev - NS'!$G:$G,'TB All Check'!$H60,'2023 Rev - NS'!$P:$P,'TB All Check'!$H$7) -> 0 | K60: =I60-J60 -> 0 | M60: Mesa | N60: Mesa, City of | O60: =SUMIFS('TB & MCC Cost Audit 2020-Curren'!$P:$P,'TB & MCC Cost Audit 2020-Curren'!$A:$A,'TB All Check'!$M60,'TB & MCC Cost Audit 2020-Curren'!$C:$C,'TB All Check'!$N$7,'TB & MCC Cost Audit 2020-Curren'!$D:$D,'TB All Check'!$M$7) -> 0 | P60: =SUMIFS('2024 Rev - NS'!$N:$N,'2024 Rev - NS'!$G:$G,'TB All Check'!$N60,'2024 Rev - NS'!$P:$P,'TB All Check'!$N$7) -> 0 | Q60: =P60-O60 -> 0
A61: Metertek | B61: Metertek Utility Services Inc | C61: =SUMIFS('TB & MCC Cost Audit 2020-Curren'!$P:$P,'TB & MCC Cost Audit 2020-Curren'!$A:$A,'TB All Check'!$A61,'TB & MCC Cost Audit 2020-Curren'!$C:$C,'TB All Check'!$B$7,'TB & MCC Cost Audit 2020-Curren'!$D:$D,'TB All Check'!$A$7) -> 0 | D61: =SUMIFS('2022 Partial Rev - NS'!$N:$N,'2022 Partial Rev - NS'!$G:$G,'TB All Check'!$B61,'2022 Partial Rev - NS'!$P:$P,'TB All Check'!$B$7) -> 0 | E61: =C61-D61 -> 0 | G61: Metertek | H61: Metertek Utility Services Inc | I61: =SUMIFS('TB & MCC Cost Audit 2020-Curren'!$P:$P,'TB & MCC Cost Audit 2020-Curren'!$A:$A,'TB All Check'!$A61,'TB & MCC Cost Audit 2020-Curren'!$C:$C,'TB All Check'!$H$7,'TB & MCC Cost Audit 2020-Curren'!$D:$D,'TB All Check'!$G$7) -> 0 | J61: =SUMIFS('2023 Rev - NS'!$N:$N,'2023 Rev - NS'!$G:$G,'TB All Check'!$H61,'2023 Rev - NS'!$P:$P,'TB All Check'!$H$7) -> 0 | K61: =I61-J61 -> 0 | M61: Metertek | N61: Metertek Utility Services Inc | O61: =SUMIFS('TB & MCC Cost Audit 2020-Curren'!$P:$P,'TB & MCC Cost Audit 2020-Curren'!$A:$A,'TB All Check'!$M61,'TB & MCC Cost Audit 2020-Curren'!$C:$C,'TB All Check'!$N$7,'TB & MCC Cost Audit 2020-Curren'!$D:$D,'TB All Check'!$M$7) -> 0 | P61: =SUMIFS('2024 Rev - NS'!$N:$N,'2024 Rev - NS'!$G:$G,'TB All Check'!$N61,'2024 Rev - NS'!$P:$P,'TB All Check'!$N$7) -> 0 | Q61: =P61-O61 -> 0
A62: Miami | B62: Miami Dade Water & Sewer | C62: =SUMIFS('TB & MCC Cost Audit 2020-Curren'!$P:$P,'TB & MCC Cost Audit 2020-Curren'!$A:$A,'TB All Check'!$A62,'TB & MCC Cost Audit 2020-Curren'!$C:$C,'TB All Check'!$B$7,'TB & MCC Cost Audit 2020-Curren'!$D:$D,'TB All Check'!$A$7) -> 20512 | D62: 20512 | E62: =C62-D62 -> 0 | G62: Miami | H62: Miami Dade Water & Sewer | I62: =SUMIFS('TB & MCC Cost Audit 2020-Curren'!$P:$P,'TB & MCC Cost Audit 2020-Curren'!$A:$A,'TB All Check'!$A62,'TB & MCC Cost Audit 2020-Curren'!$C:$C,'TB All Check'!$H$7,'TB & MCC Cost Audit 2020-Curren'!$D:$D,'TB All Check'!$G$7) -> 0 | J62: =SUMIFS('2023 Rev - NS'!$N:$N,'2023 Rev - NS'!$G:$G,'TB All Check'!$H62,'2023 Rev - NS'!$P:$P,'TB All Check'!$H$7) -> 0 | K62: =I62-J62 -> 0 | M62: Miami | N62: Miami Dade Water & Sewer | O62: =SUMIFS('TB & MCC Cost Audit 2020-Curren'!$P:$P,'TB & MCC Cost Audit 2020-Curren'!$A:$A,'TB All Check'!$M62,'TB & MCC Cost Audit 2020-Curren'!$C:$C,'TB All Check'!$N$7,'TB & MCC Cost Audit 2020-Curren'!$D:$D,'TB All Check'!$M$7) -> 0 | P62: =SUMIFS('2024 Rev - NS'!$N:$N,'2024 Rev - NS'!$G:$G,'TB All Check'!$N62,'2024 Rev - NS'!$P:$P,'TB All Check'!$N$7) -> 27783 | Q62: =P62-O62 -> 27783
A63: Middlesex | B63: Middlesex Water Company | C63: =SUMIFS('TB & MCC Cost Audit 2020-Curren'!$P:$P,'TB & MCC Cost Audit 2020-Curren'!$A:$A,'TB All Check'!$A63,'TB & MCC Cost Audit 2020-Curren'!$C:$C,'TB All Check'!$B$7,'TB & MCC Cost Audit 2020-Curren'!$D:$D,'TB All Check'!$A$7) -> 0 | D63: =SUMIFS('2022 Partial Rev - NS'!$N:$N,'2022 Partial Rev - NS'!$G:$G,'TB All Check'!$B63,'2022 Partial Rev - NS'!$P:$P,'TB All Check'!$B$7) -> 0 | E63: =C63-D63 -> 0 | G63: Middlesex | H63: Middlesex Water Company | I63: =SUMIFS('TB & MCC Cost Audit 2020-Curren'!$P:$P,'TB & MCC Cost Audit 2020-Curren'!$A:$A,'TB All Check'!$A63,'TB & MCC Cost Audit 2020-Curren'!$C:$C,'TB All Check'!$H$7,'TB & MCC Cost Audit 2020-Curren'!$D:$D,'TB All Check'!$G$7) -> 0 | J63: =SUMIFS('2023 Rev - NS'!$N:$N,'2023 Rev - NS'!$G:$G,'TB All Check'!$H63,'2023 Rev - NS'!$P:$P,'TB All Check'!$H$7) -> 0 | K63: =I63-J63 -> 0 | M63: Middlesex | N63: Middlesex Water Company | O63: =SUMIFS('TB & MCC Cost Audit 2020-Curren'!$P:$P,'TB & MCC Cost Audit 2020-Curren'!$A:$A,'TB All Check'!$M63,'TB & MCC Cost Audit 2020-Curren'!$C:$C,'TB All Check'!$N$7,'TB & MCC Cost Audit 2020-Curren'!$D:$D,'TB All Check'!$M$7) -> 14896 | P63: =SUMIFS('2024 Rev - NS'!$N:$N,'2024 Rev - NS'!$G:$G,'TB All Check'!$N63,'2024 Rev - NS'!$P:$P,'TB All Check'!$N$7) -> 14896 | Q63: =P63-O63 -> 0
A64: Midland | B64: Midland, City of | C64: =SUMIFS('TB & MCC Cost Audit 2020-Curren'!$P:$P,'TB & MCC Cost Audit 2020-Curren'!$A:$A,'TB All Check'!$A64,'TB & MCC Cost Audit 2020-Curren'!$C:$C,'TB All Check'!$B$7,'TB & MCC Cost Audit 2020-Curren'!$D:$D,'TB All Check'!$A$7) -> 0 | D64: =SUMIFS('2022 Partial Rev - NS'!$N:$N,'2022 Partial Rev - NS'!$G:$G,'TB All Check'!$B64,'2022 Partial Rev - NS'!$P:$P,'TB All Check'!$B$7) -> 0 | E64: =C64-D64 -> 0 | G64: Midland | H64: Midland, City of | I64: =SUMIFS('TB & MCC Cost Audit 2020-Curren'!$P:$P,'TB & MCC Cost Audit 2020-Curren'!$A:$A,'TB All Check'!$A64,'TB & MCC Cost Audit 2020-Curren'!$C:$C,'TB All Check'!$H$7,'TB & MCC Cost Audit 2020-Curren'!$D:$D,'TB All Check'!$G$7) -> 0 | J64: =SUMIFS('2023 Rev - NS'!$N:$N,'2023 Rev - NS'!$G:$G,'TB All Check'!$H64,'2023 Rev - NS'!$P:$P,'TB All Check'!$H$7) -> 0 | K64: =I64-J64 -> 0 | M64: Midland | N64: Midland, City of | O64: =SUMIFS('TB & MCC Cost Audit 2020-Curren'!$P:$P,'TB & MCC Cost Audit 2020-Curren'!$A:$A,'TB All Check'!$M64,'TB & MCC Cost Audit 2020-Curren'!$C:$C,'TB All Check'!$N$7,'TB & MCC Cost Audit 2020-Curren'!$D:$D,'TB All Check'!$M$7) -> 0 | P64: =SUMIFS('2024 Rev - NS'!$N:$N,'2024 Rev - NS'!$G:$G,'TB All Check'!$N64,'2024 Rev - NS'!$P:$P,'TB All Check'!$N$7) -> 0 | Q64: =P64-O64 -> 0
A65: Milcrofton | B65: Milcrofton Utility District | C65: =SUMIFS('TB & MCC Cost Audit 2020-Curren'!$P:$P,'TB & MCC Cost Audit 2020-Curren'!$A:$A,'TB All Check'!$A65,'TB & MCC Cost Audit 2020-Curren'!$C:$C,'TB All Check'!$B$7,'TB & MCC Cost Audit 2020-Curren'!$D:$D,'TB All Check'!$A$7) -> 0 | D65: =SUMIFS('2022 Partial Rev - NS'!$N:$N,'2022 Partial Rev - NS'!$G:$G,'TB All Check'!$B65,'2022 Partial Rev - NS'!$P:$P,'TB All Check'!$B$7) -> 0 | E65: =C65-D65 -> 0 | G65: Milcrofton | H65: Milcrofton Utility District | I65: =SUMIFS('TB & MCC Cost Audit 2020-Curren'!$P:$P,'TB & MCC Cost Audit 2020-Curren'!$A:$A,'TB All Check'!$A65,'TB & MCC Cost Audit 2020-Curren'!$C:$C,'TB All Check'!$H$7,'TB & MCC Cost Audit 2020-Curren'!$D:$D,'TB All Check'!$G$7) -> 0 | J65: =SUMIFS('2023 Rev - NS'!$N:$N,'2023 Rev - NS'!$G:$G,'TB All Check'!$H65,'2023 Rev - NS'!$P:$P,'TB All Check'!$H$7) -> 0 | K65: =I65-J65 -> 0 | M65: Milcrofton | N65: Milcrofton Utility District | O65: =SUMIFS('TB & MCC Cost Audit 2020-Curren'!$P:$P,'TB & MCC Cost Audit 2020-Curren'!$A:$A,'TB All Check'!$M65,'TB & MCC Cost Audit 2020-Curren'!$C:$C,'TB All Check'!$N$7,'TB & MCC Cost Audit 2020-Curren'!$D:$D,'TB All Check'!$M$7) -> 13028 | P65: =SUMIFS('2024 Rev - NS'!$N:$N,'2024 Rev - NS'!$G:$G,'TB All Check'!$N65,'2024 Rev - NS'!$P:$P,'TB All Check'!$N$7) -> 13028 | Q65: =P65-O65 -> 0
A66: Milwaukee | B66: Milwaukee, City of | C66: =SUMIFS('TB & MCC Cost Audit 2020-Curren'!$P:$P,'TB & MCC Cost Audit 2020-Curren'!$A:$A,'TB All Check'!$A66,'TB & MCC Cost Audit 2020-Curren'!$C:$C,'TB All Check'!$B$7,'TB & MCC Cost Audit 2020-Curren'!$D:$D,'TB All Check'!$A$7) -> 63364 | D66: =SUMIFS('2022 Partial Rev - NS'!$N:$N,'2022 Partial Rev - NS'!$G:$G,'TB All Check'!$B66,'2022 Partial Rev - NS'!$P:$P,'TB All Check'!$B$7) -> 63364 | E66: =C66-D66 -> 0 | G66: Milwaukee | H66: Milwaukee, City of | I66: =SUMIFS('TB & MCC Cost Audit 2020-Curren'!$P:$P,'TB & MCC Cost Audit 2020-Curren'!$A:$A,'TB All Check'!$A66,'TB & MCC Cost Audit 2020-Curren'!$C:$C,'TB All Check'!$H$7,'TB & MCC Cost Audit 2020-Curren'!$D:$D,'TB All Check'!$G$7) -> 0 | J66: =SUMIFS('2023 Rev - NS'!$N:$N,'2023 Rev - NS'!$G:$G,'TB All Check'!$H66,'2023 Rev - NS'!$P:$P,'TB All Check'!$H$7) -> 0 | K66: =I66-J66 -> 0 | M66: Milwaukee | N66: Milwaukee, City of | O66: =SUMIFS('TB & MCC Cost Audit 2020-Curren'!$P:$P,'TB & MCC Cost Audit 2020-Curren'!$A:$A,'TB All Check'!$M66,'TB & MCC Cost Audit 2020-Curren'!$C:$C,'TB All Check'!$N$7,'TB & MCC Cost Audit 2020-Curren'!$D:$D,'TB All Check'!$M$7) -> 63364 | P66: =SUMIFS('2024 Rev - NS'!$N:$N,'2024 Rev - NS'!$G:$G,'TB All Check'!$N66,'2024 Rev - NS'!$P:$P,'TB All Check'!$N$7) -> 63364 | Q66: =P66-O66 -> 0
A67: Mobile | B67: Mobile Area Water & Sewer System | C67: =SUMIFS('TB & MCC Cost Audit 2020-Curren'!$P:$P,'TB & MCC Cost Audit 2020-Curren'!$A:$A,'TB All Check'!$A67,'TB & MCC Cost Audit 2020-Curren'!$C:$C,'TB All Check'!$B$7,'TB & MCC Cost Audit 2020-Curren'!$D:$D,'TB All Check'!$A$7) -> 0 | D67: =SUMIFS('2022 Partial Rev - NS'!$N:$N,'2022 Partial Rev - NS'!$G:$G,'TB All Check'!$B67,'2022 Partial Rev - NS'!$P:$P,'TB All Check'!$B$7) -> 0 | E67: =C67-D67 -> 0 | G67: Mobile | H67: Mobile Area Water & Sewer System | I67: =SUMIFS('TB & MCC Cost Audit 2020-Curren'!$P:$P,'TB & MCC Cost Audit 2020-Curren'!$A:$A,'TB All Check'!$A67,'TB & MCC Cost Audit 2020-Curren'!$C:$C,'TB All Check'!$H$7,'TB & MCC Cost Audit 2020-Curren'!$D:$D,'TB All Check'!$G$7) -> 0 | J67: =SUMIFS('2023 Rev - NS'!$N:$N,'2023 Rev - NS'!$G:$G,'TB All Check'!$H67,'2023 Rev - NS'!$P:$P,'TB All Check'!$H$7) -> 0 | K67: =I67-J67 -> 0 | M67: Mobile | N67: Mobile Area Water & Sewer System | O67: =SUMIFS('TB & MCC Cost Audit 2020-Curren'!$P:$P,'TB & MCC Cost Audit 2020-Curren'!$A:$A,'TB All Check'!$M67,'TB & MCC Cost Audit 2020-Curren'!$C:$C,'TB All Check'!$N$7,'TB & MCC Cost Audit 2020-Curren'!$D:$D,'TB All Check'!$M$7) -> 12896 | P67: =SUMIFS('2024 Rev - NS'!$N:$N,'2024 Rev - NS'!$G:$G,'TB All Check'!$N67,'2024 Rev - NS'!$P:$P,'TB All Check'!$N$7) -> 12896 | Q67: =P67-O67 -> 0
A68: Mt Pleasant | B68: Mount Pleasant Waterworks | C68: =SUMIFS('TB & MCC Cost Audit 2020-Curren'!$P:$P,'TB & MCC Cost Audit 2020-Curren'!$A:$A,'TB All Check'!$A68,'TB & MCC Cost Audit 2020-Curren'!$C:$C,'TB All Check'!$B$7,'TB & MCC Cost Audit 2020-Curren'!$D:$D,'TB All Check'!$A$7) -> 0 | D68: =SUMIFS('2022 Partial Rev - NS'!$N:$N,'2022 Partial Rev - NS'!$G:$G,'TB All Check'!$B68,'2022 Partial Rev - NS'!$P:$P,'TB All Check'!$B$7) -> 0 | E68: =C68-D68 -> 0 | G68: Mt Pleasant | H68: Mount Pleasant Waterworks | I68: =SUMIFS('TB & MCC Cost Audit 2020-Curren'!$P:$P,'TB & MCC Cost Audit 2020-Curren'!$A:$A,'TB All Check'!$A68,'TB & MCC Cost Audit 2020-Curren'!$C:$C,'TB All Check'!$H$7,'TB & MCC Cost Audit 2020-Curren'!$D:$D,'TB All Check'!$G$7) -> 0 | J68: =SUMIFS('2023 Rev - NS'!$N:$N,'2023 Rev - NS'!$G:$G,'TB All Check'!$H68,'2023 Rev - NS'!$P:$P,'TB All Check'!$H$7) -> 0 | K68: =I68-J68 -> 0 | M68: Mt Pleasant | N68: Mount Pleasant Waterworks | O68: =SUMIFS('TB & MCC Cost Audit 2020-Curren'!$P:$P,'TB & MCC Cost Audit 2020-Curren'!$A:$A,'TB All Check'!$M68,'TB & MCC Cost Audit 2020-Curren'!$C:$C,'TB All Check'!$N$7,'TB & MCC Cost Audit 2020-Curren'!$D:$D,'TB All Check'!$M$7) -> 13607 | P68: =SUMIFS('2024 Rev - NS'!$N:$N,'2024 Rev - NS'!$G:$G,'TB All Check'!$N68,'2024 Rev - NS'!$P:$P,'TB All Check'!$N$7) -> 13607 | Q68: =P68-O68 -> 0
A69: Newport News | B69: Newport News, City of | C69: =SUMIFS('TB & MCC Cost Audit 2020-Curren'!$P:$P,'TB & MCC Cost Audit 2020-Curren'!$A:$A,'TB All Check'!$A69,'TB & MCC Cost Audit 2020-Curren'!$C:$C,'TB All Check'!$B$7,'TB & MCC Cost Audit 2020-Curren'!$D:$D,'TB All Check'!$A$7) -> 0 | D69: =SUMIFS('2022 Partial Rev - NS'!$N:$N,'2022 Partial Rev - NS'!$G:$G,'TB All Check'!$B69,'2022 Partial Rev - NS'!$P:$P,'TB All Check'!$B$7) -> 0 | E69: =C69-D69 -> 0 | G69: Newport News | H69: Newport News, City of | I69: =SUMIFS('TB & MCC Cost Audit 2020-Curren'!$P:$P,'TB & MCC Cost Audit 2020-Curren'!$A:$A,'TB All Check'!$A69,'TB & MCC Cost Audit 2020-Curren'!$C:$C,'TB All Check'!$H$7,'TB & MCC Cost Audit 2020-Curren'!$D:$D,'TB All Check'!$G$7) -> 0 | J69: =SUMIFS('2023 Rev - NS'!$N:$N,'2023 Rev - NS'!$G:$G,'TB All Check'!$H69,'2023 Rev - NS'!$P:$P,'TB All Check'!$H$7) -> 0 | K69: =I69-J69 -> 0 | M69: Newport News | N69: Newport News, City of | O69: =SUMIFS('TB & MCC Cost Audit 2020-Curren'!$P:$P,'TB & MCC Cost Audit 2020-Curren'!$A:$A,'TB All Check'!$M69,'TB & MCC Cost Audit 2020-Curren'!$C:$C,'TB All Check'!$N$7,'TB & MCC Cost Audit 2020-Curren'!$D:$D,'TB All Check'!$M$7) -> 26696 | P69: =SUMIFS('2024 Rev - NS'!$N:$N,'2024 Rev - NS'!$G:$G,'TB All Check'!$N69,'2024 Rev - NS'!$P:$P,'TB All Check'!$N$7) -> 26696 | Q69: =P69-O69 -> 0
A70: North City | B70: North City Water District | C70: =SUMIFS('TB & MCC Cost Audit 2020-Curren'!$P:$P,'TB & MCC Cost Audit 2020-Curren'!$A:$A,'TB All Check'!$A70,'TB & MCC Cost Audit 2020-Curren'!$C:$C,'TB All Check'!$B$7,'TB & MCC Cost Audit 2020-Curren'!$D:$D,'TB All Check'!$A$7) -> 0 | D70: =SUMIFS('2022 Partial Rev - NS'!$N:$N,'2022 Partial Rev - NS'!$G:$G,'TB All Check'!$B70,'2022 Partial Rev - NS'!$P:$P,'TB All Check'!$B$7) -> 0 | E70: =C70-D70 -> 0 | G70: North City | H70: North City Water District | I70: =SUMIFS('TB & MCC Cost Audit 2020-Curren'!$P:$P,'TB & MCC Cost Audit 2020-Curren'!$A:$A,'TB All Check'!$A70,'TB & MCC Cost Audit 2020-Curren'!$C:$C,'TB All Check'!$H$7,'TB & MCC Cost Audit 2020-Curren'!$D:$D,'TB All Check'!$G$7) -> 0 | J70: =SUMIFS('2023 Rev - NS'!$N:$N,'2023 Rev - NS'!$G:$G,'TB All Check'!$H70,'2023 Rev - NS'!$P:$P,'TB All Check'!$H$7) -> 0 | K70: =I70-J70 -> 0 | M70: North City | N70: North City Water District | O70: =SUMIFS('TB & MCC Cost Audit 2020-Curren'!$P:$P,'TB & MCC Cost Audit 2020-Curren'!$A:$A,'TB All Check'!$M70,'TB & MCC Cost Audit 2020-Curren'!$C:$C,'TB All Check'!$N$7,'TB & MCC Cost Audit 2020-Curren'!$D:$D,'TB All Check'!$M$7) -> 0 | P70: =SUMIFS('2024 Rev - NS'!$N:$N,'2024 Rev - NS'!$G:$G,'TB All Check'!$N70,'2024 Rev - NS'!$P:$P,'TB All Check'!$N$7) -> 0 | Q70: =P70-O70 -> 0
A71: North Marin Water District | B71: North Marin Water District | C71: =SUMIFS('TB & MCC Cost Audit 2020-Curren'!$P:$P,'TB & MCC Cost Audit 2020-Curren'!$A:$A,'TB All Check'!$A71,'TB & MCC Cost Audit 2020-Curren'!$C:$C,'TB All Check'!$B$7,'TB & MCC Cost Audit 2020-Curren'!$D:$D,'TB All Check'!$A$7) -> 0 | D71: =SUMIFS('2022 Partial Rev - NS'!$N:$N,'2022 Partial Rev - NS'!$G:$G,'TB All Check'!$B71,'2022 Partial Rev - NS'!$P:$P,'TB All Check'!$B$7) -> 0 | E71: =C71-D71 -> 0 | G71: North Marin Water District | H71: North Marin Water District | I71: =SUMIFS('TB & MCC Cost Audit 2020-Curren'!$P:$P,'TB & MCC Cost Audit 2020-Curren'!$A:$A,'TB All Check'!$A71,'TB & MCC Cost Audit 2020-Curren'!$C:$C,'TB All Check'!$H$7,'TB & MCC Cost Audit 2020-Curren'!$D:$D,'TB All Check'!$G$7) -> 0 | J71: =SUMIFS('2023 Rev - NS'!$N:$N,'2023 Rev - NS'!$G:$G,'TB All Check'!$H71,'2023 Rev - NS'!$P:$P,'TB All Check'!$H$7) -> 0 | K71: =I71-J71 -> 0 | M71: North Marin Water District | N71: North Marin Water District | O71: =SUMIFS('TB & MCC Cost Audit 2020-Curren'!$P:$P,'TB & MCC Cost Audit 2020-Curren'!$A:$A,'TB All Check'!$M71,'TB & MCC Cost Audit 2020-Curren'!$C:$C,'TB All Check'!$N$7,'TB & MCC Cost Audit 2020-Curren'!$D:$D,'TB All Check'!$M$7) -> 0 | P71: =SUMIFS('2024 Rev - NS'!$N:$N,'2024 Rev - NS'!$G:$G,'TB All Check'!$N71,'2024 Rev - NS'!$P:$P,'TB All Check'!$N$7) -> 0 | Q71: =P71-O71 -> 0
A72: North Penn | B72: North Penn Water Authority | C72: =SUMIFS('TB & MCC Cost Audit 2020-Curren'!$P:$P,'TB & MCC Cost Audit 2020-Curren'!$A:$A,'TB All Check'!$A72,'TB & MCC Cost Audit 2020-Curren'!$C:$C,'TB All Check'!$B$7,'TB & MCC Cost Audit 2020-Curren'!$D:$D,'TB All Check'!$A$7) -> 10572 | D72: =SUMIFS('2022 Partial Rev - NS'!$N:$N,'2022 Partial Rev - NS'!$G:$G,'TB All Check'!$B72,'2022 Partial Rev - NS'!$P:$P,'TB All Check'!$B$7) -> 10572 | E72: =C72-D72 -> 0 | G72: North Penn | H72: North Penn Water Authority | I72: =SUMIFS('TB & MCC Cost Audit 2020-Curren'!$P:$P,'TB & MCC Cost Audit 2020-Curren'!$A:$A,'TB All Check'!$A72,'TB & MCC Cost Audit 2020-Curren'!$C:$C,'TB All Check'!$H$7,'TB & MCC Cost Audit 2020-Curren'!$D:$D,'TB All Check'!$G$7) -> 0 | J72: =SUMIFS('2023 Rev - NS'!$N:$N,'2023 Rev - NS'!$G:$G,'TB All Check'!$H72,'2023 Rev - NS'!$P:$P,'TB All Check'!$H$7) -> 0 | K72: =I72-J72 -> 0 | M72: North Penn | N72: North Penn Water Authority | O72: =SUMIFS('TB & MCC Cost Audit 2020-Curren'!$P:$P,'TB & MCC Cost Audit 2020-Curren'!$A:$A,'TB All Check'!$M72,'TB & MCC Cost Audit 2020-Curren'!$C:$C,'TB All Check'!$N$7,'TB & MCC Cost Audit 2020-Curren'!$D:$D,'TB All Check'!$M$7) -> 12218 | P72: =SUMIFS('2024 Rev - NS'!$N:$N,'2024 Rev - NS'!$G:$G,'TB All Check'!$N72,'2024 Rev - NS'!$P:$P,'TB All Check'!$N$7) -> 12218 | Q72: =P72-O72 -> 0
A73: OCWA | B73: Onondaga County Water Authority | C73: =SUMIFS('TB & MCC Cost Audit 2020-Curren'!$P:$P,'TB & MCC Cost Audit 2020-Curren'!$A:$A,'TB All Check'!$A73,'TB & MCC Cost Audit 2020-Curren'!$C:$C,'TB All Check'!$B$7,'TB & MCC Cost Audit 2020-Curren'!$D:$D,'TB All Check'!$A$7) -> 19860.61 | D73: =SUMIFS('2022 Partial Rev - NS'!$N:$N,'2022 Partial Rev - NS'!$G:$G,'TB All Check'!$B73,'2022 Partial Rev - NS'!$P:$P,'TB All Check'!$B$7) -> 0 | E73: =C73-D73 -> 19860.61 | G73: OCWA | H73: Onondaga County Water Authority | I73: =SUMIFS('TB & MCC Cost Audit 2020-Curren'!$P:$P,'TB & MCC Cost Audit 2020-Curren'!$A:$A,'TB All Check'!$A73,'TB & MCC Cost Audit 2020-Curren'!$C:$C,'TB All Check'!$H$7,'TB & MCC Cost Audit 2020-Curren'!$D:$D,'TB All Check'!$G$7) -> 0 | J73: =SUMIFS('2023 Rev - NS'!$N:$N,'2023 Rev - NS'!$G:$G,'TB All Check'!$H73,'2023 Rev - NS'!$P:$P,'TB All Check'!$H$7) -> 0 | K73: =I73-J73 -> 0 | M73: OCWA | N73: Onondaga County Water Authority | O73: =SUMIFS('TB & MCC Cost Audit 2020-Curren'!$P:$P,'TB & MCC Cost Audit 2020-Curren'!$A:$A,'TB All Check'!$M73,'TB & MCC Cost Audit 2020-Curren'!$C:$C,'TB All Check'!$N$7,'TB & MCC Cost Audit 2020-Curren'!$D:$D,'TB All Check'!$M$7) -> 29439 | P73: =SUMIFS('2024 Rev - NS'!$N:$N,'2024 Rev - NS'!$G:$G,'TB All Check'!$N73,'2024 Rev - NS'!$P:$P,'TB All Check'!$N$7) -> 29439 | Q73: =P73-O73 -> 0
A74: ORWA | B74: Oklahoma Rural Water Association | C74: =SUMIFS('TB & MCC Cost Audit 2020-Curren'!$P:$P,'TB & MCC Cost Audit 2020-Curren'!$A:$A,'TB All Check'!$A74,'TB & MCC Cost Audit 2020-Curren'!$C:$C,'TB All Check'!$B$7,'TB & MCC Cost Audit 2020-Curren'!$D:$D,'TB All Check'!$A$7) -> 0 | D74: =SUMIFS('2022 Partial Rev - NS'!$N:$N,'2022 Partial Rev - NS'!$G:$G,'TB All Check'!$B74,'2022 Partial Rev - NS'!$P:$P,'TB All Check'!$B$7) -> 0 | E74: =C74-D74 -> 0 | G74: ORWA | H74: Oklahoma Rural Water Association | I74: =SUMIFS('TB & MCC Cost Audit 2020-Curren'!$P:$P,'TB & MCC Cost Audit 2020-Curren'!$A:$A,'TB All Check'!$A74,'TB & MCC Cost Audit 2020-Curren'!$C:$C,'TB All Check'!$H$7,'TB & MCC Cost Audit 2020-Curren'!$D:$D,'TB All Check'!$G$7) -> 0 | J74: =SUMIFS('2023 Rev - NS'!$N:$N,'2023 Rev - NS'!$G:$G,'TB All Check'!$H74,'2023 Rev - NS'!$P:$P,'TB All Check'!$H$7) -> 0 | K74: =I74-J74 -> 0 | M74: ORWA | N74: Oklahoma Rural Water Association | O74: =SUMIFS('TB & MCC Cost Audit 2020-Curren'!$P:$P,'TB & MCC Cost Audit 2020-Curren'!$A:$A,'TB All Check'!$M74,'TB & MCC Cost Audit 2020-Curren'!$C:$C,'TB All Check'!$N$7,'TB & MCC Cost Audit 2020-Curren'!$D:$D,'TB All Check'!$M$7) -> 8865 | P74: =SUMIFS('2024 Rev - NS'!$N:$N,'2024 Rev - NS'!$G:$G,'TB All Check'!$N74,'2024 Rev - NS'!$P:$P,'TB All Check'!$N$7) -> 8865 | Q74: =P74-O74 -> 0
... A102: WSSC | B102: Washington Suburban Sanitation Commission | C102: =SUMIFS('TB & MCC Cost Audit 2020-Curren'!$P:$P,'TB & MCC Cost Audit 2020-Curren'!$A:$A,'TB All Check'!$A102,'TB & MCC Cost Audit 2020-Curren'!$C:$C,'TB All Check'!$B$7,'TB & MCC Cost Audit 2020-Curren'!$D:$D,'TB All Check'!$A$7) -> 0 | D102: =SUMIFS('2022 Partial Rev - NS'!$N:$N,'2022 Partial Rev - NS'!$G:$G,'TB All Check'!$B102,'2022 Partial Rev - NS'!$P:$P,'TB All Check'!$B$7) -> 0 | E102: =C102-D102 -> 0 | G102: WSSC | H102: Washington Suburban Sanitation Commission | I102: =SUMIFS('TB & MCC Cost Audit 2020-Curren'!$P:$P,'TB & MCC Cost Audit 2020-Curren'!$A:$A,'TB All Check'!$A102,'TB & MCC Cost Audit 2020-Curren'!$C:$C,'TB All Check'!$H$7,'TB & MCC Cost Audit 2020-Curren'!$D:$D,'TB All Check'!$G$7) -> 0 | J102: =SUMIFS('2023 Rev - NS'!$N:$N,'2023 Rev - NS'!$G:$G,'TB All Check'!$H102,'2023 Rev - NS'!$P:$P,'TB All Check'!$H$7) -> 0 | K102: =I102-J102 -> 0 | M102: WSSC | N102: Washington Suburban Sanitation Commission | O102: =SUMIFS('TB & MCC Cost Audit 2020-Curren'!$P:$P,'TB & MCC Cost Audit 2020-Curren'!$A:$A,'TB All Check'!$M102,'TB & MCC Cost Audit 2020-Curren'!$C:$C,'TB All Check'!$N$7,'TB & MCC Cost Audit 2020-Curren'!$D:$D,'TB All Check'!$M$7) -> 53179 | P102: =SUMIFS('2024 Rev - NS'!$N:$N,'2024 Rev - NS'!$G:$G,'TB All Check'!$N102,'2024 Rev - NS'!$P:$P,'TB All Check'!$N$7) -> 53179 | Q102: =P102-O102 -> 0

Sheet 2022 Partial Rev - NS
A1: Internal ID | B1: Date Created | C1: Period | D1: Status | E1: Type | F1: Document Number | G1: Top Level Parent | H1: Customer - Parent | I1: Account | J1: Class | K1: Item | L1: Item Description | M1: Quantity | N1: Total Revenue
A2: 658 | B2: 44616.699 | C2: Jul 2014 | D2: Approved for Posting | E2: Journal | F2: JE45 | I2: 4011 Test Bench Equipment : Test Bench Equipment - New | N2: 140882.16 | O2: =EOMONTH(B2,0) -> 44620 | P2: TBEN
A3: 658 | B3: 44616.699 | C3: Jul 2014 | D3: Approved for Posting | E3: Journal | F3: JE45 | I3: 4074 Test Bench Other | N3: 5500 | O3: =EOMONTH(B3,0) -> 44620
A4: 659 | B4: 44616.699 | C4: Aug 2014 | D4: Approved for Posting | E4: Journal | F4: JE46 | I4: 4011 Test Bench Equipment : Test Bench Equipment - New | N4: 129589.91 | O4: =EOMONTH(B4,0) -> 44620 | P4: TBEN
A5: 659 | B5: 44616.699 | C5: Aug 2014 | D5: Approved for Posting | E5: Journal | F5: JE46 | I5: 4101 MCC Services : MCC Services - Contracted | N5: 20580 | O5: =EOMONTH(B5,0) -> 44620 | P5: MCC
A6: 660 | B6: 44616.699 | C6: Sep 2014 | D6: Approved for Posting | E6: Journal | F6: JE47 | I6: 4074 Test Bench Other | N6: 71373.12 | O6: =EOMONTH(B6,0) -> 44620
A7: 660 | B7: 44616.699 | C7: Sep 2014 | D7: Approved for Posting | E7: Journal | F7: JE47 | I7: 4011 Test Bench Equipment : Test Bench Equipment - New | N7: 49832.22 | O7: =EOMONTH(B7,0) -> 44620 | P7: TBEN
A8: 660 | B8: 44616.699 | C8: Sep 2014 | D8: Approved for Posting | E8: Journal | F8: JE47 | I8: 4101 MCC Services : MCC Services - Contracted | N8: 10275 | O8: =EOMONTH(B8,0) -> 44620 | P8: MCC
A9: 661 | B9: 44616.7 | C9: Oct 2014 | D9: Approved for Posting | E9: Journal | F9: JE48 | I9: 4011 Test Bench Equipment : Test Bench Equipment - New | N9: 38500 | O9: =EOMONTH(B9,0) -> 44620 | P9: TBEN
A10: 661 | B10: 44616.7 | C10: Oct 2014 | D10: Approved for Posting | E10: Journal | F10: JE48 | I10: 4101 MCC Services : MCC Services - Contracted | N10: 1303.3 | O10: =EOMONTH(B10,0) -> 44620 | P10: MCC
A11: 758 | B11: 44616.704 | C11: Dec 2014 | D11: Approved for Posting | E11: Journal | F11: JE50 | I11: 4101 MCC Services : MCC Services - Contracted | N11: 61408 | O11: =EOMONTH(B11,0) -> 44620 | P11: MCC
A12: 758 | B12: 44616.704 | C12: Dec 2014 | D12: Approved for Posting | E12: Journal | F12: JE50 | I12: 4074 Test Bench Other | N12: 6500 | O12: =EOMONTH(B12,0) -> 44620
A13: 859 | B13: 44616.728 | C13: Jan 2015 | D13: Approved for Posting | E13: Journal | F13: JE51 | I13: 4101 MCC Services : MCC Services - Contracted | N13: 8450 | O13: =EOMONTH(B13,0) -> 44620 | P13: MCC
A14: 859 | B14: 44616.728 | C14: Jan 2015 | D14: Approved for Posting | E14: Journal | F14: JE51 | I14: 4074 Test Bench Other | N14: 27.77 | O14: =EOMONTH(B14,0) -> 44620
A15: 859 | B15: 44616.728 | C15: Jan 2015 | D15: Approved for Posting | E15: Journal | F15: JE51 | I15: 4013 Test Bench Equipment : Project Mgmt | N15: -505.6 | O15: =EOMONTH(B15,0) -> 44620 | P15: PM
A16: 860 | B16: 44616.728 | C16: Feb 2015 | D16: Approved for Posting | E16: Journal | F16: JE52 | I16: 4011 Test Bench Equipment : Test Bench Equipment - New | N16: 60887.41 | O16: =EOMONTH(B16,0) -> 44620 | P16: TBEN
A17: 860 | B17: 44616.728 | C17: Feb 2015 | D17: Approved for Posting | E17: Journal | F17: JE52 | I17: 4101 MCC Services : MCC Services - Contracted | N17: 7450 | O17: =EOMONTH(B17,0) -> 44620 | P17: MCC
A18: 861 | B18: 44616.728 | C18: Mar 2015 | D18: Approved for Posting | E18: Journal | F18: JE53 | I18: 4074 Test Bench Other | N18: 9999.99 | O18: =EOMONTH(B18,0) -> 44620
A19: 861 | B19: 44616.728 | C19: Mar 2015 | D19: Approved for Posting | E19: Journal | F19: JE53 | I19: 4101 MCC Services : MCC Services - Contracted | N19: 4500 | O19: =EOMONTH(B19,0) -> 44620 | P19: MCC
A20: 861 | B20: 44616.728 | C20: Mar 2015 | D20: Approved for Posting | E20: Journal | F20: JE53 | I20: 4013 Test Bench Equipment : Project Mgmt | N20: 505.6 | O20: =EOMONTH(B20,0) -> 44620 | P20: PM
A21: 862 | B21: 44616.728 | C21: Apr 2015 | D21: Approved for Posting | E21: Journal | F21: JE54 | I21: 4031 TB Install & Training - New | N21: 61050 | O21: =EOMONTH(B21,0) -> 44620 | P21: TBIN
A22: 862 | B22: 44616.728 | C22: Apr 2015 | D22: Approved for Posting | E22: Journal | F22: JE54 | I22: 4074 Test Bench Other | N22: 53984.15 | O22: =EOMONTH(B22,0) -> 44620
A23: 862 | B23: 44616.728 | C23: Apr 2015 | D23: Approved for Posting | E23: Journal | F23: JE54 | I23: 4011 Test Bench Equipment : Test Bench Equipment - New | N23: 44112.86 | O23: =EOMONTH(B23,0) -> 44620 | P23: TBEN
A24: 862 | B24: 44616.728 | C24: Apr 2015 | D24: Approved for Posting | E24: Journal | F24: JE54 | I24: 4021 Test Bench Components | N24: 4132.04 | O24: =EOMONTH(B24,0) -> 44620 | P24: TBCO
A25: 863 | B25: 44616.728 | C25: May 2015 | D25: Approved for Posting | E25: Journal | F25: JE55 | I25: 4074 Test Bench Other | N25: 34334.65 | O25: =EOMONTH(B25,0) -> 44620
A26: 863 | B26: 44616.728 | C26: May 2015 | D26: Approved for Posting | E26: Journal | F26: JE55 | I26: 4021 Test Bench Components | N26: 15386.24 | O26: =EOMONTH(B26,0) -> 44620 | P26: TBCO
A27: 863 | B27: 44616.728 | C27: May 2015 | D27: Approved for Posting | E27: Journal | F27: JE55 | I27: 4101 MCC Services : MCC Services - Contracted | N27: 7000 | O27: =EOMONTH(B27,0) -> 44620 | P27: MCC
A28: 864 | B28: 44616.728 | C28: Jun 2015 | D28: Approved for Posting | E28: Journal | F28: JE56 | I28: 4011 Test Bench Equipment : Test Bench Equipment - New | N28: 28611.61 | O28: =EOMONTH(B28,0) -> 44620 | P28: TBEN
A29: 864 | B29: 44616.728 | C29: Jun 2015 | D29: Approved for Posting | E29: Journal | F29: JE56 | I29: 4101 MCC Services : MCC Services - Contracted | N29: 8500 | O29: =EOMONTH(B29,0) -> 44620 | P29: MCC
A30: 864 | B30: 44616.728 | C30: Jun 2015 | D30: Approved for Posting | E30: Journal | F30: JE56 | I30: 4021 Test Bench Components | N30: 2787.94 | O30: =EOMONTH(B30,0) -> 44620 | P30: TBCO
A31: 864 | B31: 44616.728 | C31: Jun 2015 | D31: Approved for Posting | E31: Journal | F31: JE56 | I31: 4074 Test Bench Other | N31: 2715 | O31: =EOMONTH(B31,0) -> 44620
A32: 865 | B32: 44616.728 | C32: Jul 2015 | D32: Approved for Posting | E32: Journal | F32: JE57 | I32: 4074 Test Bench Other | N32: 100322.23 | O32: =EOMONTH(B32,0) -> 44620
A33: 865 | B33: 44616.728 | C33: Jul 2015 | D33: Approved for Posting | E33: Journal | F33: JE57 | I33: 4011 Test Bench Equipment : Test Bench Equipment - New | N33: 66810.21 | O33: =EOMONTH(B33,0) -> 44620 | P33: TBEN
